Workbook

Sheet Intro
B3: 🟡 Celdas amarillas = INPUTS | H3: 🔵 / 🔴 Outputs (según hoja)
B5: Son las únicas que deberían modificar: | H5: P&L
H6: EBITDA
B7: Pricing (precios / promos) | H7: Caja
B8: DDI / surtido | H8: Alertas
B9: Mix digital
B10: Estrategia logística | H10: 👉 Son el resultado de las decisiones.
B11: Inversión en marketing
B12: Aperturas / cierres (si aplica)
B14: 👉 Representan decisiones estratégicas reales.
B17: 🧠 2. CÓMO FUNCIONA EL SIMULADOR
B19: El modelo replica un negocio real con 5 motores:
B21: 1. 💰 Pricing
B22: 2. 🛒 Surtido / DDI
B23: 3. 📲 Canal Digital
B24: 4. 🚚 Logística
B25: 5. 👤 Clientes (CLV)
B27: Todas sus decisiones impactan en:
B29: 👉 P&L + Flujo de Caja + Riesgo del negocio
B33: ⚙️ 4. QUÉ DECISIONES PUEDEN TOMAR
B37: 💰 Pricing | E37: 🛒 Surtido & DDI | I37: 📲 Canal Digital | L37: 🚚 Logística | O37: 👤 Clientes (CLV)
B39: Subir / bajar precios | E39: Reducir SKUs | I39: % ventas digitales | L39: Modelo fulfillment | O39: Inversión en adquisición vs retención
E40: Ajustar días de inventario | I40: Mix delivery vs pick-up | L40: Nivel de servicio (SLA)
O41: 👉 Impacta:
B42: 👉 Impacta: | E42: 👉 Impacta: | I42: 👉 Impacta: | L42: 👉 Impacta:
O43: frecuencia
B44: volumen | E44: ventas | I44: crecimiento | L44: costo por pedido | O44: churn
B45: margen | E45: capital de trabajo | I45: costos logísticos | L45: experiencia cliente | O45: revenue futuro
E46: quiebres de stock
B50: 💸 5. CÓMO LEER LOS RESULTADOS
B54: 📊 P&L | D54: 💸 Flujo de Caja (CLAVE) | H54: 🚨 Alertas | J54: 🧠 Score de Consistencia
B56: Revenue | D56: EBITDA | H56: Caja negativa | J56: Evalúa si su estrategia tiene sentido:
B57: Margen | D57: Capital de trabajo | H57: CAPEX excedido
B58: EBITDA | D58: CAPEX | J58: pricing vs posicionamiento
J59: surtido vs eficiencia
B60: 👉 Mide rentabilidad | D60: 👉 Mide supervivencia | J60: digital vs logística

Sheet 00_General
B2: PharmaLink 360 - Simulador Integrado de Turnaround Retail & Omnicanalidad
B4: Variable | C4: Valor | E4: Objetivos del caso
B5: Horizonte del simulador | C5: 12 meses | E5: 1 | F5: Construir presupuesto anual de 12 meses
B6: Mes de inicio | C6: Mes 1 | E6: 2 | F6: Diseñar Plan 100 días con quick wins accionables
B7: KPI madre | C7: EBITDA ajustado por Cost-to-Serve + sostenibilidad de caja | E7: 3 | F7: Maximizar EBITDA ajustado por Cost-to-Serve
B8: Punto de partida | C8: Resultado operativo positivo / flujo de caja negativo | E8: 4 | F8: Revertir flujo de caja negativo sin destruir la red
B9: PDV Base | C9: 120
B10: Ventas Mes 0 (ARS MM) | C10: 29984.5 | E10: 5 | F10: Defender decisiones con datos de los simuladores
B11: EBITDA Mes 0 (ARS MM) | C11: 881.125 | D11: =+C11/C10 -> 0.029386016
B12: Caja inicial Mes 0 (ARS MM) | C12: -25000 | E12: Hard constraints
B13: Inventario inicial (ARS MM) | C13: 60000 | E13: CAPEX | F13: No superar presupuesto total
B14: DDI inicial ponderado | C14: 62 | E14: Caja | F14: No más de 3 meses seguidos de FCF negativo
B15: CAPEX máximo (ARS MM) | C15: 50000
B16: Máx. meses consecutivos de FCF negativo | C16: 3
B17: Inflación mensual costos | C17: 0.04
B18: Factor IPC + personal/alquileres | C18: 0.02
B19: FX referencia ARS/USD | C19: 1000

Sheet 01_Master_Variables
B3: Master Variables - capa de integracion unica hacia P&L y Caja
B5: Variable | C5: Mes 0 | D5: Mes 1 | E5: Mes 2 | F5: Mes 3 | G5: Mes 4 | H5: Mes 5 | I5: Mes 6 | J5: Mes 7 | K5: Mes 8 | L5: Mes 9 | M5: Mes 10 | N5: Mes 11 | O5: Mes 12 | P5: TOTAL
B6: Revenue simulado | C6: ='00_General'!C10 -> 29984.5 | D6: =+'03_CatMan_DDI'!D69+'06_Red_CAPEX'!E73+'05_CLV_Marketing'!D50 -> 29368.464 | E6: =+'03_CatMan_DDI'!E69+'06_Red_CAPEX'!F73+'05_CLV_Marketing'!E50 -> 28959.999 | F6: =+'03_CatMan_DDI'!F69+'06_Red_CAPEX'!G73+'05_CLV_Marketing'!F50 -> 29137.949 | G6: =+'03_CatMan_DDI'!G69+'06_Red_CAPEX'!H73+'05_CLV_Marketing'!G50 -> 28569.856 | H6: =+'03_CatMan_DDI'!H69+'06_Red_CAPEX'!I73+'05_CLV_Marketing'!H50 -> 28037.177 | I6: =+'03_CatMan_DDI'!I69+'06_Red_CAPEX'!J73+'05_CLV_Marketing'!I50 -> 28060.276 | J6: =+'03_CatMan_DDI'!J69+'06_Red_CAPEX'!K73+'05_CLV_Marketing'!J50 -> 28257.162 | K6: =+'03_CatMan_DDI'!K69+'06_Red_CAPEX'!L73+'05_CLV_Marketing'!K50 -> 28340.977 | ... O6: =+'03_CatMan_DDI'!O69+'06_Red_CAPEX'!P73+'05_CLV_Marketing'!O50 -> 29507.551 | P6: =SUM(D6:O6) -> 344699.21
B7: Margen bruto % | C7: ='02_Pricing'!I18 -> 0.34171106 | D7: ='02_Pricing'!I18 -> 0.34171106 | E7: ='02_Pricing'!I18 -> 0.34171106 | F7: ='02_Pricing'!I18 -> 0.34171106 | G7: ='02_Pricing'!I18 -> 0.34171106 | H7: ='02_Pricing'!I18 -> 0.34171106 | I7: ='02_Pricing'!I18 -> 0.34171106 | J7: ='02_Pricing'!I18 -> 0.34171106 | K7: ='02_Pricing'!I18 -> 0.34171106 | L7: ='02_Pricing'!I18 -> 0.34171106 | M7: ='02_Pricing'!I18 -> 0.34171106 | N7: ='02_Pricing'!I18 -> 0.34171106 | O7: ='02_Pricing'!I18 -> 0.34171106 | P7: =+P8/P6 -> 0.34171106
B8: Margen bruto | C8: =C6*C7 -> 10246.035 | D8: =D6*D7 -> 10035.529 | E8: =E6*E7 -> 9895.9517 | F8: =F6*F7 -> 9956.7595 | G8: =G6*G7 -> 9762.6358 | H8: =H6*H7 -> 9580.6135 | I8: =I6*I7 -> 9588.5067 | J8: =J6*J7 -> 9655.7847 | ... O8: =O6*O7 -> 10083.057 | P8: =SUM(D8:O8) -> 117787.53
B9: Penetracion digital target | C9: =SUM('04_Digital_Logistica'!C8:C10) -> 0.15643549 | D9: =SUM('04_Digital_Logistica'!D8:D10) -> 0.16719977 | E9: =SUM('04_Digital_Logistica'!E8:E10) -> 0.16772445 | F9: =SUM('04_Digital_Logistica'!F8:F10) -> 0.16749406 | G9: =SUM('04_Digital_Logistica'!G8:G10) -> 0.1682396 | H9: =SUM('04_Digital_Logistica'!H8:H10) -> 0.16896612 | I9: =SUM('04_Digital_Logistica'!I8:I10) -> 0.18755467 | J9: =SUM('04_Digital_Logistica'!J8:J10) -> 0.18715365 | ... P9: =SUM('04_Digital_Logistica'!P8:P10) -> 0.26
B10: Costo logistico | C10: =+'04_Digital_Logistica'!C20 -> 1031.4813 | D10: =+'04_Digital_Logistica'!D20 -> 1020.6711 | E10: =+'04_Digital_Logistica'!E20 -> 1007.539 | F10: =+'04_Digital_Logistica'!F20 -> 1013.2601 | G10: =+'04_Digital_Logistica'!G20 -> 994.99588 | H10: =+'04_Digital_Logistica'!H20 -> 977.87025 | I10: =+'04_Digital_Logistica'!I20 -> 1015.1879 | J10: =+'04_Digital_Logistica'!J20 -> 1021.5178 | ... O10: =+'04_Digital_Logistica'!O20 -> 1171.4428 | P10: =SUM(D10:O10) -> 12584.98
B11: Inventario | C11: =+'03_CatMan_DDI'!C86 -> 41385.114 | D11: =+'03_CatMan_DDI'!D86 -> 35902.136 | E11: =+'03_CatMan_DDI'!E86 -> 35902.136 | F11: =+'03_CatMan_DDI'!F86 -> 35902.136 | G11: =+'03_CatMan_DDI'!G86 -> 35902.136 | H11: =+'03_CatMan_DDI'!H86 -> 35902.136 | I11: =+'03_CatMan_DDI'!I86 -> 35902.136 | J11: =+'03_CatMan_DDI'!J86 -> 35902.136 | ... O11: =+'03_CatMan_DDI'!O86 -> 35902.136 | Q11: Considera que baja a DDI obj en el mes 2 , porque multiplica por 65%
B12: Liberacion / absorcion WC | D12: =C11-D11 -> 5482.9781 | E12: =D11-E11 -> 0 | F12: =E11-F11 -> 0 | G12: =F11-G11 -> 0 | H12: =G11-H11 -> 0 | I12: =H11-I11 -> 0 | J12: =I11-J11 -> 0 | K12: =J11-K11 -> 0 | ... O12: =N11-O11 -> 0 | P12: =SUM(D12:O12) -> 5482.9781
B13: Marketing | C13: =+D13 -> 265.41118 | D13: =+'05_CLV_Marketing'!D57 -> 265.41118 | E13: =+'05_CLV_Marketing'!E57 -> 302.15039 | F13: =+'05_CLV_Marketing'!F57 -> 335.49743 | G13: =+'05_CLV_Marketing'!G57 -> 365.71247 | H13: =+'05_CLV_Marketing'!H57 -> 393.03734 | I13: =+'05_CLV_Marketing'!I57 -> 417.69673 | J13: =+'05_CLV_Marketing'!J57 -> 439.89941 | K13: =+'05_CLV_Marketing'!K57 -> 459.83924 | ... P13: =+'05_CLV_Marketing'!P57 -> 4978.7755
B14: CAPEX | C14: =+'06_Red_CAPEX'!D87 -> 0 | D14: =+'06_Red_CAPEX'!E87 -> 0 | E14: =+'06_Red_CAPEX'!F87 -> 0 | F14: =+'06_Red_CAPEX'!G87 -> 5833.3333 | G14: =+'06_Red_CAPEX'!H87 -> 0 | H14: =+'06_Red_CAPEX'!I87 -> 0 | I14: =+'06_Red_CAPEX'!J87 -> 4400 | J14: =+'06_Red_CAPEX'!K87 -> 5833.3333 | ... P14: =+'06_Red_CAPEX'!Q87 -> 35100
B15: Competitividad | C15: =+'02_Pricing'!C104 -> 100 | D15: =+'02_Pricing'!D104 -> 100 | E15: =+'02_Pricing'!E104 -> 100 | F15: =+'02_Pricing'!F104 -> 100 | G15: =+'02_Pricing'!G104 -> 100 | H15: =+'02_Pricing'!H104 -> 100 | I15: =+'02_Pricing'!I104 -> 100 | J15: =+'02_Pricing'!J104 -> 100 | ... O15: =+'02_Pricing'!O104 -> 100 | P15: =+'06_Red_CAPEX'!Q88 -> 0

Sheet 02_Pricing
B3: Simulador 1 - Pricing & Elasticidad
B5: Categoria | C5: PVP Base | D5: Costo Unitario Base | E5: Vol PDV Base | F5: Ventas Base Mes 0 (ARS MM) | G5: Costo Base Mes 0 (ARS MM) | H5: Vol Base Mes 0 (Units) | I5: Margen % Base | J5: Elasticidad
B6: Medicamentos A | C6: 6617 | D6: 4800 | E6: 12600 | F6: =+C6*H6/1000000 -> 10004.904 | G6: =+D6*H6/1000000 -> 7257.6 | H6: =+E6*'00_General'!$C$9 -> 1512000 | I6: =+(F6-G6)/F6 -> 0.27459574 | J6: -0.3
B7: Nutricion | C7: 31266.154 | D7: 21260.985 | E7: 400 | F7: =+C7*H7/1000000 -> 1500.7754 | G7: =+D7*H7/1000000 -> 1020.5273 | H7: =+E7*'00_General'!$C$9 -> 48000 | I7: =+(F7-G7)/F7 -> 0.32 | J7: -1.1
B8: Parafarmacia | C8: 15159.347 | D8: 9853.5759 | E8: 1100 | F8: =+C8*H8/1000000 -> 2001.0339 | G8: =+D8*H8/1000000 -> 1300.672 | H8: =+E8*'00_General'!$C$9 -> 132000 | I8: =+(F8-G8)/F8 -> 0.35 | J8: -1
B9: Suplementos | C9: 20844.103 | D9: 12923.344 | E9: 700 | F9: =+C9*H9/1000000 -> 1750.9046 | G9: =+D9*H9/1000000 -> 1085.5609 | H9: =+E9*'00_General'!$C$9 -> 84000 | I9: =+(F9-G9)/F9 -> 0.38 | J9: -1.3
B10: Venta Libre | C10: 6948.0343 | D10: 4585.7026 | E10: 4500 | F10: =+C10*H10/1000000 -> 3751.9385 | G10: =+D10*H10/1000000 -> 2476.2794 | H10: =+E10*'00_General'!$C$9 -> 540000 | I10: =+(F10-G10)/F10 -> 0.34 | J10: -0.7
B11: Cuidado Bucal | C11: 4737.2961 | D11: 3268.7343 | E11: 2200 | F11: =+C11*H11/1000000 -> 1250.6462 | G11: =+D11*H11/1000000 -> 862.94586 | H11: =+E11*'00_General'!$C$9 -> 264000 | I11: =+(F11-G11)/F11 -> 0.31 | J11: -1.1
B12: Cuidado Piel | C12: 8527.133 | D12: 4945.7371 | E12: 2200 | F12: =+C12*H12/1000000 -> 2251.1631 | G12: =+D12*H12/1000000 -> 1305.6746 | H12: =+E12*'00_General'!$C$9 -> 264000 | I12: =+(F12-G12)/F12 -> 0.42 | J12: -1.2
B13: Bebe y Mama | C13: 12506.462 | D13: 8379.3293 | E13: 750 | F13: =+C13*H13/1000000 -> 1125.5816 | G13: =+D13*H13/1000000 -> 754.13964 | H13: =+E13*'00_General'!$C$9 -> 90000 | I13: =+(F13-G13)/F13 -> 0.33 | J13: -0.8
B14: Cuidado Cabello | C14: 3821.4188 | D14: 2445.7081 | E14: 3000 | F14: =+C14*H14/1000000 -> 1375.7108 | G14: =+D14*H14/1000000 -> 880.4549 | H14: =+E14*'00_General'!$C$9 -> 360000 | I14: =+(F14-G14)/F14 -> 0.36 | J14: -1.25
B15: Cuidado Personal | C15: 1908.2629 | D15: 1240.3709 | E15: 7100 | F15: =+C15*H15/1000000 -> 1625.84 | G15: =+D15*H15/1000000 -> 1056.796 | H15: =+E15*'00_General'!$C$9 -> 852000 | I15: =+(F15-G15)/F15 -> 0.35 | J15: -1.15
B16: Dermocosmetica | C16: 40014.722 | D16: 20807.655 | E16: 700 | F16: =+C16*H16/1000000 -> 3361.2366 | G16: =+D16*H16/1000000 -> 1747.8431 | H16: =+E16*'00_General'!$C$9 -> 84000 | I16: =+(F16-G16)/F16 -> 0.48 | J16: -1.4
B18: TOTAL | E18: =SUM(E6:E16) -> 35250 | F18: =SUM(F6:F16) -> 29999.735 | G18: =SUM(G6:G16) -> 19748.494 | H18: =SUM(H6:H16) -> 4230000 | I18: =+(F18-G18)/F18 -> 0.34171106
H19: =+F18*1000000/H18 -> 7092.1359
B21: Cambio PVP %
B23: Categoria | C23: Mes 0 | D23: Mes 1 | E23: Mes 2 | F23: Mes 3 | G23: Mes 4 | H23: Mes 5 | I23: Mes 6 | J23: Mes 7 | K23: Mes 8 | L23: Mes 9 | M23: Mes 10 | N23: Mes 11 | O23: Mes 12
B24: Medicamentos | D24: 0 | E24: 0 | F24: 0 | G24: 0 | H24: 0 | I24: 0 | J24: 0 | K24: 0 | L24: 0 | M24: 0 | N24: 0 | O24: 0
B25: Nutricion | D25: 0 | E25: 0 | F25: 0 | G25: 0 | H25: 0 | I25: 0 | J25: 0 | K25: 0 | L25: 0 | M25: 0 | N25: 0 | O25: 0
B26: Parafarmacia | D26: 0 | E26: 0 | F26: 0 | G26: 0 | H26: 0 | I26: 0 | J26: 0 | K26: 0 | L26: 0 | M26: 0 | N26: 0 | O26: 0
B27: Suplementos | D27: 0 | E27: 0 | F27: 0 | G27: 0 | H27: 0 | I27: 0 | J27: 0 | K27: 0 | L27: 0 | M27: 0 | N27: 0 | O27: 0
B28: Venta Libre | D28: 0 | E28: 0 | F28: 0 | G28: 0 | H28: 0 | I28: 0 | J28: 0 | K28: 0 | L28: 0 | M28: 0 | N28: 0 | O28: 0
B29: Cuidado Bucal | D29: 0 | E29: 0 | F29: 0 | G29: 0 | H29: 0 | I29: 0 | J29: 0 | K29: 0 | L29: 0 | M29: 0 | N29: 0 | O29: 0
B30: Cuidado Piel | D30: 0 | E30: 0 | F30: 0 | G30: 0 | H30: 0 | I30: 0 | J30: 0 | K30: 0 | L30: 0 | M30: 0 | N30: 0 | O30: 0
B31: Bebe y Mama | D31: 0 | E31: 0 | F31: 0 | G31: 0 | H31: 0 | I31: 0 | J31: 0 | K31: 0 | L31: 0 | M31: 0 | N31: 0 | O31: 0
B32: Cuidado Cabello | D32: 0 | E32: 0 | F32: 0 | G32: 0 | H32: 0 | I32: 0 | J32: 0 | K32: 0 | L32: 0 | M32: 0 | N32: 0 | O32: 0
B33: Cuidado Personal | D33: 0 | E33: 0 | F33: 0 | G33: 0 | H33: 0 | I33: 0 | J33: 0 | K33: 0 | L33: 0 | M33: 0 | N33: 0 | O33: 0
B34: Dermocosmetica | D34: 0 | E34: 0 | F34: 0 | G34: 0 | H34: 0 | I34: 0 | J34: 0 | K34: 0 | L34: 0 | M34: 0 | N34: 0 | O34: 0
B36: TOTAL / POND.
B38: Revenue Simulado
B40: Categoria | C40: Mes 0 | D40: Mes 1 | E40: Mes 2 | F40: Mes 3 | G40: Mes 4 | H40: Mes 5 | I40: Mes 6 | J40: Mes 7 | K40: Mes 8 | L40: Mes 9 | M40: Mes 10 | N40: Mes 11 | O40: Mes 12
B41: Medicamentos | C41: =+F6 -> 10004.904 | D41: =+(($H$6*(1+$J$6*$D$24))*($C$6*(1+$D$24)))/1000000 -> 10004.904 | E41: =+(($H6*(1+$J6*E24))*($C6*(1+E24)))/1000000 -> 10004.904 | F41: =+(($H6*(1+$J6*F24))*($C6*(1+F24)))/1000000 -> 10004.904 | G41: =+(($H6*(1+$J6*G24))*($C6*(1+G24)))/1000000 -> 10004.904 | H41: =+(($H6*(1+$J6*H24))*($C6*(1+H24)))/1000000 -> 10004.904 | I41: =+(($H6*(1+$J6*I24))*($C6*(1+I24)))/1000000 -> 10004.904 | J41: =+(($H6*(1+$J6*J24))*($C6*(1+J24)))/1000000 -> 10004.904 | K41: =+(($H6*(1+$J6*K24))*($C6*(1+K24)))/1000000 -> 10004.904 | L41: =+(($H6*(1+$J6*L24))*($C6*(1+L24)))/1000000 -> 10004.904 | ... O41: =+(($H6*(1+$J6*O24))*($C6*(1+O24)))/1000000 -> 10004.904
B42: Nutricion | C42: =+F7 -> 1500.7754 | D42: =+(($H7*(1+$J7*D25))*($C7*(1+D25)))/1000000 -> 1500.7754 | E42: =+(($H7*(1+$J7*E25))*($C7*(1+E25)))/1000000 -> 1500.7754 | F42: =+(($H7*(1+$J7*F25))*($C7*(1+F25)))/1000000 -> 1500.7754 | G42: =+(($H7*(1+$J7*G25))*($C7*(1+G25)))/1000000 -> 1500.7754 | H42: =+(($H7*(1+$J7*H25))*($C7*(1+H25)))/1000000 -> 1500.7754 | I42: =+(($H7*(1+$J7*I25))*($C7*(1+I25)))/1000000 -> 1500.7754 | J42: =+(($H7*(1+$J7*J25))*($C7*(1+J25)))/1000000 -> 1500.7754 | K42: =+(($H7*(1+$J7*K25))*($C7*(1+K25)))/1000000 -> 1500.7754 | ... O42: =+(($H7*(1+$J7*O25))*($C7*(1+O25)))/1000000 -> 1500.7754
B43: Parafarmacia | C43: =+F8 -> 2001.0339 | D43: =+(($H8*(1+$J8*D26))*($C8*(1+D26)))/1000000 -> 2001.0339 | E43: =+(($H8*(1+$J8*E26))*($C8*(1+E26)))/1000000 -> 2001.0339 | F43: =+(($H8*(1+$J8*F26))*($C8*(1+F26)))/1000000 -> 2001.0339 | G43: =+(($H8*(1+$J8*G26))*($C8*(1+G26)))/1000000 -> 2001.0339 | H43: =+(($H8*(1+$J8*H26))*($C8*(1+H26)))/1000000 -> 2001.0339 | I43: =+(($H8*(1+$J8*I26))*($C8*(1+I26)))/1000000 -> 2001.0339 | J43: =+(($H8*(1+$J8*J26))*($C8*(1+J26)))/1000000 -> 2001.0339 | K43: =+(($H8*(1+$J8*K26))*($C8*(1+K26)))/1000000 -> 2001.0339 | ... O43: =+(($H8*(1+$J8*O26))*($C8*(1+O26)))/1000000 -> 2001.0339
B44: Suplementos | C44: =+F9 -> 1750.9046 | D44: =+(($H9*(1+$J9*D27))*($C9*(1+D27)))/1000000 -> 1750.9046 | E44: =+(($H9*(1+$J9*E27))*($C9*(1+E27)))/1000000 -> 1750.9046 | F44: =+(($H9*(1+$J9*F27))*($C9*(1+F27)))/1000000 -> 1750.9046 | G44: =+(($H9*(1+$J9*G27))*($C9*(1+G27)))/1000000 -> 1750.9046 | H44: =+(($H9*(1+$J9*H27))*($C9*(1+H27)))/1000000 -> 1750.9046 | I44: =+(($H9*(1+$J9*I27))*($C9*(1+I27)))/1000000 -> 1750.9046 | J44: =+(($H9*(1+$J9*J27))*($C9*(1+J27)))/1000000 -> 1750.9046 | K44: =+(($H9*(1+$J9*K27))*($C9*(1+K27)))/1000000 -> 1750.9046 | ... O44: =+(($H9*(1+$J9*O27))*($C9*(1+O27)))/1000000 -> 1750.9046
B45: Venta Libre | C45: =+F10 -> 3751.9385 | D45: =+(($H10*(1+$J10*D28))*($C10*(1+D28)))/1000000 -> 3751.9385 | E45: =+(($H10*(1+$J10*E28))*($C10*(1+E28)))/1000000 -> 3751.9385 | F45: =+(($H10*(1+$J10*F28))*($C10*(1+F28)))/1000000 -> 3751.9385 | G45: =+(($H10*(1+$J10*G28))*($C10*(1+G28)))/1000000 -> 3751.9385 | H45: =+(($H10*(1+$J10*H28))*($C10*(1+H28)))/1000000 -> 3751.9385 | I45: =+(($H10*(1+$J10*I28))*($C10*(1+I28)))/1000000 -> 3751.9385 | J45: =+(($H10*(1+$J10*J28))*($C10*(1+J28)))/1000000 -> 3751.9385 | K45: =+(($H10*(1+$J10*K28))*($C10*(1+K28)))/1000000 -> 3751.9385 | ... O45: =+(($H10*(1+$J10*O28))*($C10*(1+O28)))/1000000 -> 3751.9385
B46: Cuidado Bucal | C46: =+F11 -> 1250.6462 | D46: =+(($H11*(1+$J11*D29))*($C11*(1+D29)))/1000000 -> 1250.6462 | E46: =+(($H11*(1+$J11*E29))*($C11*(1+E29)))/1000000 -> 1250.6462 | F46: =+(($H11*(1+$J11*F29))*($C11*(1+F29)))/1000000 -> 1250.6462 | G46: =+(($H11*(1+$J11*G29))*($C11*(1+G29)))/1000000 -> 1250.6462 | H46: =+(($H11*(1+$J11*H29))*($C11*(1+H29)))/1000000 -> 1250.6462 | I46: =+(($H11*(1+$J11*I29))*($C11*(1+I29)))/1000000 -> 1250.6462 | J46: =+(($H11*(1+$J11*J29))*($C11*(1+J29)))/1000000 -> 1250.6462 | K46: =+(($H11*(1+$J11*K29))*($C11*(1+K29)))/1000000 -> 1250.6462 | ... O46: =+(($H11*(1+$J11*O29))*($C11*(1+O29)))/1000000 -> 1250.6462
B47: Cuidado Piel | C47: =+F12 -> 2251.1631 | D47: =+(($H12*(1+$J12*D30))*($C12*(1+D30)))/1000000 -> 2251.1631 | E47: =+(($H12*(1+$J12*E30))*($C12*(1+E30)))/1000000 -> 2251.1631 | F47: =+(($H12*(1+$J12*F30))*($C12*(1+F30)))/1000000 -> 2251.1631 | G47: =+(($H12*(1+$J12*G30))*($C12*(1+G30)))/1000000 -> 2251.1631 | H47: =+(($H12*(1+$J12*H30))*($C12*(1+H30)))/1000000 -> 2251.1631 | I47: =+(($H12*(1+$J12*I30))*($C12*(1+I30)))/1000000 -> 2251.1631 | J47: =+(($H12*(1+$J12*J30))*($C12*(1+J30)))/1000000 -> 2251.1631 | K47: =+(($H12*(1+$J12*K30))*($C12*(1+K30)))/1000000 -> 2251.1631 | ... O47: =+(($H12*(1+$J12*O30))*($C12*(1+O30)))/1000000 -> 2251.1631
B48: Bebe y Mama | C48: =+F13 -> 1125.5816 | D48: =+(($H13*(1+$J13*D31))*($C13*(1+D31)))/1000000 -> 1125.5816 | E48: =+(($H13*(1+$J13*E31))*($C13*(1+E31)))/1000000 -> 1125.5816 | F48: =+(($H13*(1+$J13*F31))*($C13*(1+F31)))/1000000 -> 1125.5816 | G48: =+(($H13*(1+$J13*G31))*($C13*(1+G31)))/1000000 -> 1125.5816 | H48: =+(($H13*(1+$J13*H31))*($C13*(1+H31)))/1000000 -> 1125.5816 | I48: =+(($H13*(1+$J13*I31))*($C13*(1+I31)))/1000000 -> 1125.5816 | J48: =+(($H13*(1+$J13*J31))*($C13*(1+J31)))/1000000 -> 1125.5816 | K48: =+(($H13*(1+$J13*K31))*($C13*(1+K31)))/1000000 -> 1125.5816 | ... O48: =+(($H13*(1+$J13*O31))*($C13*(1+O31)))/1000000 -> 1125.5816
B49: Cuidado Cabello | C49: =+F14 -> 1375.7108 | D49: =+(($H14*(1+$J14*D32))*($C14*(1+D32)))/1000000 -> 1375.7108 | E49: =+(($H14*(1+$J14*E32))*($C14*(1+E32)))/1000000 -> 1375.7108 | F49: =+(($H14*(1+$J14*F32))*($C14*(1+F32)))/1000000 -> 1375.7108 | G49: =+(($H14*(1+$J14*G32))*($C14*(1+G32)))/1000000 -> 1375.7108 | H49: =+(($H14*(1+$J14*H32))*($C14*(1+H32)))/1000000 -> 1375.7108 | I49: =+(($H14*(1+$J14*I32))*($C14*(1+I32)))/1000000 -> 1375.7108 | J49: =+(($H14*(1+$J14*J32))*($C14*(1+J32)))/1000000 -> 1375.7108 | K49: =+(($H14*(1+$J14*K32))*($C14*(1+K32)))/1000000 -> 1375.7108 | ... O49: =+(($H14*(1+$J14*O32))*($C14*(1+O32)))/1000000 -> 1375.7108
B50: Cuidado Personal | C50: =+F15 -> 1625.84 | D50: =+(($H15*(1+$J15*D33))*($C15*(1+D33)))/1000000 -> 1625.84 | E50: =+(($H15*(1+$J15*E33))*($C15*(1+E33)))/1000000 -> 1625.84 | F50: =+(($H15*(1+$J15*F33))*($C15*(1+F33)))/1000000 -> 1625.84 | G50: =+(($H15*(1+$J15*G33))*($C15*(1+G33)))/1000000 -> 1625.84 | H50: =+(($H15*(1+$J15*H33))*($C15*(1+H33)))/1000000 -> 1625.84 | I50: =+(($H15*(1+$J15*I33))*($C15*(1+I33)))/1000000 -> 1625.84 | J50: =+(($H15*(1+$J15*J33))*($C15*(1+J33)))/1000000 -> 1625.84 | K50: =+(($H15*(1+$J15*K33))*($C15*(1+K33)))/1000000 -> 1625.84 | ... O50: =+(($H15*(1+$J15*O33))*($C15*(1+O33)))/1000000 -> 1625.84
B51: Dermocosmetica | C51: =+F16 -> 3361.2366 | D51: =+(($H16*(1+$J16*D34))*($C16*(1+D34)))/1000000 -> 3361.2366 | E51: =+(($H16*(1+$J16*E34))*($C16*(1+E34)))/1000000 -> 3361.2366 | F51: =+(($H16*(1+$J16*F34))*($C16*(1+F34)))/1000000 -> 3361.2366 | G51: =+(($H16*(1+$J16*G34))*($C16*(1+G34)))/1000000 -> 3361.2366 | H51: =+(($H16*(1+$J16*H34))*($C16*(1+H34)))/1000000 -> 3361.2366 | I51: =+(($H16*(1+$J16*I34))*($C16*(1+I34)))/1000000 -> 3361.2366 | J51: =+(($H16*(1+$J16*J34))*($C16*(1+J34)))/1000000 -> 3361.2366 | K51: =+(($H16*(1+$J16*K34))*($C16*(1+K34)))/1000000 -> 3361.2366 | ... O51: =+(($H16*(1+$J16*O34))*($C16*(1+O34)))/1000000 -> 3361.2366
B53: TOTAL / POND. | C53: =SUM(C41:C51) -> 29999.735 | D53: =SUM(D41:D51) -> 29999.735 | E53: =SUM(E41:E51) -> 29999.735 | F53: =SUM(F41:F51) -> 29999.735 | G53: =SUM(G41:G51) -> 29999.735 | H53: =SUM(H41:H51) -> 29999.735 | I53: =SUM(I41:I51) -> 29999.735 | J53: =SUM(J41:J51) -> 29999.735 | ... O53: =SUM(O41:O51) -> 29999.735
B55: Margen Bruto Simulado
B57: Categoria | C57: Mes 0 | D57: Mes 1 | E57: Mes 2 | F57: Mes 3 | G57: Mes 4 | H57: Mes 5 | I57: Mes 6 | J57: Mes 7 | K57: Mes 8 | L57: Mes 9 | M57: Mes 10 | N57: Mes 11 | O57: Mes 12
B58: Medicamentos | C58: =+(($H6*(1+$J6*C24))*($C6*(1+C24)-$D6))/1000000 -> 2747.304 | D58: =+(($H6*(1+$J6*D24))*($C6*(1+D24)-$D6))/1000000 -> 2747.304 | E58: =+(($H6*(1+$J6*E24))*($C6*(1+E24)-$D6))/1000000 -> 2747.304 | F58: =+(($H6*(1+$J6*F24))*($C6*(1+F24)-$D6))/1000000 -> 2747.304 | G58: =+(($H6*(1+$J6*G24))*($C6*(1+G24)-$D6))/1000000 -> 2747.304 | H58: =+(($H6*(1+$J6*H24))*($C6*(1+H24)-$D6))/1000000 -> 2747.304 | I58: =+(($H6*(1+$J6*I24))*($C6*(1+I24)-$D6))/1000000 -> 2747.304 | J58: =+(($H6*(1+$J6*J24))*($C6*(1+J24)-$D6))/1000000 -> 2747.304 | ... O58: =+(($H6*(1+$J6*O24))*($C6*(1+O24)-$D6))/1000000 -> 2747.304
B59: Nutricion | C59: =+(($H7*(1+$J7*C25))*($C7*(1+C25)-$D7))/1000000 -> 480.24813 | D59: =+(($H7*(1+$J7*D25))*($C7*(1+D25)-$D7))/1000000 -> 480.24813 | E59: =+(($H7*(1+$J7*E25))*($C7*(1+E25)-$D7))/1000000 -> 480.24813 | F59: =+(($H7*(1+$J7*F25))*($C7*(1+F25)-$D7))/1000000 -> 480.24813 | G59: =+(($H7*(1+$J7*G25))*($C7*(1+G25)-$D7))/1000000 -> 480.24813 | H59: =+(($H7*(1+$J7*H25))*($C7*(1+H25)-$D7))/1000000 -> 480.24813 | I59: =+(($H7*(1+$J7*I25))*($C7*(1+I25)-$D7))/1000000 -> 480.24813 | J59: =+(($H7*(1+$J7*J25))*($C7*(1+J25)-$D7))/1000000 -> 480.24813 | ... O59: =+(($H7*(1+$J7*O25))*($C7*(1+O25)-$D7))/1000000 -> 480.24813
B60: Parafarmacia | C60: =+(($H8*(1+$J8*C26))*($C8*(1+C26)-$D8))/1000000 -> 700.36185 | D60: =+(($H8*(1+$J8*D26))*($C8*(1+D26)-$D8))/1000000 -> 700.36185 | E60: =+(($H8*(1+$J8*E26))*($C8*(1+E26)-$D8))/1000000 -> 700.36185 | F60: =+(($H8*(1+$J8*F26))*($C8*(1+F26)-$D8))/1000000 -> 700.36185 | G60: =+(($H8*(1+$J8*G26))*($C8*(1+G26)-$D8))/1000000 -> 700.36185 | H60: =+(($H8*(1+$J8*H26))*($C8*(1+H26)-$D8))/1000000 -> 700.36185 | I60: =+(($H8*(1+$J8*I26))*($C8*(1+I26)-$D8))/1000000 -> 700.36185 | J60: =+(($H8*(1+$J8*J26))*($C8*(1+J26)-$D8))/1000000 -> 700.36185 | ... O60: =+(($H8*(1+$J8*O26))*($C8*(1+O26)-$D8))/1000000 -> 700.36185
B61: Suplementos | C61: =+(($H9*(1+$J9*C27))*($C9*(1+C27)-$D9))/1000000 -> 665.34376 | D61: =+(($H9*(1+$J9*D27))*($C9*(1+D27)-$D9))/1000000 -> 665.34376 | E61: =+(($H9*(1+$J9*E27))*($C9*(1+E27)-$D9))/1000000 -> 665.34376 | F61: =+(($H9*(1+$J9*F27))*($C9*(1+F27)-$D9))/1000000 -> 665.34376 | G61: =+(($H9*(1+$J9*G27))*($C9*(1+G27)-$D9))/1000000 -> 665.34376 | H61: =+(($H9*(1+$J9*H27))*($C9*(1+H27)-$D9))/1000000 -> 665.34376 | I61: =+(($H9*(1+$J9*I27))*($C9*(1+I27)-$D9))/1000000 -> 665.34376 | J61: =+(($H9*(1+$J9*J27))*($C9*(1+J27)-$D9))/1000000 -> 665.34376 | ... O61: =+(($H9*(1+$J9*O27))*($C9*(1+O27)-$D9))/1000000 -> 665.34376
B62: Venta Libre | C62: =+(($H10*(1+$J10*C28))*($C10*(1+C28)-$D10))/1000000 -> 1275.6591 | D62: =+(($H10*(1+$J10*D28))*($C10*(1+D28)-$D10))/1000000 -> 1275.6591 | E62: =+(($H10*(1+$J10*E28))*($C10*(1+E28)-$D10))/1000000 -> 1275.6591 | F62: =+(($H10*(1+$J10*F28))*($C10*(1+F28)-$D10))/1000000 -> 1275.6591 | G62: =+(($H10*(1+$J10*G28))*($C10*(1+G28)-$D10))/1000000 -> 1275.6591 | H62: =+(($H10*(1+$J10*H28))*($C10*(1+H28)-$D10))/1000000 -> 1275.6591 | I62: =+(($H10*(1+$J10*I28))*($C10*(1+I28)-$D10))/1000000 -> 1275.6591 | J62: =+(($H10*(1+$J10*J28))*($C10*(1+J28)-$D10))/1000000 -> 1275.6591 | ... O62: =+(($H10*(1+$J10*O28))*($C10*(1+O28)-$D10))/1000000 -> 1275.6591
B63: Cuidado Bucal | C63: =+(($H11*(1+$J11*C29))*($C11*(1+C29)-$D11))/1000000 -> 387.70031 | D63: =+(($H11*(1+$J11*D29))*($C11*(1+D29)-$D11))/1000000 -> 387.70031 | E63: =+(($H11*(1+$J11*E29))*($C11*(1+E29)-$D11))/1000000 -> 387.70031 | F63: =+(($H11*(1+$J11*F29))*($C11*(1+F29)-$D11))/1000000 -> 387.70031 | G63: =+(($H11*(1+$J11*G29))*($C11*(1+G29)-$D11))/1000000 -> 387.70031 | H63: =+(($H11*(1+$J11*H29))*($C11*(1+H29)-$D11))/1000000 -> 387.70031 | I63: =+(($H11*(1+$J11*I29))*($C11*(1+I29)-$D11))/1000000 -> 387.70031 | J63: =+(($H11*(1+$J11*J29))*($C11*(1+J29)-$D11))/1000000 -> 387.70031 | ... O63: =+(($H11*(1+$J11*O29))*($C11*(1+O29)-$D11))/1000000 -> 387.70031
B64: Cuidado Piel | C64: =+(($H12*(1+$J12*C30))*($C12*(1+C30)-$D12))/1000000 -> 945.4885 | D64: =+(($H12*(1+$J12*D30))*($C12*(1+D30)-$D12))/1000000 -> 945.4885 | E64: =+(($H12*(1+$J12*E30))*($C12*(1+E30)-$D12))/1000000 -> 945.4885 | F64: =+(($H12*(1+$J12*F30))*($C12*(1+F30)-$D12))/1000000 -> 945.4885 | G64: =+(($H12*(1+$J12*G30))*($C12*(1+G30)-$D12))/1000000 -> 945.4885 | H64: =+(($H12*(1+$J12*H30))*($C12*(1+H30)-$D12))/1000000 -> 945.4885 | I64: =+(($H12*(1+$J12*I30))*($C12*(1+I30)-$D12))/1000000 -> 945.4885 | J64: =+(($H12*(1+$J12*J30))*($C12*(1+J30)-$D12))/1000000 -> 945.4885 | ... O64: =+(($H12*(1+$J12*O30))*($C12*(1+O30)-$D12))/1000000 -> 945.4885
B65: Bebe y Mama | C65: =+(($H13*(1+$J13*C31))*($C13*(1+C31)-$D13))/1000000 -> 371.44191 | D65: =+(($H13*(1+$J13*D31))*($C13*(1+D31)-$D13))/1000000 -> 371.44191 | E65: =+(($H13*(1+$J13*E31))*($C13*(1+E31)-$D13))/1000000 -> 371.44191 | F65: =+(($H13*(1+$J13*F31))*($C13*(1+F31)-$D13))/1000000 -> 371.44191 | G65: =+(($H13*(1+$J13*G31))*($C13*(1+G31)-$D13))/1000000 -> 371.44191 | H65: =+(($H13*(1+$J13*H31))*($C13*(1+H31)-$D13))/1000000 -> 371.44191 | I65: =+(($H13*(1+$J13*I31))*($C13*(1+I31)-$D13))/1000000 -> 371.44191 | J65: =+(($H13*(1+$J13*J31))*($C13*(1+J31)-$D13))/1000000 -> 371.44191 | ... O65: =+(($H13*(1+$J13*O31))*($C13*(1+O31)-$D13))/1000000 -> 371.44191
B66: Cuidado Cabello | C66: =+(($H14*(1+$J14*C32))*($C14*(1+C32)-$D14))/1000000 -> 495.25588 | D66: =+(($H14*(1+$J14*D32))*($C14*(1+D32)-$D14))/1000000 -> 495.25588 | E66: =+(($H14*(1+$J14*E32))*($C14*(1+E32)-$D14))/1000000 -> 495.25588 | F66: =+(($H14*(1+$J14*F32))*($C14*(1+F32)-$D14))/1000000 -> 495.25588 | G66: =+(($H14*(1+$J14*G32))*($C14*(1+G32)-$D14))/1000000 -> 495.25588 | H66: =+(($H14*(1+$J14*H32))*($C14*(1+H32)-$D14))/1000000 -> 495.25588 | I66: =+(($H14*(1+$J14*I32))*($C14*(1+I32)-$D14))/1000000 -> 495.25588 | J66: =+(($H14*(1+$J14*J32))*($C14*(1+J32)-$D14))/1000000 -> 495.25588 | ... O66: =+(($H14*(1+$J14*O32))*($C14*(1+O32)-$D14))/1000000 -> 495.25588
B67: Cuidado Personal | C67: =+(($H15*(1+$J15*C33))*($C15*(1+C33)-$D15))/1000000 -> 569.04401 | D67: =+(($H15*(1+$J15*D33))*($C15*(1+D33)-$D15))/1000000 -> 569.04401 | E67: =+(($H15*(1+$J15*E33))*($C15*(1+E33)-$D15))/1000000 -> 569.04401 | F67: =+(($H15*(1+$J15*F33))*($C15*(1+F33)-$D15))/1000000 -> 569.04401 | G67: =+(($H15*(1+$J15*G33))*($C15*(1+G33)-$D15))/1000000 -> 569.04401 | H67: =+(($H15*(1+$J15*H33))*($C15*(1+H33)-$D15))/1000000 -> 569.04401 | I67: =+(($H15*(1+$J15*I33))*($C15*(1+I33)-$D15))/1000000 -> 569.04401 | J67: =+(($H15*(1+$J15*J33))*($C15*(1+J33)-$D15))/1000000 -> 569.04401 | ... O67: =+(($H15*(1+$J15*O33))*($C15*(1+O33)-$D15))/1000000 -> 569.04401
B68: Dermocosmetica | C68: =+(($H16*(1+$J16*C34))*($C16*(1+C34)-$D16))/1000000 -> 1613.3936 | D68: =+(($H16*(1+$J16*D34))*($C16*(1+D34)-$D16))/1000000 -> 1613.3936 | E68: =+(($H16*(1+$J16*E34))*($C16*(1+E34)-$D16))/1000000 -> 1613.3936 | F68: =+(($H16*(1+$J16*F34))*($C16*(1+F34)-$D16))/1000000 -> 1613.3936 | G68: =+(($H16*(1+$J16*G34))*($C16*(1+G34)-$D16))/1000000 -> 1613.3936 | H68: =+(($H16*(1+$J16*H34))*($C16*(1+H34)-$D16))/1000000 -> 1613.3936 | I68: =+(($H16*(1+$J16*I34))*($C16*(1+I34)-$D16))/1000000 -> 1613.3936 | J68: =+(($H16*(1+$J16*J34))*($C16*(1+J34)-$D16))/1000000 -> 1613.3936 | ... O68: =+(($H16*(1+$J16*O34))*($C16*(1+O34)-$D16))/1000000 -> 1613.3936
B70: TOTAL / POND. | C70: =SUM(C58:C68) -> 10251.241 | D70: =SUM(D58:D68) -> 10251.241 | E70: =SUM(E58:E68) -> 10251.241 | F70: =SUM(F58:F68) -> 10251.241 | G70: =SUM(G58:G68) -> 10251.241 | H70: =SUM(H58:H68) -> 10251.241 | I70: =SUM(I58:I68) -> 10251.241 | J70: =SUM(J58:J68) -> 10251.241 | ... O70: =SUM(O58:O68) -> 10251.241
B72: MB %
B74: Categoria | C74: Mes 0 | D74: Mes 1 | E74: Mes 2 | F74: Mes 3 | G74: Mes 4 | H74: Mes 5 | I74: Mes 6 | J74: Mes 7 | K74: Mes 8 | L74: Mes 9 | M74: Mes 10 | N74: Mes 11 | O74: Mes 12
B75: Medicamentos | C75: =+C58/C41 -> 0.27459574 | D75: =+D58/D41 -> 0.27459574 | E75: =+E58/E41 -> 0.27459574 | F75: =+F58/F41 -> 0.27459574 | G75: =+G58/G41 -> 0.27459574 | H75: =+H58/H41 -> 0.27459574 | I75: =+I58/I41 -> 0.27459574 | J75: =+J58/J41 -> 0.27459574 | ... O75: =+O58/O41 -> 0.27459574
B76: Nutricion | C76: =+C59/C42 -> 0.32 | D76: =+D59/D42 -> 0.32 | E76: =+E59/E42 -> 0.32 | F76: =+F59/F42 -> 0.32 | G76: =+G59/G42 -> 0.32 | H76: =+H59/H42 -> 0.32 | I76: =+I59/I42 -> 0.32 | J76: =+J59/J42 -> 0.32 | ... O76: =+O59/O42 -> 0.32
B77: Parafarmacia | C77: =+C60/C43 -> 0.35 | D77: =+D60/D43 -> 0.35 | E77: =+E60/E43 -> 0.35 | F77: =+F60/F43 -> 0.35 | G77: =+G60/G43 -> 0.35 | H77: =+H60/H43 -> 0.35 | I77: =+I60/I43 -> 0.35 | J77: =+J60/J43 -> 0.35 | ... O77: =+O60/O43 -> 0.35
B78: Suplementos | C78: =+C61/C44 -> 0.38 | D78: =+D61/D44 -> 0.38 | E78: =+E61/E44 -> 0.38 | F78: =+F61/F44 -> 0.38 | G78: =+G61/G44 -> 0.38 | H78: =+H61/H44 -> 0.38 | I78: =+I61/I44 -> 0.38 | J78: =+J61/J44 -> 0.38 | ... O78: =+O61/O44 -> 0.38
B79: Venta Libre | C79: =+C62/C45 -> 0.34 | D79: =+D62/D45 -> 0.34 | E79: =+E62/E45 -> 0.34 | F79: =+F62/F45 -> 0.34 | G79: =+G62/G45 -> 0.34 | H79: =+H62/H45 -> 0.34 | I79: =+I62/I45 -> 0.34 | J79: =+J62/J45 -> 0.34 | ... O79: =+O62/O45 -> 0.34
B80: Cuidado Bucal | C80: =+C63/C46 -> 0.31 | D80: =+D63/D46 -> 0.31 | E80: =+E63/E46 -> 0.31 | F80: =+F63/F46 -> 0.31 | G80: =+G63/G46 -> 0.31 | H80: =+H63/H46 -> 0.31 | I80: =+I63/I46 -> 0.31 | J80: =+J63/J46 -> 0.31 | ... O80: =+O63/O46 -> 0.31
B81: Cuidado Piel | C81: =+C64/C47 -> 0.42 | D81: =+D64/D47 -> 0.42 | E81: =+E64/E47 -> 0.42 | F81: =+F64/F47 -> 0.42 | G81: =+G64/G47 -> 0.42 | H81: =+H64/H47 -> 0.42 | I81: =+I64/I47 -> 0.42 | J81: =+J64/J47 -> 0.42 | ... O81: =+O64/O47 -> 0.42
B82: Bebe y Mama | C82: =+C65/C48 -> 0.33 | D82: =+D65/D48 -> 0.33 | E82: =+E65/E48 -> 0.33 | F82: =+F65/F48 -> 0.33 | G82: =+G65/G48 -> 0.33 | H82: =+H65/H48 -> 0.33 | I82: =+I65/I48 -> 0.33 | J82: =+J65/J48 -> 0.33 | ... O82: =+O65/O48 -> 0.33
B83: Cuidado Cabello | C83: =+C66/C49 -> 0.36 | D83: =+D66/D49 -> 0.36 | E83: =+E66/E49 -> 0.36 | F83: =+F66/F49 -> 0.36 | G83: =+G66/G49 -> 0.36 | H83: =+H66/H49 -> 0.36 | I83: =+I66/I49 -> 0.36 | J83: =+J66/J49 -> 0.36 | ... O83: =+O66/O49 -> 0.36
B84: Cuidado Personal | C84: =+C67/C50 -> 0.35 | D84: =+D67/D50 -> 0.35 | E84: =+E67/E50 -> 0.35 | F84: =+F67/F50 -> 0.35 | G84: =+G67/G50 -> 0.35 | H84: =+H67/H50 -> 0.35 | I84: =+I67/I50 -> 0.35 | J84: =+J67/J50 -> 0.35 | ... O84: =+O67/O50 -> 0.35
B85: Dermocosmetica | C85: =+C68/C51 -> 0.48 | D85: =+D68/D51 -> 0.48 | E85: =+E68/E51 -> 0.48 | F85: =+F68/F51 -> 0.48 | G85: =+G68/G51 -> 0.48 | H85: =+H68/H51 -> 0.48 | I85: =+I68/I51 -> 0.48 | J85: =+J68/J51 -> 0.48 | ... O85: =+O68/O51 -> 0.48
B87: TOTAL / POND. | C87: =+C70/C53 -> 0.34171106 | D87: =+D70/D53 -> 0.34171106 | E87: =+E70/E53 -> 0.34171106 | F87: =+F70/F53 -> 0.34171106 | G87: =+G70/G53 -> 0.34171106 | H87: =+H70/H53 -> 0.34171106 | I87: =+I70/I53 -> 0.34171106 | J87: =+J70/J53 -> 0.34171106 | ... O87: =+O70/O53 -> 0.34171106
B89: Competitividad %
B91: Categoria | C91: Mes 0 | D91: Mes 1 | E91: Mes 2 | F91: Mes 3 | G91: Mes 4 | H91: Mes 5 | I91: Mes 6 | J91: Mes 7 | K91: Mes 8 | L91: Mes 9 | M91: Mes 10 | N91: Mes 11 | O91: Mes 12
B92: Medicamentos | C92: =IF(C24="",100,100*(1+C24)) -> 100 | D92: =IF(D24="",100,100*(1+D24)) -> 100 | E92: =IF(E24="",100,100*(1+E24)) -> 100 | F92: =IF(F24="",100,100*(1+F24)) -> 100 | G92: =IF(G24="",100,100*(1+G24)) -> 100 | H92: =IF(H24="",100,100*(1+H24)) -> 100 | I92: =IF(I24="",100,100*(1+I24)) -> 100 | J92: =IF(J24="",100,100*(1+J24)) -> 100 | ... O92: =IF(O24="",100,100*(1+O24)) -> 100
B93: Nutricion | C93: =IF(C25="",100,100*(1+C25)) -> 100 | D93: =IF(D25="",100,100*(1+D25)) -> 100 | E93: =IF(E25="",100,100*(1+E25)) -> 100 | F93: =IF(F25="",100,100*(1+F25)) -> 100 | G93: =IF(G25="",100,100*(1+G25)) -> 100 | H93: =IF(H25="",100,100*(1+H25)) -> 100 | I93: =IF(I25="",100,100*(1+I25)) -> 100 | J93: =IF(J25="",100,100*(1+J25)) -> 100 | ... O93: =IF(O25="",100,100*(1+O25)) -> 100
B94: Parafarmacia | C94: =IF(C26="",100,100*(1+C26)) -> 100 | D94: =IF(D26="",100,100*(1+D26)) -> 100 | E94: =IF(E26="",100,100*(1+E26)) -> 100 | F94: =IF(F26="",100,100*(1+F26)) -> 100 | G94: =IF(G26="",100,100*(1+G26)) -> 100 | H94: =IF(H26="",100,100*(1+H26)) -> 100 | I94: =IF(I26="",100,100*(1+I26)) -> 100 | J94: =IF(J26="",100,100*(1+J26)) -> 100 | ... O94: =IF(O26="",100,100*(1+O26)) -> 100
B95: Suplementos | C95: =IF(C27="",100,100*(1+C27)) -> 100 | D95: =IF(D27="",100,100*(1+D27)) -> 100 | E95: =IF(E27="",100,100*(1+E27)) -> 100 | F95: =IF(F27="",100,100*(1+F27)) -> 100 | G95: =IF(G27="",100,100*(1+G27)) -> 100 | H95: =IF(H27="",100,100*(1+H27)) -> 100 | I95: =IF(I27="",100,100*(1+I27)) -> 100 | J95: =IF(J27="",100,100*(1+J27)) -> 100 | ... O95: =IF(O27="",100,100*(1+O27)) -> 100
B96: Venta Libre | C96: =IF(C28="",100,100*(1+C28)) -> 100 | D96: =IF(D28="",100,100*(1+D28)) -> 100 | E96: =IF(E28="",100,100*(1+E28)) -> 100 | F96: =IF(F28="",100,100*(1+F28)) -> 100 | G96: =IF(G28="",100,100*(1+G28)) -> 100 | H96: =IF(H28="",100,100*(1+H28)) -> 100 | I96: =IF(I28="",100,100*(1+I28)) -> 100 | J96: =IF(J28="",100,100*(1+J28)) -> 100 | ... O96: =IF(O28="",100,100*(1+O28)) -> 100
B97: Cuidado Bucal | C97: =IF(C29="",100,100*(1+C29)) -> 100 | D97: =IF(D29="",100,100*(1+D29)) -> 100 | E97: =IF(E29="",100,100*(1+E29)) -> 100 | F97: =IF(F29="",100,100*(1+F29)) -> 100 | G97: =IF(G29="",100,100*(1+G29)) -> 100 | H97: =IF(H29="",100,100*(1+H29)) -> 100 | I97: =IF(I29="",100,100*(1+I29)) -> 100 | J97: =IF(J29="",100,100*(1+J29)) -> 100 | ... O97: =IF(O29="",100,100*(1+O29)) -> 100
B98: Cuidado Piel | C98: =IF(C30="",100,100*(1+C30)) -> 100 | D98: =IF(D30="",100,100*(1+D30)) -> 100 | E98: =IF(E30="",100,100*(1+E30)) -> 100 | F98: =IF(F30="",100,100*(1+F30)) -> 100 | G98: =IF(G30="",100,100*(1+G30)) -> 100 | H98: =IF(H30="",100,100*(1+H30)) -> 100 | I98: =IF(I30="",100,100*(1+I30)) -> 100 | J98: =IF(J30="",100,100*(1+J30)) -> 100 | ... O98: =IF(O30="",100,100*(1+O30)) -> 100
B99: Bebe y Mama | C99: =IF(C31="",100,100*(1+C31)) -> 100 | D99: =IF(D31="",100,100*(1+D31)) -> 100 | E99: =IF(E31="",100,100*(1+E31)) -> 100 | F99: =IF(F31="",100,100*(1+F31)) -> 100 | G99: =IF(G31="",100,100*(1+G31)) -> 100 | H99: =IF(H31="",100,100*(1+H31)) -> 100 | I99: =IF(I31="",100,100*(1+I31)) -> 100 | J99: =IF(J31="",100,100*(1+J31)) -> 100 | ... O99: =IF(O31="",100,100*(1+O31)) -> 100
B100: Cuidado Cabello | C100: =IF(C32="",100,100*(1+C32)) -> 100 | D100: =IF(D32="",100,100*(1+D32)) -> 100 | E100: =IF(E32="",100,100*(1+E32)) -> 100 | F100: =IF(F32="",100,100*(1+F32)) -> 100 | G100: =IF(G32="",100,100*(1+G32)) -> 100 | H100: =IF(H32="",100,100*(1+H32)) -> 100 | I100: =IF(I32="",100,100*(1+I32)) -> 100 | J100: =IF(J32="",100,100*(1+J32)) -> 100 | ... O100: =IF(O32="",100,100*(1+O32)) -> 100
B101: Cuidado Personal | C101: =IF(C33="",100,100*(1+C33)) -> 100 | D101: =IF(D33="",100,100*(1+D33)) -> 100 | E101: =IF(E33="",100,100*(1+E33)) -> 100 | F101: =IF(F33="",100,100*(1+F33)) -> 100 | G101: =IF(G33="",100,100*(1+G33)) -> 100 | H101: =IF(H33="",100,100*(1+H33)) -> 100 | I101: =IF(I33="",100,100*(1+I33)) -> 100 | J101: =IF(J33="",100,100*(1+J33)) -> 100 | ... O101: =IF(O33="",100,100*(1+O33)) -> 100
B102: Dermocosmetica | C102: =IF(C34="",100,100*(1+C34)) -> 100 | D102: =IF(D34="",100,100*(1+D34)) -> 100 | E102: =IF(E34="",100,100*(1+E34)) -> 100 | F102: =IF(F34="",100,100*(1+F34)) -> 100 | G102: =IF(G34="",100,100*(1+G34)) -> 100 | H102: =IF(H34="",100,100*(1+H34)) -> 100 | I102: =IF(I34="",100,100*(1+I34)) -> 100 | J102: =IF(J34="",100,100*(1+J34)) -> 100 | ... O102: =IF(O34="",100,100*(1+O34)) -> 100
B104: Comp % | C104: =SUMPRODUCT(C92:C102,C41:C51)/C53 -> 100 | D104: =SUMPRODUCT(D92:D102,D41:D51)/D53 -> 100 | E104: =SUMPRODUCT(E92:E102,E41:E51)/E53 -> 100 | F104: =SUMPRODUCT(F92:F102,F41:F51)/F53 -> 100 | G104: =SUMPRODUCT(G92:G102,G41:G51)/G53 -> 100 | H104: =SUMPRODUCT(H92:H102,H41:H51)/H53 -> 100 | I104: =SUMPRODUCT(I92:I102,I41:I51)/I53 -> 100 | J104: =SUMPRODUCT(J92:J102,J41:J51)/J53 -> 100 | ... O104: =SUMPRODUCT(O92:O102,O41:O51)/O53 -> 100

Sheet 03_CatMan_DDI
B3: Simulador 2 - CatMan, Surtido, Cobertura y DDI
B5: Categoria | C5: SKUs Base | D5: Cobertura % | E5: Reduccion SKUs % | F5: Merma %
B6: Medicamentos | C6: 420 | D6: 0.95 | E6: 0.05 | F6: =MAX(0.002,0.012-E6*0.03) -> 0.0105
B7: Nutricion | C7: 160 | D7: 0.95 | E7: 0.05 | F7: =MAX(0.002,0.012-E7*0.03) -> 0.0105
B8: Parafarmacia | C8: 240 | D8: 0.95 | E8: 0.05 | F8: =MAX(0.002,0.012-E8*0.03) -> 0.0105
B9: Suplementos | C9: 180 | D9: 0.95 | E9: 0.05 | F9: =MAX(0.002,0.012-E9*0.03) -> 0.0105
B10: Venta Libre | C10: 260 | D10: 0.95 | E10: 0.05 | F10: =MAX(0.002,0.012-E10*0.03) -> 0.0105
B11: Cuidado Bucal | C11: 140 | D11: 0.95 | E11: 0.05 | F11: =MAX(0.002,0.012-E11*0.03) -> 0.0105
B12: Cuidado Piel | C12: 180 | D12: 0.95 | E12: 0.05 | F12: =MAX(0.002,0.012-E12*0.03) -> 0.0105
B13: Bebe y Mama | C13: 120 | D13: 0.95 | E13: 0.05 | F13: =MAX(0.002,0.012-E13*0.03) -> 0.0105
B14: Cuidado Cabello | C14: 160 | D14: 0.95 | E14: 0.05 | F14: =MAX(0.002,0.012-E14*0.03) -> 0.0105
B15: Cuidado Personal | C15: 190 | D15: 0.95 | E15: 0.05 | F15: =MAX(0.002,0.012-E15*0.03) -> 0.0105
B16: Dermocosmetica | C16: 220 | D16: 0.95 | E16: 0.05 | F16: =MAX(0.002,0.012-E16*0.03) -> 0.0105
B18: TOTAL / POND. | C18: =SUM(C6:C16) -> 2270 | D18: =AVERAGE(D6:D16) -> 0.95 | E18: =AVERAGE(E6:E16) -> 0.05 | F18: =SUMPRODUCT(F6:F16,P57:P67)/P69 -> 0.0105
B20: DDI Objetivo
B22: Categoria | C22: Mes 0 | D22: Mes 1 | E22: Mes 2 | F22: Mes 3 | G22: Mes 4 | H22: Mes 5 | I22: Mes 6 | J22: Mes 7 | K22: Mes 8 | L22: Mes 9 | M22: Mes 10 | N22: Mes 11 | O22: Mes 12
B23: Medicamentos | C23: 55 | D23: 47 | E23: 47 | F23: 47 | G23: 47 | H23: 47 | I23: 47 | J23: 47 | K23: 47 | L23: 47 | M23: 47 | N23: 47 | O23: 47
B24: Nutricion | C24: 65 | D24: 57 | E24: 57 | F24: 57 | G24: 57 | H24: 57 | I24: 57 | J24: 57 | K24: 57 | L24: 57 | M24: 57 | N24: 57 | O24: 57
B25: Parafarmacia | C25: 70 | D25: 62 | E25: 62 | F25: 62 | G25: 62 | H25: 62 | I25: 62 | J25: 62 | K25: 62 | L25: 62 | M25: 62 | N25: 62 | O25: 62
B26: Suplementos | C26: 75 | D26: 67 | E26: 67 | F26: 67 | G26: 67 | H26: 67 | I26: 67 | J26: 67 | K26: 67 | L26: 67 | M26: 67 | N26: 67 | O26: 67
B27: Venta Libre | C27: 60 | D27: 52 | E27: 52 | F27: 52 | G27: 52 | H27: 52 | I27: 52 | J27: 52 | K27: 52 | L27: 52 | M27: 52 | N27: 52 | O27: 52
B28: Cuidado Bucal | C28: 58 | D28: 50 | E28: 50 | F28: 50 | G28: 50 | H28: 50 | I28: 50 | J28: 50 | K28: 50 | L28: 50 | M28: 50 | N28: 50 | O28: 50
B29: Cuidado Piel | C29: 70 | D29: 62 | E29: 62 | F29: 62 | G29: 62 | H29: 62 | I29: 62 | J29: 62 | K29: 62 | L29: 62 | M29: 62 | N29: 62 | O29: 62
B30: Bebe y Mama | C30: 62 | D30: 54 | E30: 54 | F30: 54 | G30: 54 | H30: 54 | I30: 54 | J30: 54 | K30: 54 | L30: 54 | M30: 54 | N30: 54 | O30: 54
B31: Cuidado Cabello | C31: 65 | D31: 57 | E31: 57 | F31: 57 | G31: 57 | H31: 57 | I31: 57 | J31: 57 | K31: 57 | L31: 57 | M31: 57 | N31: 57 | O31: 57
B32: Cuidado Personal | C32: 66 | D32: 58 | E32: 58 | F32: 58 | G32: 58 | H32: 58 | I32: 58 | J32: 58 | K32: 58 | L32: 58 | M32: 58 | N32: 58 | O32: 58
B33: Dermocosmetica | C33: 80 | D33: 72 | E33: 72 | F33: 72 | G33: 72 | H33: 72 | I33: 72 | J33: 72 | K33: 72 | L33: 72 | M33: 72 | N33: 72 | O33: 72
B35: TOTAL / POND. | C35: =SUMPRODUCT(C23:C33,C74:C84)/C86 -> 63.927442 | D35: =SUMPRODUCT(D23:D33,D74:D84)/D86 -> 56.081875 | E35: =SUMPRODUCT(E23:E33,E74:E84)/E86 -> 56.081875 | F35: =SUMPRODUCT(F23:F33,F74:F84)/F86 -> 56.081875 | G35: =SUMPRODUCT(G23:G33,G74:G84)/G86 -> 56.081875 | H35: =SUMPRODUCT(H23:H33,H74:H84)/H86 -> 56.081875 | I35: =SUMPRODUCT(I23:I33,I74:I84)/I86 -> 56.081875 | J35: =SUMPRODUCT(J23:J33,J74:J84)/J86 -> 56.081875 | ... O35: =SUMPRODUCT(O23:O33,O74:O84)/O86 -> 56.081875
B37: Quiebre Estimado %
B39: Categoria | C39: Mes 0 | D39: Mes 1 | E39: Mes 2 | F39: Mes 3 | G39: Mes 4 | H39: Mes 5 | I39: Mes 6 | J39: Mes 7 | K39: Mes 8 | L39: Mes 9 | M39: Mes 10 | N39: Mes 11 | O39: Mes 12
B40: Medicamentos | D40: =MAX(0,(1-$D6)*0.12+MAX(0,45-D23)*0.004) -> 0.006 | E40: =MAX(0,(1-$D6)*0.12+MAX(0,45-E23)*0.004) -> 0.006 | F40: =MAX(0,(1-$D6)*0.12+MAX(0,45-F23)*0.004) -> 0.006 | G40: =MAX(0,(1-$D6)*0.12+MAX(0,45-G23)*0.004) -> 0.006 | H40: =MAX(0,(1-$D6)*0.12+MAX(0,45-H23)*0.004) -> 0.006 | I40: =MAX(0,(1-$D6)*0.12+MAX(0,45-I23)*0.004) -> 0.006 | J40: =MAX(0,(1-$D6)*0.12+MAX(0,45-J23)*0.004) -> 0.006 | K40: =MAX(0,(1-$D6)*0.12+MAX(0,45-K23)*0.004) -> 0.006 | ... O40: =MAX(0,(1-$D6)*0.12+MAX(0,45-O23)*0.004) -> 0.006
B41: Nutricion | D41: =MAX(0,(1-$D7)*0.12+MAX(0,45-D24)*0.004) -> 0.006 | E41: =MAX(0,(1-$D7)*0.12+MAX(0,45-E24)*0.004) -> 0.006 | F41: =MAX(0,(1-$D7)*0.12+MAX(0,45-F24)*0.004) -> 0.006 | G41: =MAX(0,(1-$D7)*0.12+MAX(0,45-G24)*0.004) -> 0.006 | H41: =MAX(0,(1-$D7)*0.12+MAX(0,45-H24)*0.004) -> 0.006 | I41: =MAX(0,(1-$D7)*0.12+MAX(0,45-I24)*0.004) -> 0.006 | J41: =MAX(0,(1-$D7)*0.12+MAX(0,45-J24)*0.004) -> 0.006 | K41: =MAX(0,(1-$D7)*0.12+MAX(0,45-K24)*0.004) -> 0.006 | ... O41: =MAX(0,(1-$D7)*0.12+MAX(0,45-O24)*0.004) -> 0.006
B42: Parafarmacia | D42: =MAX(0,(1-$D8)*0.12+MAX(0,45-D25)*0.004) -> 0.006 | E42: =MAX(0,(1-$D8)*0.12+MAX(0,45-E25)*0.004) -> 0.006 | F42: =MAX(0,(1-$D8)*0.12+MAX(0,45-F25)*0.004) -> 0.006 | G42: =MAX(0,(1-$D8)*0.12+MAX(0,45-G25)*0.004) -> 0.006 | H42: =MAX(0,(1-$D8)*0.12+MAX(0,45-H25)*0.004) -> 0.006 | I42: =MAX(0,(1-$D8)*0.12+MAX(0,45-I25)*0.004) -> 0.006 | J42: =MAX(0,(1-$D8)*0.12+MAX(0,45-J25)*0.004) -> 0.006 | K42: =MAX(0,(1-$D8)*0.12+MAX(0,45-K25)*0.004) -> 0.006 | ... O42: =MAX(0,(1-$D8)*0.12+MAX(0,45-O25)*0.004) -> 0.006
B43: Suplementos | D43: =MAX(0,(1-$D9)*0.12+MAX(0,45-D26)*0.004) -> 0.006 | E43: =MAX(0,(1-$D9)*0.12+MAX(0,45-E26)*0.004) -> 0.006 | F43: =MAX(0,(1-$D9)*0.12+MAX(0,45-F26)*0.004) -> 0.006 | G43: =MAX(0,(1-$D9)*0.12+MAX(0,45-G26)*0.004) -> 0.006 | H43: =MAX(0,(1-$D9)*0.12+MAX(0,45-H26)*0.004) -> 0.006 | I43: =MAX(0,(1-$D9)*0.12+MAX(0,45-I26)*0.004) -> 0.006 | J43: =MAX(0,(1-$D9)*0.12+MAX(0,45-J26)*0.004) -> 0.006 | K43: =MAX(0,(1-$D9)*0.12+MAX(0,45-K26)*0.004) -> 0.006 | ... O43: =MAX(0,(1-$D9)*0.12+MAX(0,45-O26)*0.004) -> 0.006
B44: Venta Libre | D44: =MAX(0,(1-$D10)*0.12+MAX(0,45-D27)*0.004) -> 0.006 | E44: =MAX(0,(1-$D10)*0.12+MAX(0,45-E27)*0.004) -> 0.006 | F44: =MAX(0,(1-$D10)*0.12+MAX(0,45-F27)*0.004) -> 0.006 | G44: =MAX(0,(1-$D10)*0.12+MAX(0,45-G27)*0.004) -> 0.006 | H44: =MAX(0,(1-$D10)*0.12+MAX(0,45-H27)*0.004) -> 0.006 | I44: =MAX(0,(1-$D10)*0.12+MAX(0,45-I27)*0.004) -> 0.006 | J44: =MAX(0,(1-$D10)*0.12+MAX(0,45-J27)*0.004) -> 0.006 | K44: =MAX(0,(1-$D10)*0.12+MAX(0,45-K27)*0.004) -> 0.006 | ... O44: =MAX(0,(1-$D10)*0.12+MAX(0,45-O27)*0.004) -> 0.006
B45: Cuidado Bucal | D45: =MAX(0,(1-$D11)*0.12+MAX(0,45-D28)*0.004) -> 0.006 | E45: =MAX(0,(1-$D11)*0.12+MAX(0,45-E28)*0.004) -> 0.006 | F45: =MAX(0,(1-$D11)*0.12+MAX(0,45-F28)*0.004) -> 0.006 | G45: =MAX(0,(1-$D11)*0.12+MAX(0,45-G28)*0.004) -> 0.006 | H45: =MAX(0,(1-$D11)*0.12+MAX(0,45-H28)*0.004) -> 0.006 | I45: =MAX(0,(1-$D11)*0.12+MAX(0,45-I28)*0.004) -> 0.006 | J45: =MAX(0,(1-$D11)*0.12+MAX(0,45-J28)*0.004) -> 0.006 | K45: =MAX(0,(1-$D11)*0.12+MAX(0,45-K28)*0.004) -> 0.006 | ... O45: =MAX(0,(1-$D11)*0.12+MAX(0,45-O28)*0.004) -> 0.006
B46: Cuidado Piel | D46: =MAX(0,(1-$D12)*0.12+MAX(0,45-D29)*0.004) -> 0.006 | E46: =MAX(0,(1-$D12)*0.12+MAX(0,45-E29)*0.004) -> 0.006 | F46: =MAX(0,(1-$D12)*0.12+MAX(0,45-F29)*0.004) -> 0.006 | G46: =MAX(0,(1-$D12)*0.12+MAX(0,45-G29)*0.004) -> 0.006 | H46: =MAX(0,(1-$D12)*0.12+MAX(0,45-H29)*0.004) -> 0.006 | I46: =MAX(0,(1-$D12)*0.12+MAX(0,45-I29)*0.004) -> 0.006 | J46: =MAX(0,(1-$D12)*0.12+MAX(0,45-J29)*0.004) -> 0.006 | K46: =MAX(0,(1-$D12)*0.12+MAX(0,45-K29)*0.004) -> 0.006 | ... O46: =MAX(0,(1-$D12)*0.12+MAX(0,45-O29)*0.004) -> 0.006
B47: Bebe y Mama | D47: =MAX(0,(1-$D13)*0.12+MAX(0,45-D30)*0.004) -> 0.006 | E47: =MAX(0,(1-$D13)*0.12+MAX(0,45-E30)*0.004) -> 0.006 | F47: =MAX(0,(1-$D13)*0.12+MAX(0,45-F30)*0.004) -> 0.006 | G47: =MAX(0,(1-$D13)*0.12+MAX(0,45-G30)*0.004) -> 0.006 | H47: =MAX(0,(1-$D13)*0.12+MAX(0,45-H30)*0.004) -> 0.006 | I47: =MAX(0,(1-$D13)*0.12+MAX(0,45-I30)*0.004) -> 0.006 | J47: =MAX(0,(1-$D13)*0.12+MAX(0,45-J30)*0.004) -> 0.006 | K47: =MAX(0,(1-$D13)*0.12+MAX(0,45-K30)*0.004) -> 0.006 | ... O47: =MAX(0,(1-$D13)*0.12+MAX(0,45-O30)*0.004) -> 0.006
B48: Cuidado Cabello | D48: =MAX(0,(1-$D14)*0.12+MAX(0,45-D31)*0.004) -> 0.006 | E48: =MAX(0,(1-$D14)*0.12+MAX(0,45-E31)*0.004) -> 0.006 | F48: =MAX(0,(1-$D14)*0.12+MAX(0,45-F31)*0.004) -> 0.006 | G48: =MAX(0,(1-$D14)*0.12+MAX(0,45-G31)*0.004) -> 0.006 | H48: =MAX(0,(1-$D14)*0.12+MAX(0,45-H31)*0.004) -> 0.006 | I48: =MAX(0,(1-$D14)*0.12+MAX(0,45-I31)*0.004) -> 0.006 | J48: =MAX(0,(1-$D14)*0.12+MAX(0,45-J31)*0.004) -> 0.006 | K48: =MAX(0,(1-$D14)*0.12+MAX(0,45-K31)*0.004) -> 0.006 | ... O48: =MAX(0,(1-$D14)*0.12+MAX(0,45-O31)*0.004) -> 0.006
B49: Cuidado Personal | D49: =MAX(0,(1-$D15)*0.12+MAX(0,45-D32)*0.004) -> 0.006 | E49: =MAX(0,(1-$D15)*0.12+MAX(0,45-E32)*0.004) -> 0.006 | F49: =MAX(0,(1-$D15)*0.12+MAX(0,45-F32)*0.004) -> 0.006 | G49: =MAX(0,(1-$D15)*0.12+MAX(0,45-G32)*0.004) -> 0.006 | H49: =MAX(0,(1-$D15)*0.12+MAX(0,45-H32)*0.004) -> 0.006 | I49: =MAX(0,(1-$D15)*0.12+MAX(0,45-I32)*0.004) -> 0.006 | J49: =MAX(0,(1-$D15)*0.12+MAX(0,45-J32)*0.004) -> 0.006 | K49: =MAX(0,(1-$D15)*0.12+MAX(0,45-K32)*0.004) -> 0.006 | ... O49: =MAX(0,(1-$D15)*0.12+MAX(0,45-O32)*0.004) -> 0.006
B50: Dermocosmetica | D50: =MAX(0,(1-$D16)*0.12+MAX(0,45-D33)*0.004) -> 0.006 | E50: =MAX(0,(1-$D16)*0.12+MAX(0,45-E33)*0.004) -> 0.006 | F50: =MAX(0,(1-$D16)*0.12+MAX(0,45-F33)*0.004) -> 0.006 | G50: =MAX(0,(1-$D16)*0.12+MAX(0,45-G33)*0.004) -> 0.006 | H50: =MAX(0,(1-$D16)*0.12+MAX(0,45-H33)*0.004) -> 0.006 | I50: =MAX(0,(1-$D16)*0.12+MAX(0,45-I33)*0.004) -> 0.006 | J50: =MAX(0,(1-$D16)*0.12+MAX(0,45-J33)*0.004) -> 0.006 | K50: =MAX(0,(1-$D16)*0.12+MAX(0,45-K33)*0.004) -> 0.006 | ... O50: =MAX(0,(1-$D16)*0.12+MAX(0,45-O33)*0.004) -> 0.006
B52: TOTAL / POND.
B54: Revenue Ajustado
B56: Categoria | C56: Mes 0 | D56: Mes 1 | E56: Mes 2 | F56: Mes 3 | G56: Mes 4 | H56: Mes 5 | I56: Mes 6 | J56: Mes 7 | K56: Mes 8 | L56: Mes 9 | M56: Mes 10 | N56: Mes 11 | O56: Mes 12 | P56: Total
B57: Medicamentos | C57: =+'02_Pricing'!C41*(1-'03_CatMan_DDI'!C40) -> 10004.904 | D57: =+'02_Pricing'!D41*(1-'03_CatMan_DDI'!D40) -> 9944.8746 | E57: =+'02_Pricing'!E41*(1-'03_CatMan_DDI'!E40) -> 9944.8746 | F57: =+'02_Pricing'!F41*(1-'03_CatMan_DDI'!F40) -> 9944.8746 | G57: =+'02_Pricing'!G41*(1-'03_CatMan_DDI'!G40) -> 9944.8746 | H57: =+'02_Pricing'!H41*(1-'03_CatMan_DDI'!H40) -> 9944.8746 | I57: =+'02_Pricing'!I41*(1-'03_CatMan_DDI'!I40) -> 9944.8746 | J57: =+'02_Pricing'!J41*(1-'03_CatMan_DDI'!J40) -> 9944.8746 | ... O57: =+'02_Pricing'!O41*(1-'03_CatMan_DDI'!O40) -> 9944.8746 | P57: =SUM(D57:O57) -> 119338.49
B58: Nutricion | C58: =+'02_Pricing'!C42*(1-'03_CatMan_DDI'!C41) -> 1500.7754 | D58: =+'02_Pricing'!D42*(1-'03_CatMan_DDI'!D41) -> 1491.7707 | E58: =+'02_Pricing'!E42*(1-'03_CatMan_DDI'!E41) -> 1491.7707 | F58: =+'02_Pricing'!F42*(1-'03_CatMan_DDI'!F41) -> 1491.7707 | G58: =+'02_Pricing'!G42*(1-'03_CatMan_DDI'!G41) -> 1491.7707 | H58: =+'02_Pricing'!H42*(1-'03_CatMan_DDI'!H41) -> 1491.7707 | I58: =+'02_Pricing'!I42*(1-'03_CatMan_DDI'!I41) -> 1491.7707 | J58: =+'02_Pricing'!J42*(1-'03_CatMan_DDI'!J41) -> 1491.7707 | ... O58: =+'02_Pricing'!O42*(1-'03_CatMan_DDI'!O41) -> 1491.7707 | P58: =SUM(D58:O58) -> 17901.249
B59: Parafarmacia | C59: =+'02_Pricing'!C43*(1-'03_CatMan_DDI'!C42) -> 2001.0339 | D59: =+'02_Pricing'!D43*(1-'03_CatMan_DDI'!D42) -> 1989.0277 | E59: =+'02_Pricing'!E43*(1-'03_CatMan_DDI'!E42) -> 1989.0277 | F59: =+'02_Pricing'!F43*(1-'03_CatMan_DDI'!F42) -> 1989.0277 | G59: =+'02_Pricing'!G43*(1-'03_CatMan_DDI'!G42) -> 1989.0277 | H59: =+'02_Pricing'!H43*(1-'03_CatMan_DDI'!H42) -> 1989.0277 | I59: =+'02_Pricing'!I43*(1-'03_CatMan_DDI'!I42) -> 1989.0277 | J59: =+'02_Pricing'!J43*(1-'03_CatMan_DDI'!J42) -> 1989.0277 | ... O59: =+'02_Pricing'!O43*(1-'03_CatMan_DDI'!O42) -> 1989.0277 | P59: =SUM(D59:O59) -> 23868.332
B60: Suplementos | C60: =+'02_Pricing'!C44*(1-'03_CatMan_DDI'!C43) -> 1750.9046 | D60: =+'02_Pricing'!D44*(1-'03_CatMan_DDI'!D43) -> 1740.3992 | E60: =+'02_Pricing'!E44*(1-'03_CatMan_DDI'!E43) -> 1740.3992 | F60: =+'02_Pricing'!F44*(1-'03_CatMan_DDI'!F43) -> 1740.3992 | G60: =+'02_Pricing'!G44*(1-'03_CatMan_DDI'!G43) -> 1740.3992 | H60: =+'02_Pricing'!H44*(1-'03_CatMan_DDI'!H43) -> 1740.3992 | I60: =+'02_Pricing'!I44*(1-'03_CatMan_DDI'!I43) -> 1740.3992 | J60: =+'02_Pricing'!J44*(1-'03_CatMan_DDI'!J43) -> 1740.3992 | ... O60: =+'02_Pricing'!O44*(1-'03_CatMan_DDI'!O43) -> 1740.3992 | P60: =SUM(D60:O60) -> 20884.79
B61: Venta Libre | C61: =+'02_Pricing'!C45*(1-'03_CatMan_DDI'!C44) -> 3751.9385 | D61: =+'02_Pricing'!D45*(1-'03_CatMan_DDI'!D44) -> 3729.4269 | E61: =+'02_Pricing'!E45*(1-'03_CatMan_DDI'!E44) -> 3729.4269 | F61: =+'02_Pricing'!F45*(1-'03_CatMan_DDI'!F44) -> 3729.4269 | G61: =+'02_Pricing'!G45*(1-'03_CatMan_DDI'!G44) -> 3729.4269 | H61: =+'02_Pricing'!H45*(1-'03_CatMan_DDI'!H44) -> 3729.4269 | I61: =+'02_Pricing'!I45*(1-'03_CatMan_DDI'!I44) -> 3729.4269 | J61: =+'02_Pricing'!J45*(1-'03_CatMan_DDI'!J44) -> 3729.4269 | ... O61: =+'02_Pricing'!O45*(1-'03_CatMan_DDI'!O44) -> 3729.4269 | P61: =SUM(D61:O61) -> 44753.122
B62: Cuidado Bucal | C62: =+'02_Pricing'!C46*(1-'03_CatMan_DDI'!C45) -> 1250.6462 | D62: =+'02_Pricing'!D46*(1-'03_CatMan_DDI'!D45) -> 1243.1423 | E62: =+'02_Pricing'!E46*(1-'03_CatMan_DDI'!E45) -> 1243.1423 | F62: =+'02_Pricing'!F46*(1-'03_CatMan_DDI'!F45) -> 1243.1423 | G62: =+'02_Pricing'!G46*(1-'03_CatMan_DDI'!G45) -> 1243.1423 | H62: =+'02_Pricing'!H46*(1-'03_CatMan_DDI'!H45) -> 1243.1423 | I62: =+'02_Pricing'!I46*(1-'03_CatMan_DDI'!I45) -> 1243.1423 | J62: =+'02_Pricing'!J46*(1-'03_CatMan_DDI'!J45) -> 1243.1423 | ... O62: =+'02_Pricing'!O46*(1-'03_CatMan_DDI'!O45) -> 1243.1423 | P62: =SUM(D62:O62) -> 14917.707
B63: Cuidado Piel | C63: =+'02_Pricing'!C47*(1-'03_CatMan_DDI'!C46) -> 2251.1631 | D63: =+'02_Pricing'!D47*(1-'03_CatMan_DDI'!D46) -> 2237.6561 | E63: =+'02_Pricing'!E47*(1-'03_CatMan_DDI'!E46) -> 2237.6561 | F63: =+'02_Pricing'!F47*(1-'03_CatMan_DDI'!F46) -> 2237.6561 | G63: =+'02_Pricing'!G47*(1-'03_CatMan_DDI'!G46) -> 2237.6561 | H63: =+'02_Pricing'!H47*(1-'03_CatMan_DDI'!H46) -> 2237.6561 | I63: =+'02_Pricing'!I47*(1-'03_CatMan_DDI'!I46) -> 2237.6561 | J63: =+'02_Pricing'!J47*(1-'03_CatMan_DDI'!J46) -> 2237.6561 | ... O63: =+'02_Pricing'!O47*(1-'03_CatMan_DDI'!O46) -> 2237.6561 | P63: =SUM(D63:O63) -> 26851.873
B64: Bebe y Mama | C64: =+'02_Pricing'!C48*(1-'03_CatMan_DDI'!C47) -> 1125.5816 | D64: =+'02_Pricing'!D48*(1-'03_CatMan_DDI'!D47) -> 1118.8281 | E64: =+'02_Pricing'!E48*(1-'03_CatMan_DDI'!E47) -> 1118.8281 | F64: =+'02_Pricing'!F48*(1-'03_CatMan_DDI'!F47) -> 1118.8281 | G64: =+'02_Pricing'!G48*(1-'03_CatMan_DDI'!G47) -> 1118.8281 | H64: =+'02_Pricing'!H48*(1-'03_CatMan_DDI'!H47) -> 1118.8281 | I64: =+'02_Pricing'!I48*(1-'03_CatMan_DDI'!I47) -> 1118.8281 | J64: =+'02_Pricing'!J48*(1-'03_CatMan_DDI'!J47) -> 1118.8281 | ... O64: =+'02_Pricing'!O48*(1-'03_CatMan_DDI'!O47) -> 1118.8281 | P64: =SUM(D64:O64) -> 13425.937
B65: Cuidado Cabello | C65: =+'02_Pricing'!C49*(1-'03_CatMan_DDI'!C48) -> 1375.7108 | D65: =+'02_Pricing'!D49*(1-'03_CatMan_DDI'!D48) -> 1367.4565 | E65: =+'02_Pricing'!E49*(1-'03_CatMan_DDI'!E48) -> 1367.4565 | F65: =+'02_Pricing'!F49*(1-'03_CatMan_DDI'!F48) -> 1367.4565 | G65: =+'02_Pricing'!G49*(1-'03_CatMan_DDI'!G48) -> 1367.4565 | H65: =+'02_Pricing'!H49*(1-'03_CatMan_DDI'!H48) -> 1367.4565 | I65: =+'02_Pricing'!I49*(1-'03_CatMan_DDI'!I48) -> 1367.4565 | J65: =+'02_Pricing'!J49*(1-'03_CatMan_DDI'!J48) -> 1367.4565 | ... O65: =+'02_Pricing'!O49*(1-'03_CatMan_DDI'!O48) -> 1367.4565 | P65: =SUM(D65:O65) -> 16409.478
B66: Cuidado Personal | C66: =+'02_Pricing'!C50*(1-'03_CatMan_DDI'!C49) -> 1625.84 | D66: =+'02_Pricing'!D50*(1-'03_CatMan_DDI'!D49) -> 1616.085 | E66: =+'02_Pricing'!E50*(1-'03_CatMan_DDI'!E49) -> 1616.085 | F66: =+'02_Pricing'!F50*(1-'03_CatMan_DDI'!F49) -> 1616.085 | G66: =+'02_Pricing'!G50*(1-'03_CatMan_DDI'!G49) -> 1616.085 | H66: =+'02_Pricing'!H50*(1-'03_CatMan_DDI'!H49) -> 1616.085 | I66: =+'02_Pricing'!I50*(1-'03_CatMan_DDI'!I49) -> 1616.085 | J66: =+'02_Pricing'!J50*(1-'03_CatMan_DDI'!J49) -> 1616.085 | ... O66: =+'02_Pricing'!O50*(1-'03_CatMan_DDI'!O49) -> 1616.085 | P66: =SUM(D66:O66) -> 19393.02
B67: Dermocosmetica | C67: =+'02_Pricing'!C51*(1-'03_CatMan_DDI'!C50) -> 3361.2366 | D67: =+'02_Pricing'!D51*(1-'03_CatMan_DDI'!D50) -> 3341.0692 | E67: =+'02_Pricing'!E51*(1-'03_CatMan_DDI'!E50) -> 3341.0692 | F67: =+'02_Pricing'!F51*(1-'03_CatMan_DDI'!F50) -> 3341.0692 | G67: =+'02_Pricing'!G51*(1-'03_CatMan_DDI'!G50) -> 3341.0692 | H67: =+'02_Pricing'!H51*(1-'03_CatMan_DDI'!H50) -> 3341.0692 | I67: =+'02_Pricing'!I51*(1-'03_CatMan_DDI'!I50) -> 3341.0692 | J67: =+'02_Pricing'!J51*(1-'03_CatMan_DDI'!J50) -> 3341.0692 | ... O67: =+'02_Pricing'!O51*(1-'03_CatMan_DDI'!O50) -> 3341.0692 | P67: =SUM(D67:O67) -> 40092.831
B69: TOTAL / POND. | C69: =SUM(C57:C67) -> 29999.735 | D69: =SUM(D57:D67) -> 29819.736 | E69: =SUM(E57:E67) -> 29819.736 | F69: =SUM(F57:F67) -> 29819.736 | G69: =SUM(G57:G67) -> 29819.736 | H69: =SUM(H57:H67) -> 29819.736 | I69: =SUM(I57:I67) -> 29819.736 | J69: =SUM(J57:J67) -> 29819.736 | ... O69: =SUM(O57:O67) -> 29819.736 | P69: =SUM(D69:O69) -> 357836.84
B71: Inventario (ARS MM)
B73: Categoria | C73: Mes 0 | D73: Mes 1 | E73: Mes 2 | F73: Mes 3 | G73: Mes 4 | H73: Mes 5 | I73: Mes 6 | J73: Mes 7 | K73: Mes 8 | L73: Mes 9 | M73: Mes 10 | N73: Mes 11 | O73: Mes 12 | P73: Total
B74: Medicamentos | C74: =+(C57/30)*C23*(1-'02_Pricing'!C75) -> 13305.6 | D74: =+(D57/30)*D23*(1-'02_Pricing'!D75) -> 11302.019 | E74: =+(E57/30)*E23*(1-'02_Pricing'!E75) -> 11302.019 | F74: =+(F57/30)*F23*(1-'02_Pricing'!F75) -> 11302.019 | G74: =+(G57/30)*G23*(1-'02_Pricing'!G75) -> 11302.019 | H74: =+(H57/30)*H23*(1-'02_Pricing'!H75) -> 11302.019 | I74: =+(I57/30)*I23*(1-'02_Pricing'!I75) -> 11302.019 | J74: =+(J57/30)*J23*(1-'02_Pricing'!J75) -> 11302.019 | ... O74: =+(O57/30)*O23*(1-'02_Pricing'!O75) -> 11302.019 | P74: =SUM(D74:O74) -> 135624.22
B75: Nutricion | C75: =+(C58/30)*C24*(1-'02_Pricing'!C76) -> 2211.1424 | D75: =+(D58/30)*D24*(1-'02_Pricing'!D76) -> 1927.3678 | E75: =+(E58/30)*E24*(1-'02_Pricing'!E76) -> 1927.3678 | F75: =+(F58/30)*F24*(1-'02_Pricing'!F76) -> 1927.3678 | G75: =+(G58/30)*G24*(1-'02_Pricing'!G76) -> 1927.3678 | H75: =+(H58/30)*H24*(1-'02_Pricing'!H76) -> 1927.3678 | I75: =+(I58/30)*I24*(1-'02_Pricing'!I76) -> 1927.3678 | J75: =+(J58/30)*J24*(1-'02_Pricing'!J76) -> 1927.3678 | ... O75: =+(O58/30)*O24*(1-'02_Pricing'!O76) -> 1927.3678 | P75: =SUM(D75:O75) -> 23128.414
B76: Parafarmacia | C76: =+(C59/30)*C25*(1-'02_Pricing'!C77) -> 3034.9014 | D76: =+(D59/30)*D25*(1-'02_Pricing'!D77) -> 2671.9272 | E76: =+(E59/30)*E25*(1-'02_Pricing'!E77) -> 2671.9272 | F76: =+(F59/30)*F25*(1-'02_Pricing'!F77) -> 2671.9272 | G76: =+(G59/30)*G25*(1-'02_Pricing'!G77) -> 2671.9272 | H76: =+(H59/30)*H25*(1-'02_Pricing'!H77) -> 2671.9272 | I76: =+(I59/30)*I25*(1-'02_Pricing'!I77) -> 2671.9272 | J76: =+(J59/30)*J25*(1-'02_Pricing'!J77) -> 2671.9272 | ... O76: =+(O59/30)*O25*(1-'02_Pricing'!O77) -> 2671.9272 | P76: =SUM(D76:O76) -> 32063.126
B77: Suplementos | C77: =+(C60/30)*C26*(1-'02_Pricing'!C78) -> 2713.9022 | D77: =+(D60/30)*D26*(1-'02_Pricing'!D78) -> 2409.8728 | E77: =+(E60/30)*E26*(1-'02_Pricing'!E78) -> 2409.8728 | F77: =+(F60/30)*F26*(1-'02_Pricing'!F78) -> 2409.8728 | G77: =+(G60/30)*G26*(1-'02_Pricing'!G78) -> 2409.8728 | H77: =+(H60/30)*H26*(1-'02_Pricing'!H78) -> 2409.8728 | I77: =+(I60/30)*I26*(1-'02_Pricing'!I78) -> 2409.8728 | J77: =+(J60/30)*J26*(1-'02_Pricing'!J78) -> 2409.8728 | ... O77: =+(O60/30)*O26*(1-'02_Pricing'!O78) -> 2409.8728 | P77: =SUM(D77:O77) -> 28918.473
B78: Venta Libre | C78: =+(C61/30)*C27*(1-'02_Pricing'!C79) -> 4952.5588 | D78: =+(D61/30)*D27*(1-'02_Pricing'!D79) -> 4266.4643 | E78: =+(E61/30)*E27*(1-'02_Pricing'!E79) -> 4266.4643 | F78: =+(F61/30)*F27*(1-'02_Pricing'!F79) -> 4266.4643 | G78: =+(G61/30)*G27*(1-'02_Pricing'!G79) -> 4266.4643 | H78: =+(H61/30)*H27*(1-'02_Pricing'!H79) -> 4266.4643 | I78: =+(I61/30)*I27*(1-'02_Pricing'!I79) -> 4266.4643 | J78: =+(J61/30)*J27*(1-'02_Pricing'!J79) -> 4266.4643 | ... O78: =+(O61/30)*O27*(1-'02_Pricing'!O79) -> 4266.4643 | P78: =SUM(D78:O78) -> 51197.572
B79: Cuidado Bucal | C79: =+(C62/30)*C28*(1-'02_Pricing'!C80) -> 1668.362 | D79: =+(D62/30)*D28*(1-'02_Pricing'!D80) -> 1429.6136 | E79: =+(E62/30)*E28*(1-'02_Pricing'!E80) -> 1429.6136 | F79: =+(F62/30)*F28*(1-'02_Pricing'!F80) -> 1429.6136 | G79: =+(G62/30)*G28*(1-'02_Pricing'!G80) -> 1429.6136 | H79: =+(H62/30)*H28*(1-'02_Pricing'!H80) -> 1429.6136 | I79: =+(I62/30)*I28*(1-'02_Pricing'!I80) -> 1429.6136 | J79: =+(J62/30)*J28*(1-'02_Pricing'!J80) -> 1429.6136 | ... O79: =+(O62/30)*O28*(1-'02_Pricing'!O80) -> 1429.6136 | P79: =SUM(D79:O79) -> 17155.364
B80: Cuidado Piel | C80: =+(C63/30)*C29*(1-'02_Pricing'!C81) -> 3046.5741 | D80: =+(D63/30)*D29*(1-'02_Pricing'!D81) -> 2682.2038 | E80: =+(E63/30)*E29*(1-'02_Pricing'!E81) -> 2682.2038 | F80: =+(F63/30)*F29*(1-'02_Pricing'!F81) -> 2682.2038 | G80: =+(G63/30)*G29*(1-'02_Pricing'!G81) -> 2682.2038 | H80: =+(H63/30)*H29*(1-'02_Pricing'!H81) -> 2682.2038 | I80: =+(I63/30)*I29*(1-'02_Pricing'!I81) -> 2682.2038 | J80: =+(J63/30)*J29*(1-'02_Pricing'!J81) -> 2682.2038 | ... O80: =+(O63/30)*O29*(1-'02_Pricing'!O81) -> 2682.2038 | P80: =SUM(D80:O80) -> 32186.446
B81: Bebe y Mama | C81: =+(C64/30)*C30*(1-'02_Pricing'!C82) -> 1558.5553 | D81: =+(D64/30)*D30*(1-'02_Pricing'!D82) -> 1349.3066 | E81: =+(E64/30)*E30*(1-'02_Pricing'!E82) -> 1349.3066 | F81: =+(F64/30)*F30*(1-'02_Pricing'!F82) -> 1349.3066 | G81: =+(G64/30)*G30*(1-'02_Pricing'!G82) -> 1349.3066 | H81: =+(H64/30)*H30*(1-'02_Pricing'!H82) -> 1349.3066 | I81: =+(I64/30)*I30*(1-'02_Pricing'!I82) -> 1349.3066 | J81: =+(J64/30)*J30*(1-'02_Pricing'!J82) -> 1349.3066 | ... O81: =+(O64/30)*O30*(1-'02_Pricing'!O82) -> 1349.3066 | P81: =SUM(D81:O81) -> 16191.68
B82: Cuidado Cabello | C82: =+(C65/30)*C31*(1-'02_Pricing'!C83) -> 1907.6523 | D82: =+(D65/30)*D31*(1-'02_Pricing'!D83) -> 1662.8271 | E82: =+(E65/30)*E31*(1-'02_Pricing'!E83) -> 1662.8271 | F82: =+(F65/30)*F31*(1-'02_Pricing'!F83) -> 1662.8271 | G82: =+(G65/30)*G31*(1-'02_Pricing'!G83) -> 1662.8271 | H82: =+(H65/30)*H31*(1-'02_Pricing'!H83) -> 1662.8271 | I82: =+(I65/30)*I31*(1-'02_Pricing'!I83) -> 1662.8271 | J82: =+(J65/30)*J31*(1-'02_Pricing'!J83) -> 1662.8271 | ... O82: =+(O65/30)*O31*(1-'02_Pricing'!O83) -> 1662.8271 | P82: =SUM(D82:O82) -> 19953.926
B83: Cuidado Personal | C83: =+(C66/30)*C32*(1-'02_Pricing'!C84) -> 2324.9512 | D83: =+(D66/30)*D32*(1-'02_Pricing'!D84) -> 2030.8801 | E83: =+(E66/30)*E32*(1-'02_Pricing'!E84) -> 2030.8801 | F83: =+(F66/30)*F32*(1-'02_Pricing'!F84) -> 2030.8801 | G83: =+(G66/30)*G32*(1-'02_Pricing'!G84) -> 2030.8801 | H83: =+(H66/30)*H32*(1-'02_Pricing'!H84) -> 2030.8801 | I83: =+(I66/30)*I32*(1-'02_Pricing'!I84) -> 2030.8801 | J83: =+(J66/30)*J32*(1-'02_Pricing'!J84) -> 2030.8801 | ... O83: =+(O66/30)*O32*(1-'02_Pricing'!O84) -> 2030.8801 | P83: =SUM(D83:O83) -> 24370.561
B84: Dermocosmetica | C84: =+(C67/30)*C33*(1-'02_Pricing'!C85) -> 4660.9148 | D84: =+(D67/30)*D33*(1-'02_Pricing'!D85) -> 4169.6544 | E84: =+(E67/30)*E33*(1-'02_Pricing'!E85) -> 4169.6544 | F84: =+(F67/30)*F33*(1-'02_Pricing'!F85) -> 4169.6544 | G84: =+(G67/30)*G33*(1-'02_Pricing'!G85) -> 4169.6544 | H84: =+(H67/30)*H33*(1-'02_Pricing'!H85) -> 4169.6544 | I84: =+(I67/30)*I33*(1-'02_Pricing'!I85) -> 4169.6544 | J84: =+(J67/30)*J33*(1-'02_Pricing'!J85) -> 4169.6544 | ... O84: =+(O67/30)*O33*(1-'02_Pricing'!O85) -> 4169.6544 | P84: =SUM(D84:O84) -> 50035.853
B86: TOTAL / POND. | C86: =SUM(C74:C84) -> 41385.114 | D86: =SUM(D74:D84) -> 35902.136 | E86: =SUM(E74:E84) -> 35902.136 | F86: =SUM(F74:F84) -> 35902.136 | G86: =SUM(G74:G84) -> 35902.136 | H86: =SUM(H74:H84) -> 35902.136 | I86: =SUM(I74:I84) -> 35902.136 | J86: =SUM(J74:J84) -> 35902.136 | ... O86: =SUM(O74:O84) -> 35902.136 | P86: =SUM(D86:O86) -> 430825.64
B88: Liberación Caja (ARS MM)
B90: Categoria | C90: Mes 0 | D90: Mes 1 | E90: Mes 2 | F90: Mes 3 | G90: Mes 4 | H90: Mes 5 | I90: Mes 6 | J90: Mes 7 | K90: Mes 8 | L90: Mes 9 | M90: Mes 10 | N90: Mes 11 | O90: Mes 12 | P90: Total
B91: Medicamentos | D91: =+D74-C74 -> -2003.5814 | E91: =+E74-D74 -> 0 | F91: =+F74-E74 -> 0 | G91: =+G74-F74 -> 0 | H91: =+H74-G74 -> 0 | I91: =+I74-H74 -> 0 | J91: =+J74-I74 -> 0 | K91: =+K74-J74 -> 0 | ... O91: =+O74-N74 -> 0 | P91: =SUM(D91:O91) -> -2003.5814
B92: Nutricion | D92: =+D75-C75 -> -283.77462 | E92: =+E75-D75 -> 0 | F92: =+F75-E75 -> 0 | G92: =+G75-F75 -> 0 | H92: =+H75-G75 -> 0 | I92: =+I75-H75 -> 0 | J92: =+J75-I75 -> 0 | K92: =+K75-J75 -> 0 | ... O92: =+O75-N75 -> 0 | P92: =SUM(D92:O92) -> -283.77462
B93: Parafarmacia | D93: =+D76-C76 -> -362.9742 | E93: =+E76-D76 -> 0 | F93: =+F76-E76 -> 0 | G93: =+G76-F76 -> 0 | H93: =+H76-G76 -> 0 | I93: =+I76-H76 -> 0 | J93: =+J76-I76 -> 0 | K93: =+K76-J76 -> 0 | ... O93: =+O76-N76 -> 0 | P93: =SUM(D93:O93) -> -362.9742
B94: Suplementos | D94: =+D77-C77 -> -304.02942 | E94: =+E77-D77 -> 0 | F94: =+F77-E77 -> 0 | G94: =+G77-F77 -> 0 | H94: =+H77-G77 -> 0 | I94: =+I77-H77 -> 0 | J94: =+J77-I77 -> 0 | K94: =+K77-J77 -> 0 | ... O94: =+O77-N77 -> 0 | P94: =SUM(D94:O94) -> -304.02942
B95: Venta Libre | D95: =+D78-C78 -> -686.09448 | E95: =+E78-D78 -> 0 | F95: =+F78-E78 -> 0 | G95: =+G78-F78 -> 0 | H95: =+H78-G78 -> 0 | I95: =+I78-H78 -> 0 | J95: =+J78-I78 -> 0 | K95: =+K78-J78 -> 0 | ... O95: =+O78-N78 -> 0 | P95: =SUM(D95:O95) -> -686.09448
B96: Cuidado Bucal | D96: =+D79-C79 -> -238.74835 | E96: =+E79-D79 -> 0 | F96: =+F79-E79 -> 0 | G96: =+G79-F79 -> 0 | H96: =+H79-G79 -> 0 | I96: =+I79-H79 -> 0 | J96: =+J79-I79 -> 0 | K96: =+K79-J79 -> 0 | ... O96: =+O79-N79 -> 0 | P96: =SUM(D96:O96) -> -238.74835
B97: Cuidado Piel | D97: =+D80-C80 -> -364.37026 | E97: =+E80-D80 -> 0 | F97: =+F80-E80 -> 0 | G97: =+G80-F80 -> 0 | H97: =+H80-G80 -> 0 | I97: =+I80-H80 -> 0 | J97: =+J80-I80 -> 0 | K97: =+K80-J80 -> 0 | ... O97: =+O80-N80 -> 0 | P97: =SUM(D97:O97) -> -364.37026
B98: Bebe y Mama | D98: =+D81-C81 -> -209.24861 | E98: =+E81-D81 -> 0 | F98: =+F81-E81 -> 0 | G98: =+G81-F81 -> 0 | H98: =+H81-G81 -> 0 | I98: =+I81-H81 -> 0 | J98: =+J81-I81 -> 0 | K98: =+K81-J81 -> 0 | ... O98: =+O81-N81 -> 0 | P98: =SUM(D98:O98) -> -209.24861
B99: Cuidado Cabello | D99: =+D82-C82 -> -244.82516 | E99: =+E82-D82 -> 0 | F99: =+F82-E82 -> 0 | G99: =+G82-F82 -> 0 | H99: =+H82-G82 -> 0 | I99: =+I82-H82 -> 0 | J99: =+J82-I82 -> 0 | K99: =+K82-J82 -> 0 | ... O99: =+O82-N82 -> 0 | P99: =SUM(D99:O99) -> -244.82516
B100: Cuidado Personal | D100: =+D83-C83 -> -294.0711 | E100: =+E83-D83 -> 0 | F100: =+F83-E83 -> 0 | G100: =+G83-F83 -> 0 | H100: =+H83-G83 -> 0 | I100: =+I83-H83 -> 0 | J100: =+J83-I83 -> 0 | K100: =+K83-J83 -> 0 | ... O100: =+O83-N83 -> 0 | P100: =SUM(D100:O100) -> -294.0711
B101: Dermocosmetica | D101: =+D84-C84 -> -491.26042 | E101: =+E84-D84 -> 0 | F101: =+F84-E84 -> 0 | G101: =+G84-F84 -> 0 | H101: =+H84-G84 -> 0 | I101: =+I84-H84 -> 0 | J101: =+J84-I84 -> 0 | K101: =+K84-J84 -> 0 | ... O101: =+O84-N84 -> 0 | P101: =SUM(D101:O101) -> -491.26042
B103: TOTAL / POND. | D103: =SUM(D91:D101) -> -5482.9781 | E103: =SUM(E91:E101) -> 0 | F103: =SUM(F91:F101) -> 0 | G103: =SUM(G91:G101) -> 0 | H103: =SUM(H91:H101) -> 0 | I103: =SUM(I91:I101) -> 0 | J103: =SUM(J91:J101) -> 0 | K103: =SUM(K91:K101) -> 0 | ... O103: =SUM(O91:O101) -> 0 | P103: =SUM(D103:O103) -> -5482.9781

Sheet 04_Digital_Logistica
B3: Simulador 3 - Digital, Fulfillment y Cost-to-Serve
B5: Mix % Canal / Modelo | C5: Mes 0 | D5: Mes 1 | E5: Mes 2 | F5: Mes 3 | G5: Mes 4 | H5: Mes 5 | I5: Mes 6 | J5: Mes 7 | K5: Mes 8 | L5: Mes 9 | M5: Mes 10 | N5: Mes 11 | O5: Mes 12 | P5: Costo-to-Serve % | Q5: SLA Prometido | R5: Penalidad SLA | S5: Costo Logistico (ARS MM) | T5: Score Servicio
B7: Tienda Fisica | C7: =100%-C8-C9-C10 -> 0.84356451 | D7: =100%-D8-D9-D10 -> 0.83280023 | E7: =100%-E8-E9-E10 -> 0.83227555 | F7: =100%-F8-F9-F10 -> 0.83250594 | G7: =100%-G8-G9-G10 -> 0.8317604 | H7: =100%-H8-H9-H10 -> 0.83103388 | I7: =100%-I8-I9-I10 -> 0.81244533 | J7: =100%-J8-J9-J10 -> 0.81284635 | ... O7: =100%-O8-O9-O10 -> 0.76214625 | P7: 0.025 | Q7: Inmediato | R7: 0 | S7: ='01_Master_Variables'!C6*C7*(P7+R7) -> 632.3465 | T7: =MAX(0,100-(P7+R7)*300) -> 92.5
B8: Delivery | C8: 0.05 | D8: 0.05 | E8: 0.05 | F8: 0.05 | G8: 0.05 | H8: 0.05 | I8: 0.05 | J8: 0.05 | K8: 0.05 | L8: 0.05 | M8: 0.05 | N8: 0.05 | O8: 0.05 | P8: 0.12 | Q8: 24/48 hs | R8: 0 | S8: ='01_Master_Variables'!C6*C8*(P8+R8) -> 179.907 | T8: =MAX(0,100-(P8+R8)*300) -> 64
B9: Pick-up | C9: 0.07 | D9: 0.08 | E9: 0.08 | F9: 0.08 | G9: 0.08 | H9: 0.08 | I9: 0.08 | J9: 0.08 | K9: 0.08 | L9: 0.08 | M9: 0.08 | N9: 0.08 | O9: 0.08 | P9: 0.055 | Q9: 4 hs | R9: 0 | S9: ='01_Master_Variables'!C6*C9*(P9+R9) -> 115.44033 | T9: =MAX(0,100-(P9+R9)*300) -> 83.5
B10: Hub/Dark Store | C10: =+('07_PL_TiposPDV'!D25+'07_PL_TiposPDV'!D26)/'01_Master_Variables'!C6 -> 0.036435492 | D10: =+('07_PL_TiposPDV'!E25+'07_PL_TiposPDV'!E26)/'01_Master_Variables'!D6 -> 0.037199767 | E10: =+('07_PL_TiposPDV'!F25+'07_PL_TiposPDV'!F26)/'01_Master_Variables'!E6 -> 0.037724449 | F10: =+('07_PL_TiposPDV'!G25+'07_PL_TiposPDV'!G26)/'01_Master_Variables'!F6 -> 0.037494059 | G10: =+('07_PL_TiposPDV'!H25+'07_PL_TiposPDV'!H26)/'01_Master_Variables'!G6 -> 0.038239604 | H10: =+('07_PL_TiposPDV'!I25+'07_PL_TiposPDV'!I26)/'01_Master_Variables'!H6 -> 0.03896612 | I10: =+('07_PL_TiposPDV'!J25+'07_PL_TiposPDV'!J26)/'01_Master_Variables'!I6 -> 0.057554672 | J10: =+('07_PL_TiposPDV'!K25+'07_PL_TiposPDV'!K26)/'01_Master_Variables'!J6 -> 0.057153652 | ... O10: =+('07_PL_TiposPDV'!P25+'07_PL_TiposPDV'!P26)/'01_Master_Variables'!O6 -> 0.10785375 | P10: 0.085 | Q10: Same day | R10: 0.01 | S10: ='01_Master_Variables'!C6*C10*(P10+R10) -> 103.7875 | T10: =MAX(0,100-(P10+R10)*300) -> 71.5
B12: TOTAL / CONTROL | C12: =SUM(C7:C10) -> 1 | D12: =SUM(D7:D10) -> 1 | E12: =SUM(E7:E10) -> 1 | F12: =SUM(F7:F10) -> 1 | G12: =SUM(G7:G10) -> 1 | H12: =SUM(H7:H10) -> 1 | I12: =SUM(I7:I10) -> 1 | J12: =SUM(J7:J10) -> 1 | ... O12: =SUM(O7:O10) -> 1 | P12: =SUMPRODUCT(C7:C10,P7:P10) -> 0.03403613 | S12: =SUM(S7:S10) -> 1031.4813 | T12: =SUMPRODUCT(T7:T10,#REF!) -> #REF!
P13: =+(C7*P7+P9*C9)/(C7+C9) -> 0.027298688
B15: Costo Logistico (ARS MM) | C15: Mes 0 | D15: Mes 1 | E15: Mes 2 | F15: Mes 3 | G15: Mes 4 | H15: Mes 5 | I15: Mes 6 | J15: Mes 7 | K15: Mes 8 | L15: Mes 9 | M15: Mes 10 | N15: Mes 11 | O15: Mes 12 | P15: Total
B16: Tienda Fisica | C16: =+'01_Master_Variables'!C$6*'04_Digital_Logistica'!C7*('04_Digital_Logistica'!$P7+'04_Digital_Logistica'!$R7) -> 632.3465 | D16: =+'01_Master_Variables'!D$6*'04_Digital_Logistica'!D7*('04_Digital_Logistica'!$P7+'04_Digital_Logistica'!$R7) -> 611.45159 | E16: =+'01_Master_Variables'!E$6*'04_Digital_Logistica'!E7*('04_Digital_Logistica'!$P7+'04_Digital_Logistica'!$R7) -> 602.56747 | F16: =+'01_Master_Variables'!F$6*'04_Digital_Logistica'!F7*('04_Digital_Logistica'!$P7+'04_Digital_Logistica'!$R7) -> 606.4379 | G16: =+'01_Master_Variables'!G$6*'04_Digital_Logistica'!G7*('04_Digital_Logistica'!$P7+'04_Digital_Logistica'!$R7) -> 594.08187 | H16: =+'01_Master_Variables'!H$6*'04_Digital_Logistica'!H7*('04_Digital_Logistica'!$P7+'04_Digital_Logistica'!$R7) -> 582.4961 | I16: =+'01_Master_Variables'!I$6*'04_Digital_Logistica'!I7*('04_Digital_Logistica'!$P7+'04_Digital_Logistica'!$R7) -> 569.93601 | J16: =+'01_Master_Variables'!J$6*'04_Digital_Logistica'!J7*('04_Digital_Logistica'!$P7+'04_Digital_Logistica'!$R7) -> 574.21828 | ... O16: =+'01_Master_Variables'!O$6*'04_Digital_Logistica'!O7*('04_Digital_Logistica'!$P7+'04_Digital_Logistica'!$R7) -> 562.22674 | P16: =SUM(D16:O16) -> 6960.4579
B17: Delivery | C17: =+'01_Master_Variables'!C$6*'04_Digital_Logistica'!C8*('04_Digital_Logistica'!$P8+'04_Digital_Logistica'!$R8) -> 179.907 | D17: =+'01_Master_Variables'!D$6*'04_Digital_Logistica'!D8*('04_Digital_Logistica'!$P8+'04_Digital_Logistica'!$R8) -> 176.21078 | E17: =+'01_Master_Variables'!E$6*'04_Digital_Logistica'!E8*('04_Digital_Logistica'!$P8+'04_Digital_Logistica'!$R8) -> 173.75999 | F17: =+'01_Master_Variables'!F$6*'04_Digital_Logistica'!F8*('04_Digital_Logistica'!$P8+'04_Digital_Logistica'!$R8) -> 174.8277 | G17: =+'01_Master_Variables'!G$6*'04_Digital_Logistica'!G8*('04_Digital_Logistica'!$P8+'04_Digital_Logistica'!$R8) -> 171.41914 | H17: =+'01_Master_Variables'!H$6*'04_Digital_Logistica'!H8*('04_Digital_Logistica'!$P8+'04_Digital_Logistica'!$R8) -> 168.22306 | I17: =+'01_Master_Variables'!I$6*'04_Digital_Logistica'!I8*('04_Digital_Logistica'!$P8+'04_Digital_Logistica'!$R8) -> 168.36166 | J17: =+'01_Master_Variables'!J$6*'04_Digital_Logistica'!J8*('04_Digital_Logistica'!$P8+'04_Digital_Logistica'!$R8) -> 169.54297 | ... O17: =+'01_Master_Variables'!O$6*'04_Digital_Logistica'!O8*('04_Digital_Logistica'!$P8+'04_Digital_Logistica'!$R8) -> 177.04531 | P17: =SUM(D17:O17) -> 2068.1953
B18: Pick-up | C18: =+'01_Master_Variables'!C$6*'04_Digital_Logistica'!C9*('04_Digital_Logistica'!$P9+'04_Digital_Logistica'!$R9) -> 115.44033 | D18: =+'01_Master_Variables'!D$6*'04_Digital_Logistica'!D9*('04_Digital_Logistica'!$P9+'04_Digital_Logistica'!$R9) -> 129.22124 | E18: =+'01_Master_Variables'!E$6*'04_Digital_Logistica'!E9*('04_Digital_Logistica'!$P9+'04_Digital_Logistica'!$R9) -> 127.42399 | F18: =+'01_Master_Variables'!F$6*'04_Digital_Logistica'!F9*('04_Digital_Logistica'!$P9+'04_Digital_Logistica'!$R9) -> 128.20698 | G18: =+'01_Master_Variables'!G$6*'04_Digital_Logistica'!G9*('04_Digital_Logistica'!$P9+'04_Digital_Logistica'!$R9) -> 125.70737 | H18: =+'01_Master_Variables'!H$6*'04_Digital_Logistica'!H9*('04_Digital_Logistica'!$P9+'04_Digital_Logistica'!$R9) -> 123.36358 | I18: =+'01_Master_Variables'!I$6*'04_Digital_Logistica'!I9*('04_Digital_Logistica'!$P9+'04_Digital_Logistica'!$R9) -> 123.46522 | J18: =+'01_Master_Variables'!J$6*'04_Digital_Logistica'!J9*('04_Digital_Logistica'!$P9+'04_Digital_Logistica'!$R9) -> 124.33151 | ... O18: =+'01_Master_Variables'!O$6*'04_Digital_Logistica'!O9*('04_Digital_Logistica'!$P9+'04_Digital_Logistica'!$R9) -> 129.83323 | P18: =SUM(D18:O18) -> 1516.6765
B19: Hub/Dark Store | C19: =+'01_Master_Variables'!C$6*'04_Digital_Logistica'!C10*('04_Digital_Logistica'!$P10+'04_Digital_Logistica'!$R10) -> 103.7875 | D19: =+'01_Master_Variables'!D$6*'04_Digital_Logistica'!D10*('04_Digital_Logistica'!$P10+'04_Digital_Logistica'!$R10) -> 103.7875 | E19: =+'01_Master_Variables'!E$6*'04_Digital_Logistica'!E10*('04_Digital_Logistica'!$P10+'04_Digital_Logistica'!$R10) -> 103.7875 | F19: =+'01_Master_Variables'!F$6*'04_Digital_Logistica'!F10*('04_Digital_Logistica'!$P10+'04_Digital_Logistica'!$R10) -> 103.7875 | G19: =+'01_Master_Variables'!G$6*'04_Digital_Logistica'!G10*('04_Digital_Logistica'!$P10+'04_Digital_Logistica'!$R10) -> 103.7875 | H19: =+'01_Master_Variables'!H$6*'04_Digital_Logistica'!H10*('04_Digital_Logistica'!$P10+'04_Digital_Logistica'!$R10) -> 103.7875 | I19: =+'01_Master_Variables'!I$6*'04_Digital_Logistica'!I10*('04_Digital_Logistica'!$P10+'04_Digital_Logistica'!$R10) -> 153.425 | J19: =+'01_Master_Variables'!J$6*'04_Digital_Logistica'!J10*('04_Digital_Logistica'!$P10+'04_Digital_Logistica'!$R10) -> 153.425 | ... O19: =+'01_Master_Variables'!O$6*'04_Digital_Logistica'!O10*('04_Digital_Logistica'!$P10+'04_Digital_Logistica'!$R10) -> 302.3375 | P19: =SUM(D19:O19) -> 2039.65
C20: =SUM(C16:C19) -> 1031.4813 | D20: =SUM(D16:D19) -> 1020.6711 | E20: =SUM(E16:E19) -> 1007.539 | F20: =SUM(F16:F19) -> 1013.2601 | G20: =SUM(G16:G19) -> 994.99588 | H20: =SUM(H16:H19) -> 977.87025 | I20: =SUM(I16:I19) -> 1015.1879 | J20: =SUM(J16:J19) -> 1021.5178 | ... O20: =SUM(O16:O19) -> 1171.4428 | P20: =SUM(D20:O20) -> 12584.98
B26: Criterios Digital
B27: Delivery es un % target configurable; no debe asumirse gratis.
B28: Apertura/cierre de PDV modifica venta y costo logístico por zona.
B29: Hubs/Dark Store priorizan Éticos y eficiencia de última milla.

Sheet 05_CLV_Marketing
B2: Simulador 4 - CLV, Segmentacion y Marketing
B4: Segmento | C4: # Clientes Base | D4: Ticket Promedio | E4: Frecuencia Mensual | F4: Consumo Mensual | G4: Churn Base %
B5: VIPs | C5: 552631.58 | D5: =7092*2.5 -> 17730 | E5: 1.8 | F5: =+E5*D5 -> 31914 | G5: 0.015
B6: Riesgo Fuga | C6: 1105263.2 | D6: =7092*1.26 -> 8935.92 | E6: 0.9 | F6: =+E6*D6 -> 8042.328 | G6: 0.06
B7: Oportunistas | C7: 1842105.3 | D7: =7092*0.6 -> 4255.2 | E7: 0.45 | F7: =+E7*D7 -> 1914.84 | G7: 0.08
B8: TOTAL | C8: =SUM(C5:C7) -> 3500000 | D8: =SUMPRODUCT(D5:D7,$C$5:$C$7)/$C$8 -> 7860.9221 | E8: =SUMPRODUCT(E5:E7,$C$5:$C$7)/$C$8 -> 0.80526316 | F8: =SUMPRODUCT(F5:F7,$C$5:$C$7)/$C$8 -> 8586.5457 | G8: =SUMPRODUCT(G5:G7,C5:C7)/SUM(C5:C7) -> 0.063421053
B10: Churn Base % | C10: Mes 0 | D10: Mes 1 | E10: Mes 2 | F10: Mes 3 | G10: Mes 4 | H10: Mes 5 | I10: Mes 6 | J10: Mes 7 | K10: Mes 8 | L10: Mes 9 | M10: Mes 10 | N10: Mes 11 | O10: Mes 12
B11: VIPs | C11: 0.015 | D11: 0.015 | E11: 0.015 | F11: 0.015 | G11: 0.015 | H11: 0.015 | I11: 0.015 | J11: 0.015 | K11: 0.015 | L11: 0.015 | M11: 0.015 | N11: 0.015 | O11: 0.015
B12: Riesgo Fuga | C12: 0.06 | D12: 0.06 | E12: 0.06 | F12: 0.06 | G12: 0.06 | H12: 0.06 | I12: 0.06 | J12: 0.06 | K12: 0.06 | L12: 0.06 | M12: 0.06 | N12: 0.06 | O12: 0.06
B13: Oportunistas | C13: 0.08 | D13: 0.08 | E13: 0.08 | F13: 0.08 | G13: 0.08 | H13: 0.08 | I13: 0.08 | J13: 0.08 | K13: 0.08 | L13: 0.08 | M13: 0.08 | N13: 0.08 | O13: 0.08
B14: Nuevos
C15: =SUMPRODUCT(C11:C14,$C$39:$C$42)/$C$43 -> 0.063421053 | D15: =SUMPRODUCT(D11:D14,$C$39:$C$42)/$C$43 -> 0.063421053 | E15: =SUMPRODUCT(E11:E14,$C$39:$C$42)/$C$43 -> 0.063421053 | F15: =SUMPRODUCT(F11:F14,$C$39:$C$42)/$C$43 -> 0.063421053 | G15: =SUMPRODUCT(G11:G14,$C$39:$C$42)/$C$43 -> 0.063421053 | H15: =SUMPRODUCT(H11:H14,$C$39:$C$42)/$C$43 -> 0.063421053 | I15: =SUMPRODUCT(I11:I14,$C$39:$C$42)/$C$43 -> 0.063421053 | J15: =SUMPRODUCT(J11:J14,$C$39:$C$42)/$C$43 -> 0.063421053 | ... O15: =SUMPRODUCT(O11:O14,$C$39:$C$42)/$C$43 -> 0.063421053
B17: Foco Retención % | C17: Mes 0 | D17: Mes 1 | E17: Mes 2 | F17: Mes 3 | G17: Mes 4 | H17: Mes 5 | I17: Mes 6 | J17: Mes 7 | K17: Mes 8 | L17: Mes 9 | M17: Mes 10 | N17: Mes 11 | O17: Mes 12
B18: VIPs | D18: 0.5 | E18: 0.5 | F18: 0.5 | G18: 0.5 | H18: 0.5 | I18: 0.5 | J18: 0.5 | K18: 0.5 | L18: 0.5 | M18: 0.5 | N18: 0.5 | O18: 0.5
B19: Riesgo Fuga | D19: 0.5 | E19: 0.5 | F19: 0.5 | G19: 0.5 | H19: 0.5 | I19: 0.5 | J19: 0.5 | K19: 0.5 | L19: 0.5 | M19: 0.5 | N19: 0.5 | O19: 0.5
B20: Oportunistas | D20: 0 | E20: 0 | F20: 0 | G20: 0 | H20: 0 | I20: 0 | J20: 0 | K20: 0 | L20: 0 | M20: 0 | N20: 0 | O20: 0
B21: Nuevos
C22: =SUM(C18:C21) -> 0 | D22: =SUM(D18:D21) -> 1 | E22: =SUM(E18:E21) -> 1 | F22: =SUM(F18:F21) -> 1 | G22: =SUM(G18:G21) -> 1 | H22: =SUM(H18:H21) -> 1 | I22: =SUM(I18:I21) -> 1 | J22: =SUM(J18:J21) -> 1 | ... O22: =SUM(O18:O21) -> 1
B24: Churn Ajustado % | C24: Mes 0 | D24: Mes 1 | E24: Mes 2 | F24: Mes 3 | G24: Mes 4 | H24: Mes 5 | I24: Mes 6 | J24: Mes 7 | K24: Mes 8 | L24: Mes 9 | M24: Mes 10 | N24: Mes 11 | O24: Mes 12
B25: VIPs | D25: =MAX(0,+D11*(1-D18*0.5)) -> 0.01125 | E25: =MAX(0,+E11*(1-E18*0.5)) -> 0.01125 | F25: =MAX(0,+F11*(1-F18*0.5)) -> 0.01125 | G25: =MAX(0,+G11*(1-G18*0.5)) -> 0.01125 | H25: =MAX(0,+H11*(1-H18*0.5)) -> 0.01125 | I25: =MAX(0,+I11*(1-I18*0.5)) -> 0.01125 | J25: =MAX(0,+J11*(1-J18*0.5)) -> 0.01125 | K25: =MAX(0,+K11*(1-K18*0.5)) -> 0.01125 | ... O25: =MAX(0,+O11*(1-O18*0.5)) -> 0.01125
B26: Riesgo Fuga | D26: =MAX(0,+D12*(1-D19*0.5)) -> 0.045 | E26: =MAX(0,+E12*(1-E19*0.5)) -> 0.045 | F26: =MAX(0,+F12*(1-F19*0.5)) -> 0.045 | G26: =MAX(0,+G12*(1-G19*0.5)) -> 0.045 | H26: =MAX(0,+H12*(1-H19*0.5)) -> 0.045 | I26: =MAX(0,+I12*(1-I19*0.5)) -> 0.045 | J26: =MAX(0,+J12*(1-J19*0.5)) -> 0.045 | K26: =MAX(0,+K12*(1-K19*0.5)) -> 0.045 | ... O26: =MAX(0,+O12*(1-O19*0.5)) -> 0.045
B27: Oportunistas | D27: =MAX(0,+D13*(1-D20*0.5)) -> 0.08 | E27: =MAX(0,+E13*(1-E20*0.5)) -> 0.08 | F27: =MAX(0,+F13*(1-F20*0.5)) -> 0.08 | G27: =MAX(0,+G13*(1-G20*0.5)) -> 0.08 | H27: =MAX(0,+H13*(1-H20*0.5)) -> 0.08 | I27: =MAX(0,+I13*(1-I20*0.5)) -> 0.08 | J27: =MAX(0,+J13*(1-J20*0.5)) -> 0.08 | K27: =MAX(0,+K13*(1-K20*0.5)) -> 0.08 | ... O27: =MAX(0,+O13*(1-O20*0.5)) -> 0.08
B28: Nuevos
D29: =SUMPRODUCT(D25:D27,D39:D41)/SUM(D39:D41) -> 0.057398634 | E29: =SUMPRODUCT(E25:E27,E39:E41)/SUM(E39:E41) -> 0.056693341 | F29: =SUMPRODUCT(F25:F27,F39:F41)/SUM(F39:F41) -> 0.055976769 | G29: =SUMPRODUCT(G25:G27,G39:G41)/SUM(G39:G41) -> 0.055249515 | H29: =SUMPRODUCT(H25:H27,H39:H41)/SUM(H39:H41) -> 0.054512217 | I29: =SUMPRODUCT(I25:I27,I39:I41)/SUM(I39:I41) -> 0.053765562 | J29: =SUMPRODUCT(J25:J27,J39:J41)/SUM(J39:J41) -> 0.053010277 | K29: =SUMPRODUCT(K25:K27,K39:K41)/SUM(K39:K41) -> 0.052247132 | ... O29: =SUMPRODUCT(O25:O27,O39:O41)/SUM(O39:O41) -> 0.049132538
B31: Clientes Base | C31: Mes 0 | D31: Mes 1 | E31: Mes 2 | F31: Mes 3 | G31: Mes 4 | H31: Mes 5 | I31: Mes 6 | J31: Mes 7 | K31: Mes 8 | L31: Mes 9 | M31: Mes 10 | N31: Mes 11 | O31: Mes 12
B32: VIPs | C32: =+C5 -> 552631.58 | D32: =+C32*(1-D11) -> 544342.11 | E32: =+D32*(1-E11) -> 536176.97 | F32: =+E32*(1-F11) -> 528134.32 | G32: =+F32*(1-G11) -> 520212.3 | H32: =+G32*(1-H11) -> 512409.12 | I32: =+H32*(1-I11) -> 504722.98 | J32: =+I32*(1-J11) -> 497152.14 | K32: =+J32*(1-K11) -> 489694.86 | ... O32: =+N32*(1-O11) -> 460967.67
B33: Riesgo Fuga | C33: =+C6 -> 1105263.2 | D33: =+C33*(1-D12) -> 1038947.4 | E33: =+D33*(1-E12) -> 976610.53 | F33: =+E33*(1-F12) -> 918013.89 | G33: =+F33*(1-G12) -> 862933.06 | H33: =+G33*(1-H12) -> 811157.08 | I33: =+H33*(1-I12) -> 762487.65 | J33: =+I33*(1-J12) -> 716738.39 | K33: =+J33*(1-K12) -> 673734.09 | ... O33: =+N33*(1-O12) -> 526017.19
B34: Oportunistas | C34: =+C7 -> 1842105.3 | D34: =+C34*(1-D13) -> 1694736.8 | E34: =+D34*(1-E13) -> 1559157.9 | F34: =+E34*(1-F13) -> 1434425.3 | G34: =+F34*(1-G13) -> 1319671.2 | H34: =+G34*(1-H13) -> 1214097.5 | I34: =+H34*(1-I13) -> 1116969.7 | J34: =+I34*(1-J13) -> 1027612.2 | K34: =+J34*(1-K13) -> 945403.19 | ... O34: =+N34*(1-O13) -> 677280.19
B35: Nuevos
C36: =SUM(C32:C35) -> 3500000 | D36: =SUM(D32:D35) -> 3278026.3 | E36: =SUM(E32:E35) -> 3071945.4 | F36: =SUM(F32:F35) -> 2880573.5 | G36: =SUM(G32:G35) -> 2702816.6 | H36: =SUM(H32:H35) -> 2537663.7 | I36: =SUM(I32:I35) -> 2384180.4 | J36: =SUM(J32:J35) -> 2241502.7 | ... O36: =SUM(O32:O35) -> 1664265
B38: Clientes Finales | C38: Mes 0 | D38: Mes 1 | E38: Mes 2 | F38: Mes 3 | G38: Mes 4 | H38: Mes 5 | I38: Mes 6 | J38: Mes 7 | K38: Mes 8 | L38: Mes 9 | M38: Mes 10 | N38: Mes 11 | O38: Mes 12
B39: VIPs | C39: =+C5 -> 552631.58 | D39: =+C39*(1-D25) -> 546414.47 | E39: =+D39*(1-E25) -> 540267.31 | F39: =+E39*(1-F25) -> 534189.3 | G39: =+F39*(1-G25) -> 528179.67 | H39: =+G39*(1-H25) -> 522237.65 | I39: =+H39*(1-I25) -> 516362.48 | J39: =+I39*(1-J25) -> 510553.4 | K39: =+J39*(1-K25) -> 504809.68 | ... O39: =+N39*(1-O25) -> 482473.71 | P39: =+O39/C39-1 -> -0.12695233
B40: Riesgo Fuga | C40: =+C6 -> 1105263.2 | D40: =+C40*(1-D26) -> 1055526.3 | E40: =+D40*(1-E26) -> 1008027.6 | F40: =+E40*(1-F26) -> 962666.39 | G40: =+F40*(1-G26) -> 919346.4 | H40: =+G40*(1-H26) -> 877975.81 | I40: =+H40*(1-I26) -> 838466.9 | J40: =+I40*(1-J26) -> 800735.89 | K40: =+J40*(1-K26) -> 764702.78 | ... O40: =+N40*(1-O26) -> 636071.82 | P40: =+O40/C40-1 -> -0.42450645
B41: Oportunistas | C41: =+C7 -> 1842105.3 | D41: =+C41*(1-D27) -> 1694736.8 | E41: =+D41*(1-E27) -> 1559157.9 | F41: =+E41*(1-F27) -> 1434425.3 | G41: =+F41*(1-G27) -> 1319671.2 | H41: =+G41*(1-H27) -> 1214097.5 | I41: =+H41*(1-I27) -> 1116969.7 | J41: =+I41*(1-J27) -> 1027612.2 | K41: =+J41*(1-K27) -> 945403.19 | ... O41: =+N41*(1-O27) -> 677280.19 | P41: =+O41/C41-1 -> -0.63233361
B42: Nuevos | D42: 50000 | E42: 50000 | F42: 50000 | G42: 50000 | H42: 50000 | I42: 50000 | J42: 50000 | K42: 50000 | L42: 50000 | M42: 50000 | N42: 50000 | O42: 50000
B43: TOTAL | C43: =SUM(C39:C42) -> 3500000 | D43: =SUM(D39:D42) -> 3346677.6 | E43: =SUM(E39:E42) -> 3157452.8 | F43: =SUM(F39:F42) -> 2981281 | G43: =SUM(G39:G42) -> 2817197.3 | H43: =SUM(H39:H42) -> 2664311 | I43: =SUM(I39:I42) -> 2521799.1 | J43: =SUM(J39:J42) -> 2388901.5 | ... O43: =SUM(O39:O42) -> 1845825.7
B45: Revenue Incremental (ARS MM) | C45: Mes 0 | D45: Mes 1 | E45: Mes 2 | F45: Mes 3 | G45: Mes 4 | H45: Mes 5 | I45: Mes 6 | J45: Mes 7 | K45: Mes 8 | L45: Mes 9 | M45: Mes 10 | N45: Mes 11 | O45: Mes 12 | P45: Total
B46: VIPs | D46: =+((D39-C39)*$F5)/1000000+C46 -> -198.4127 | E46: =+((E39-D39)*$F5)/1000000+D46 -> -394.59325 | F46: =+((F39-E39)*$F5)/1000000+E46 -> -588.56678 | G46: =+((G39-F39)*$F5)/1000000+F46 -> -780.3581 | H46: =+((H39-G39)*$F5)/1000000+G46 -> -969.99177 | I46: =+((I39-H39)*$F5)/1000000+H46 -> -1157.4921 | J46: =+((J39-I39)*$F5)/1000000+I46 -> -1342.883 | K46: =+((K39-J39)*$F5)/1000000+J46 -> -1526.1882 | ... O46: =+((O39-N39)*$F5)/1000000+N46 -> -2239.0181 | P46: =SUM(D46:O46) -> -14855.394
B47: Riesgo Fuga | D47: =+((D40-C40)*$F6)/1000000+C47 -> -400 | E47: =+((E40-D40)*$F6)/1000000+D47 -> -782 | F47: =+((F40-E40)*$F6)/1000000+E47 -> -1146.81 | G47: =+((G40-F40)*$F6)/1000000+F47 -> -1495.2035 | H47: =+((H40-G40)*$F6)/1000000+G47 -> -1827.9194 | I47: =+((I40-H40)*$F6)/1000000+H47 -> -2145.663 | J47: =+((J40-I40)*$F6)/1000000+I47 -> -2449.1082 | K47: =+((K40-J40)*$F6)/1000000+J47 -> -2738.8983 | ... O47: =+((O40-N40)*$F6)/1000000+N47 -> -3773.3907 | P47: =SUM(D47:O47) -> -26586.931
B48: Oportunistas | D48: =+((D41-C41)*$F7)/1000000+C48 -> -282.18695 | E48: =+((E41-D41)*$F7)/1000000+D48 -> -541.79894 | F48: =+((F41-E41)*$F7)/1000000+E48 -> -780.64197 | G48: =+((G41-F41)*$F7)/1000000+F48 -> -1000.3776 | H48: =+((H41-G41)*$F7)/1000000+G48 -> -1202.5343 | I48: =+((I41-H41)*$F7)/1000000+H48 -> -1388.5185 | J48: =+((J41-I41)*$F7)/1000000+I48 -> -1559.624 | K48: =+((K41-J41)*$F7)/1000000+J48 -> -1717.041 | ... O48: =+((O41-N41)*$F7)/1000000+N48 -> -2230.4536 | P48: =SUM(D48:O48) -> -16677.825
B49: Nuevos | D49: =+D42*$F$8/1000000 -> 429.32728 | E49: =+E42*$F$8/1000000+D49 -> 858.65457 | F49: =+F42*$F$8/1000000+E49 -> 1287.9819 | G49: =+G42*$F$8/1000000+F49 -> 1717.3091 | H49: =+H42*$F$8/1000000+G49 -> 2146.6364 | I49: =+I42*$F$8/1000000+H49 -> 2575.9637 | J49: =+J42*$F$8/1000000+I49 -> 3005.291 | K49: =+K42*$F$8/1000000+J49 -> 3434.6183 | L49: =+L42*$F$8/1000000+K49 -> 3863.9456 | ... O49: =+O42*$F$8/1000000+N49 -> 5151.9274 | P49: =SUM(D49:O49) -> 33487.528
B50: TOTAL | D50: =SUM(D46:D49) -> -451.27236 | E50: =SUM(E46:E49) -> -859.73762 | F50: =SUM(F46:F49) -> -1228.0369 | G50: =SUM(G46:G49) -> -1558.6301 | H50: =SUM(H46:H49) -> -1853.809 | I50: =SUM(I46:I49) -> -2115.7099 | J50: =SUM(J46:J49) -> -2346.3241 | K50: =SUM(K46:K49) -> -2547.5093 | ... P50: =SUM(P46:P49) -> -24632.622
B52: Budget Marketing (ARS MM) | C52: $/Cliente | D52: Mes 1 | E52: Mes 2 | F52: Mes 3 | G52: Mes 4 | H52: Mes 5 | I52: Mes 6 | J52: Mes 7 | K52: Mes 8 | L52: Mes 9 | M52: Mes 10 | N52: Mes 11 | O52: Mes 12 | P52: Total
A53: =C53/F5 -> 0.10966974 | B53: VIPs | C53: 3500 | D53: =+((D39-D32)*$C53)/1000000 -> 7.2532895 | E53: =+((E39-E32)*$C53)/1000000 -> 14.31618 | F53: =+((F39-F32)*$C53)/1000000 -> 21.192446 | G53: =+((G39-G32)*$C53)/1000000 -> 27.885794 | H53: =+((H39-H32)*$C53)/1000000 -> 34.399865 | I53: =+((I39-I32)*$C53)/1000000 -> 40.738236 | J53: =+((J39-J32)*$C53)/1000000 -> 46.90442 | K53: =+((K39-K32)*$C53)/1000000 -> 52.901867 | ... O53: =+((O39-O32)*$C53)/1000000 -> 75.271162 | P53: =SUM(D53:O53) -> 513.91665
A54: =C54/F6 -> 0.24868421 | B54: Riesgo Fuga | C54: 2000 | D54: =+((D40-D33)*$C54)/1000000 -> 33.157895 | E54: =+((E40-E33)*$C54)/1000000 -> 62.834211 | F54: =+((F40-F33)*$C54)/1000000 -> 89.304987 | G54: =+((G40-G33)*$C54)/1000000 -> 112.82668 | H54: =+((H40-H33)*$C54)/1000000 -> 133.63747 | I54: =+((I40-I33)*$C54)/1000000 -> 151.9585 | J54: =+((J40-J33)*$C54)/1000000 -> 167.99499 | K54: =+((K40-K33)*$C54)/1000000 -> 181.93737 | ... O54: =+((O40-O33)*$C54)/1000000 -> 220.10925 | P54: =SUM(D54:O54) -> 1764.8588
A55: =C55/F7 -> 0.52223684 | B55: Oportunistas | C55: 1000 | D55: =+((D41-D34)*$C55)/1000000 -> 0 | E55: =+((E41-E34)*$C55)/1000000 -> 0 | F55: =+((F41-F34)*$C55)/1000000 -> 0 | G55: =+((G41-G34)*$C55)/1000000 -> 0 | H55: =+((H41-H34)*$C55)/1000000 -> 0 | I55: =+((I41-I34)*$C55)/1000000 -> 0 | J55: =+((J41-J34)*$C55)/1000000 -> 0 | K55: =+((K41-K34)*$C55)/1000000 -> 0 | ... O55: =+((O41-O34)*$C55)/1000000 -> 0 | P55: =SUM(D55:O55) -> 0
A56: =C56/F8 -> 0.52407571 | B56: Nuevos (CAC) | C56: 4500 | D56: =+($C$56*D42)/1000000 -> 225 | E56: =+($C$56*E42)/1000000 -> 225 | F56: =+($C$56*F42)/1000000 -> 225 | G56: =+($C$56*G42)/1000000 -> 225 | H56: =+($C$56*H42)/1000000 -> 225 | I56: =+($C$56*I42)/1000000 -> 225 | J56: =+($C$56*J42)/1000000 -> 225 | K56: =+($C$56*K42)/1000000 -> 225 | ... O56: =+($C$56*O42)/1000000 -> 225 | P56: =SUM(D56:O56) -> 2700
B57: TOTAL | D57: =SUM(D53:D56) -> 265.41118 | E57: =SUM(E53:E56) -> 302.15039 | F57: =SUM(F53:F56) -> 335.49743 | G57: =SUM(G53:G56) -> 365.71247 | H57: =SUM(H53:H56) -> 393.03734 | I57: =SUM(I53:I56) -> 417.69673 | J57: =SUM(J53:J56) -> 439.89941 | K57: =SUM(K53:K56) -> 459.83924 | ... P57: =SUM(P53:P56) -> 4978.7755
B58: Budget Marketing % | D58: =+D57/'01_Master_Variables'!D6 -> 0.0090372852 | E58: =+E57/'01_Master_Variables'!E6 -> 0.01043337 | F58: =+F57/'01_Master_Variables'!F6 -> 0.011514106 | G58: =+G57/'01_Master_Variables'!G6 -> 0.012800641 | H58: =+H57/'01_Master_Variables'!H6 -> 0.014018435 | I58: =+I57/'01_Master_Variables'!I6 -> 0.014885696 | J58: =+J57/'01_Master_Variables'!J6 -> 0.015567714 | K58: =+K57/'01_Master_Variables'!K6 -> 0.016225243 | ... P58: =+P57/'01_Master_Variables'!P6 -> 0.014443826

Sheet 06_Red_CAPEX
B3: Simulador 5 - Red de PDV, Aperturas/Cierres y CAPEX
B5: Formato | C5: Zona | D5: PDV Iniciales | E5: Aperturas | F5: Cierres | G5: PDV Finales | H5: CAPEX Apertura (ARS MM) | I5: Ventas/PDV Mes (ARS MM)
B6: Flagship | C6: CABA | D6: 8 | E6: =+Q20 -> 3 | F6: =+Q48 -> 0 | G6: =SUM(D6:F6) -> 11 | H6: 5833.3333 | I6: 665
B7: Flagship | C7: GBA | D7: 6 | E7: =+Q21 -> 0 | F7: =+Q49 -> 0 | G7: =SUM(D7:F7) -> 6 | H7: 10320.513 | I7: 1092.5
B8: Standard | C8: CABA | D8: 20 | E8: =+Q22 -> 0 | F8: =+Q50 -> 0 | G8: =SUM(D8:F8) -> 20 | H8: 1125 | I8: 142.5
B9: Standard | C9: GBA | D9: 32 | E9: =+Q23 -> 0 | F9: =+Q51 -> 0 | G9: =SUM(D9:F9) -> 32 | H9: 2105.2632 | I9: 237.5
B10: Proximidad | C10: CABA | D10: 18 | E10: =+Q24 -> 0 | F10: =+Q52 -> 0 | G10: =SUM(D10:F10) -> 18 | H10: 600 | I10: 71.25
B11: Proximidad | C11: GBA | D11: 32 | E11: =+Q25 -> 0 | F11: =+Q53 -> -11 | G11: =SUM(D11:F11) -> 21 | H11: 1000 | I11: 118.75
B12: Hub/Dark Store | C12: CABA | D12: 1 | E12: =+Q26 -> 4 | F12: =+Q54 -> 0 | G12: =SUM(D12:F12) -> 5 | H12: 2000 | I12: 237.5
B13: Hub/Dark Store | C13: GBA | D13: 3 | E13: =+Q27 -> 4 | F13: =+Q55 -> 0 | G13: =SUM(D13:F13) -> 7 | H13: 2400 | I13: 285
B15: TOTAL | D15: =SUM(D6:D13) -> 120 | E15: =SUM(E6:E13) -> 11 | F15: =SUM(F6:F13) -> -11 | G15: =SUM(G6:G13) -> 120 | H15: =SUMPRODUCT(H6:H13,$D$6:$D$13)/$D$15 -> 2087.1514 | I15: =SUMPRODUCT(I6:I13,$D$6:$D$13)/$D$15 -> 237.5
B17: Aperturas # PDV
B19: Formato | C19: Zona | D19: Mes 0 | E19: Mes 1 | F19: Mes 2 | G19: Mes 3 | H19: Mes 4 | I19: Mes 5 | J19: Mes 6 | K19: Mes 7 | L19: Mes 8 | M19: Mes 9 | N19: Mes 10 | O19: Mes 11 | P19: Mes 12 | Q19: Total
B20: Flagship | C20: CABA | E20: 0 | F20: 0 | G20: 1 | H20: 0 | I20: 0 | J20: 0 | K20: 1 | L20: 0 | M20: 0 | N20: 1 | O20: 0 | P20: 0 | Q20: =SUM(E20:P20) -> 3
B21: Flagship | C21: GBA | E21: 0 | F21: 0 | G21: 0 | H21: 0 | I21: 0 | J21: 0 | K21: 0 | L21: 0 | M21: 0 | N21: 0 | O21: 0 | P21: 0 | Q21: =SUM(E21:P21) -> 0
B22: Standard | C22: CABA | E22: 0 | F22: 0 | G22: 0 | H22: 0 | I22: 0 | J22: 0 | K22: 0 | L22: 0 | M22: 0 | N22: 0 | O22: 0 | P22: 0 | Q22: =SUM(E22:P22) -> 0
B23: Standard | C23: GBA | E23: 0 | F23: 0 | G23: 0 | H23: 0 | I23: 0 | J23: 0 | K23: 0 | L23: 0 | M23: 0 | N23: 0 | O23: 0 | P23: 0 | Q23: =SUM(E23:P23) -> 0
B24: Proximidad | C24: CABA | E24: 0 | F24: 0 | G24: 0 | H24: 0 | I24: 0 | J24: 0 | K24: 0 | L24: 0 | M24: 0 | N24: 0 | O24: 0 | P24: 0 | Q24: =SUM(E24:P24) -> 0
B25: Proximidad | C25: GBA | E25: 0 | F25: 0 | G25: 0 | H25: 0 | I25: 0 | J25: 0 | K25: 0 | L25: 0 | M25: 0 | N25: 0 | O25: 0 | P25: 0 | Q25: =SUM(E25:P25) -> 0
B26: Hub/Dark Store | C26: CABA | E26: 0 | F26: 0 | G26: 0 | H26: 0 | I26: 0 | J26: 1 | K26: 0 | L26: 1 | M26: 0 | N26: 1 | O26: 0 | P26: 1 | Q26: =SUM(E26:P26) -> 4
B27: Hub/Dark Store | C27: GBA | E27: 0 | F27: 0 | G27: 0 | H27: 0 | I27: 0 | J27: 1 | K27: 0 | L27: 1 | M27: 0 | N27: 1 | O27: 0 | P27: 1 | Q27: =SUM(E27:P27) -> 4
B29: TOTAL | D29: =SUM(D20:D27) -> 0 | E29: =SUM(E20:E27) -> 0 | F29: =SUM(F20:F27) -> 0 | G29: =SUM(G20:G27) -> 1 | H29: =SUM(H20:H27) -> 0 | I29: =SUM(I20:I27) -> 0 | J29: =SUM(J20:J27) -> 2 | K29: =SUM(K20:K27) -> 1 | ... Q29: =SUM(Q20:Q27) -> 11
B31: Aperturas PDV (ARS MM)
B33: Formato | C33: Zona | D33: Mes 0 | E33: Mes 1 | F33: Mes 2 | G33: Mes 3 | H33: Mes 4 | I33: Mes 5 | J33: Mes 6 | K33: Mes 7 | L33: Mes 8 | M33: Mes 9 | N33: Mes 10 | O33: Mes 11 | P33: Mes 12 | Q33: Total
B34: Flagship | C34: CABA | E34: =+E20*$I6 -> 0 | F34: =+F20*$I6+E34 -> 0 | G34: =+G20*$I6+F34 -> 665 | H34: =+H20*$I6+G34 -> 665 | I34: =+I20*$I6+H34 -> 665 | J34: =+J20*$I6+I34 -> 665 | K34: =+K20*$I6+J34 -> 1330 | L34: =+L20*$I6+K34 -> 1330 | M34: =+M20*$I6+L34 -> 1330 | ... P34: =+P20*$I6+O34 -> 1995 | Q34: =SUM(E34:P34) -> 12635
B35: Flagship | C35: GBA | E35: =+E21*$I7 -> 0 | F35: =+F21*$I7+E35 -> 0 | G35: =+G21*$I7+F35 -> 0 | H35: =+H21*$I7+G35 -> 0 | I35: =+I21*$I7+H35 -> 0 | J35: =+J21*$I7+I35 -> 0 | K35: =+K21*$I7+J35 -> 0 | L35: =+L21*$I7+K35 -> 0 | M35: =+M21*$I7+L35 -> 0 | ... P35: =+P21*$I7+O35 -> 0 | Q35: =SUM(E35:P35) -> 0
B36: Standard | C36: CABA | E36: =+E22*$I8 -> 0 | F36: =+F22*$I8+E36 -> 0 | G36: =+G22*$I8+F36 -> 0 | H36: =+H22*$I8+G36 -> 0 | I36: =+I22*$I8+H36 -> 0 | J36: =+J22*$I8+I36 -> 0 | K36: =+K22*$I8+J36 -> 0 | L36: =+L22*$I8+K36 -> 0 | M36: =+M22*$I8+L36 -> 0 | ... P36: =+P22*$I8+O36 -> 0 | Q36: =SUM(E36:P36) -> 0
B37: Standard | C37: GBA | E37: =+E23*$I9 -> 0 | F37: =+F23*$I9+E37 -> 0 | G37: =+G23*$I9+F37 -> 0 | H37: =+H23*$I9+G37 -> 0 | I37: =+I23*$I9+H37 -> 0 | J37: =+J23*$I9+I37 -> 0 | K37: =+K23*$I9+J37 -> 0 | L37: =+L23*$I9+K37 -> 0 | M37: =+M23*$I9+L37 -> 0 | ... P37: =+P23*$I9+O37 -> 0 | Q37: =SUM(E37:P37) -> 0
B38: Proximidad | C38: CABA | E38: =+E24*$I10 -> 0 | F38: =+F24*$I10+E38 -> 0 | G38: =+G24*$I10+F38 -> 0 | H38: =+H24*$I10+G38 -> 0 | I38: =+I24*$I10+H38 -> 0 | J38: =+J24*$I10+I38 -> 0 | K38: =+K24*$I10+J38 -> 0 | L38: =+L24*$I10+K38 -> 0 | M38: =+M24*$I10+L38 -> 0 | ... P38: =+P24*$I10+O38 -> 0 | Q38: =SUM(E38:P38) -> 0
B39: Proximidad | C39: GBA | E39: =+E25*$I11 -> 0 | F39: =+F25*$I11+E39 -> 0 | G39: =+G25*$I11+F39 -> 0 | H39: =+H25*$I11+G39 -> 0 | I39: =+I25*$I11+H39 -> 0 | J39: =+J25*$I11+I39 -> 0 | K39: =+K25*$I11+J39 -> 0 | L39: =+L25*$I11+K39 -> 0 | M39: =+M25*$I11+L39 -> 0 | ... P39: =+P25*$I11+O39 -> 0 | Q39: =SUM(E39:P39) -> 0
B40: Hub/Dark Store | C40: CABA | E40: =+E26*$I12 -> 0 | F40: =+F26*$I12+E40 -> 0 | G40: =+G26*$I12+F40 -> 0 | H40: =+H26*$I12+G40 -> 0 | I40: =+I26*$I12+H40 -> 0 | J40: =+J26*$I12+I40 -> 237.5 | K40: =+K26*$I12+J40 -> 237.5 | L40: =+L26*$I12+K40 -> 475 | M40: =+M26*$I12+L40 -> 475 | ... P40: =+P26*$I12+O40 -> 950 | Q40: =SUM(E40:P40) -> 3800
B41: Hub/Dark Store | C41: GBA | E41: =+E27*$I13 -> 0 | F41: =+F27*$I13+E41 -> 0 | G41: =+G27*$I13+F41 -> 0 | H41: =+H27*$I13+G41 -> 0 | I41: =+I27*$I13+H41 -> 0 | J41: =+J27*$I13+I41 -> 285 | K41: =+K27*$I13+J41 -> 285 | L41: =+L27*$I13+K41 -> 570 | M41: =+M27*$I13+L41 -> 570 | ... P41: =+P27*$I13+O41 -> 1140 | Q41: =SUM(E41:P41) -> 4560
B43: TOTAL | D43: =SUM(D34:D41) -> 0 | E43: =SUM(E34:E41) -> 0 | F43: =SUM(F34:F41) -> 0 | G43: =SUM(G34:G41) -> 665 | H43: =SUM(H34:H41) -> 665 | I43: =SUM(I34:I41) -> 665 | J43: =SUM(J34:J41) -> 1187.5 | K43: =SUM(K34:K41) -> 1852.5 | ... Q43: =SUM(Q34:Q41) -> 20995
B45: Cierre # PDV
B47: Formato | C47: Zona | D47: Mes 0 | E47: Mes 1 | F47: Mes 2 | G47: Mes 3 | H47: Mes 4 | I47: Mes 5 | J47: Mes 6 | K47: Mes 7 | L47: Mes 8 | M47: Mes 9 | N47: Mes 10 | O47: Mes 11 | P47: Mes 12 | Q47: Total
B48: Flagship | C48: CABA | E48: 0 | F48: 0 | G48: 0 | H48: 0 | I48: 0 | J48: 0 | K48: 0 | L48: 0 | M48: 0 | N48: 0 | O48: 0 | P48: 0 | Q48: =SUM(E48:P48) -> 0
B49: Flagship | C49: GBA | E49: 0 | F49: 0 | G49: 0 | H49: 0 | I49: 0 | J49: 0 | K49: 0 | L49: 0 | M49: 0 | N49: 0 | O49: 0 | P49: 0 | Q49: =SUM(E49:P49) -> 0
B50: Standard | C50: CABA | E50: 0 | F50: 0 | G50: 0 | H50: 0 | I50: 0 | J50: 0 | K50: 0 | L50: 0 | M50: 0 | N50: 0 | O50: 0 | P50: 0 | Q50: =SUM(E50:P50) -> 0
B51: Standard | C51: GBA | E51: 0 | F51: 0 | G51: 0 | H51: 0 | I51: 0 | J51: 0 | K51: 0 | L51: 0 | M51: 0 | N51: 0 | O51: 0 | P51: 0 | Q51: =SUM(E51:P51) -> 0
B52: Proximidad | C52: CABA | E52: 0 | F52: 0 | G52: 0 | H52: 0 | I52: 0 | J52: 0 | K52: 0 | L52: 0 | M52: 0 | N52: 0 | O52: 0 | P52: 0 | Q52: =SUM(E52:P52) -> 0
B53: Proximidad | C53: GBA | E53: 0 | F53: 0 | G53: -1 | H53: -2 | I53: -2 | J53: -2 | K53: -2 | L53: -2 | M53: 0 | N53: 0 | O53: 0 | P53: 0 | Q53: =SUM(E53:P53) -> -11
B54: Hub/Dark Store | C54: CABA | E54: 0 | F54: 0 | G54: 0 | H54: 0 | I54: 0 | J54: 0 | K54: 0 | L54: 0 | M54: 0 | N54: 0 | O54: 0 | P54: 0 | Q54: =SUM(E54:P54) -> 0
B55: Hub/Dark Store | C55: GBA | E55: 0 | F55: 0 | G55: 0 | H55: 0 | I55: 0 | J55: 0 | K55: 0 | L55: 0 | M55: 0 | N55: 0 | O55: 0 | P55: 0 | Q55: =SUM(E55:P55) -> 0
B57: TOTAL | D57: =SUM(D48:D55) -> 0 | E57: =SUM(E48:E55) -> 0 | F57: =SUM(F48:F55) -> 0 | G57: =SUM(G48:G55) -> -1 | H57: =SUM(H48:H55) -> -2 | I57: =SUM(I48:I55) -> -2 | J57: =SUM(J48:J55) -> -2 | K57: =SUM(K48:K55) -> -2 | ... Q57: =SUM(Q48:Q55) -> -11
B59: Cierre PDV (ARS MM)
B61: Formato | C61: Zona | D61: Mes 0 | E61: Mes 1 | F61: Mes 2 | G61: Mes 3 | H61: Mes 4 | I61: Mes 5 | J61: Mes 6 | K61: Mes 7 | L61: Mes 8 | M61: Mes 9 | N61: Mes 10 | O61: Mes 11 | P61: Mes 12 | Q61: Total
B62: Flagship | C62: CABA | E62: =+E48*$I6 -> 0 | F62: =+F48*$I6+E62 -> 0 | G62: =+G48*$I6+F62 -> 0 | H62: =+H48*$I6+G62 -> 0 | I62: =+I48*$I6+H62 -> 0 | J62: =+J48*$I6+I62 -> 0 | K62: =+K48*$I6+J62 -> 0 | L62: =+L48*$I6+K62 -> 0 | M62: =+M48*$I6+L62 -> 0 | ... P62: =+P48*$I6+O62 -> 0 | Q62: =SUM(E62:P62) -> 0
B63: Flagship | C63: GBA | E63: =+E49*$I7 -> 0 | F63: =+F49*$I7+E63 -> 0 | G63: =+G49*$I7+F63 -> 0 | H63: =+H49*$I7+G63 -> 0 | I63: =+I49*$I7+H63 -> 0 | J63: =+J49*$I7+I63 -> 0 | K63: =+K49*$I7+J63 -> 0 | L63: =+L49*$I7+K63 -> 0 | M63: =+M49*$I7+L63 -> 0 | ... P63: =+P49*$I7+O63 -> 0 | Q63: =SUM(E63:P63) -> 0
B64: Standard | C64: CABA | E64: =+E50*$I8 -> 0 | F64: =+F50*$I8+E64 -> 0 | G64: =+G50*$I8+F64 -> 0 | H64: =+H50*$I8+G64 -> 0 | I64: =+I50*$I8+H64 -> 0 | J64: =+J50*$I8+I64 -> 0 | K64: =+K50*$I8+J64 -> 0 | L64: =+L50*$I8+K64 -> 0 | M64: =+M50*$I8+L64 -> 0 | ... P64: =+P50*$I8+O64 -> 0 | Q64: =SUM(E64:P64) -> 0
B65: Standard | C65: GBA | E65: =+E51*$I9 -> 0 | F65: =+F51*$I9+E65 -> 0 | G65: =+G51*$I9+F65 -> 0 | H65: =+H51*$I9+G65 -> 0 | I65: =+I51*$I9+H65 -> 0 | J65: =+J51*$I9+I65 -> 0 | K65: =+K51*$I9+J65 -> 0 | L65: =+L51*$I9+K65 -> 0 | M65: =+M51*$I9+L65 -> 0 | ... P65: =+P51*$I9+O65 -> 0 | Q65: =SUM(E65:P65) -> 0
B66: Proximidad | C66: CABA | E66: =+E52*$I10 -> 0 | F66: =+F52*$I10+E66 -> 0 | G66: =+G52*$I10+F66 -> 0 | H66: =+H52*$I10+G66 -> 0 | I66: =+I52*$I10+H66 -> 0 | J66: =+J52*$I10+I66 -> 0 | K66: =+K52*$I10+J66 -> 0 | L66: =+L52*$I10+K66 -> 0 | M66: =+M52*$I10+L66 -> 0 | ... P66: =+P52*$I10+O66 -> 0 | Q66: =SUM(E66:P66) -> 0
B67: Proximidad | C67: GBA | E67: =+E53*$I11 -> 0 | F67: =+F53*$I11+E67 -> 0 | G67: =+G53*$I11+F67 -> -118.75 | H67: =+H53*$I11+G67 -> -356.25 | I67: =+I53*$I11+H67 -> -593.75 | J67: =+J53*$I11+I67 -> -831.25 | K67: =+K53*$I11+J67 -> -1068.75 | L67: =+L53*$I11+K67 -> -1306.25 | M67: =+M53*$I11+L67 -> -1306.25 | ... P67: =+P53*$I11+O67 -> -1306.25 | Q67: =SUM(E67:P67) -> -9500
B68: Hub/Dark Store | C68: CABA | E68: =+E54*$I12 -> 0 | F68: =+F54*$I12+E68 -> 0 | G68: =+G54*$I12+F68 -> 0 | H68: =+H54*$I12+G68 -> 0 | I68: =+I54*$I12+H68 -> 0 | J68: =+J54*$I12+I68 -> 0 | K68: =+K54*$I12+J68 -> 0 | L68: =+L54*$I12+K68 -> 0 | M68: =+M54*$I12+L68 -> 0 | ... P68: =+P54*$I12+O68 -> 0 | Q68: =SUM(E68:P68) -> 0
B69: Hub/Dark Store | C69: GBA | E69: =+E55*$I13 -> 0 | F69: =+F55*$I13+E69 -> 0 | G69: =+G55*$I13+F69 -> 0 | H69: =+H55*$I13+G69 -> 0 | I69: =+I55*$I13+H69 -> 0 | J69: =+J55*$I13+I69 -> 0 | K69: =+K55*$I13+J69 -> 0 | L69: =+L55*$I13+K69 -> 0 | M69: =+M55*$I13+L69 -> 0 | ... P69: =+P55*$I13+O69 -> 0 | Q69: =SUM(E69:P69) -> 0
B71: TOTAL | D71: =SUM(D62:D69) -> 0 | E71: =SUM(E62:E69) -> 0 | F71: =SUM(F62:F69) -> 0 | G71: =SUM(G62:G69) -> -118.75 | H71: =SUM(H62:H69) -> -356.25 | I71: =SUM(I62:I69) -> -593.75 | J71: =SUM(J62:J69) -> -831.25 | K71: =SUM(K62:K69) -> -1068.75 | ... Q71: =SUM(Q62:Q69) -> -9500
B73: Revenue Apert/Cierre | E73: =+E71+E43 -> 0 | F73: =+F71+F43 -> 0 | G73: =+G71+G43 -> 546.25 | H73: =+H71+H43 -> 308.75 | I73: =+I71+I43 -> 71.25 | J73: =+J71+J43 -> 356.25 | K73: =+K71+K43 -> 783.75 | L73: =+L71+L43 -> 1068.75 | ... Q73: =+Q71+Q43 -> 11495
B75: CAPEX PDV (ARS MM)
B77: Formato | C77: Zona | D77: Mes 0 | E77: Mes 1 | F77: Mes 2 | G77: Mes 3 | H77: Mes 4 | I77: Mes 5 | J77: Mes 6 | K77: Mes 7 | L77: Mes 8 | M77: Mes 9 | N77: Mes 10 | O77: Mes 11 | P77: Mes 12 | Q77: Total
B78: Flagship | C78: CABA | E78: =+E20*$H6 -> 0 | F78: =+F20*$H6 -> 0 | G78: =+G20*$H6 -> 5833.3333 | H78: =+H20*$H6 -> 0 | I78: =+I20*$H6 -> 0 | J78: =+J20*$H6 -> 0 | K78: =+K20*$H6 -> 5833.3333 | L78: =+L20*$H6 -> 0 | ... P78: =+P20*$H6 -> 0 | Q78: =SUM(E78:P78) -> 17500
B79: Flagship | C79: GBA | E79: =+E21*$H7 -> 0 | F79: =+F21*$H7 -> 0 | G79: =+G21*$H7 -> 0 | H79: =+H21*$H7 -> 0 | I79: =+I21*$H7 -> 0 | J79: =+J21*$H7 -> 0 | K79: =+K21*$H7 -> 0 | L79: =+L21*$H7 -> 0 | ... P79: =+P21*$H7 -> 0 | Q79: =SUM(E79:P79) -> 0
B80: Standard | C80: CABA | E80: =+E22*$H8 -> 0 | F80: =+F22*$H8 -> 0 | G80: =+G22*$H8 -> 0 | H80: =+H22*$H8 -> 0 | I80: =+I22*$H8 -> 0 | J80: =+J22*$H8 -> 0 | K80: =+K22*$H8 -> 0 | L80: =+L22*$H8 -> 0 | ... P80: =+P22*$H8 -> 0 | Q80: =SUM(E80:P80) -> 0
B81: Standard | C81: GBA | E81: =+E23*$H9 -> 0 | F81: =+F23*$H9 -> 0 | G81: =+G23*$H9 -> 0 | H81: =+H23*$H9 -> 0 | I81: =+I23*$H9 -> 0 | J81: =+J23*$H9 -> 0 | K81: =+K23*$H9 -> 0 | L81: =+L23*$H9 -> 0 | ... P81: =+P23*$H9 -> 0 | Q81: =SUM(E81:P81) -> 0
B82: Proximidad | C82: CABA | E82: =+E24*$H10 -> 0 | F82: =+F24*$H10 -> 0 | G82: =+G24*$H10 -> 0 | H82: =+H24*$H10 -> 0 | I82: =+I24*$H10 -> 0 | J82: =+J24*$H10 -> 0 | K82: =+K24*$H10 -> 0 | L82: =+L24*$H10 -> 0 | ... P82: =+P24*$H10 -> 0 | Q82: =SUM(E82:P82) -> 0
B83: Proximidad | C83: GBA | E83: =+E25*$H11 -> 0 | F83: =+F25*$H11 -> 0 | G83: =+G25*$H11 -> 0 | H83: =+H25*$H11 -> 0 | I83: =+I25*$H11 -> 0 | J83: =+J25*$H11 -> 0 | K83: =+K25*$H11 -> 0 | L83: =+L25*$H11 -> 0 | ... P83: =+P25*$H11 -> 0 | Q83: =SUM(E83:P83) -> 0
B84: Hub/Dark Store | C84: CABA | E84: =+E26*$H12 -> 0 | F84: =+F26*$H12 -> 0 | G84: =+G26*$H12 -> 0 | H84: =+H26*$H12 -> 0 | I84: =+I26*$H12 -> 0 | J84: =+J26*$H12 -> 2000 | K84: =+K26*$H12 -> 0 | L84: =+L26*$H12 -> 2000 | ... P84: =+P26*$H12 -> 2000 | Q84: =SUM(E84:P84) -> 8000
B85: Hub/Dark Store | C85: GBA | E85: =+E27*$H13 -> 0 | F85: =+F27*$H13 -> 0 | G85: =+G27*$H13 -> 0 | H85: =+H27*$H13 -> 0 | I85: =+I27*$H13 -> 0 | J85: =+J27*$H13 -> 2400 | K85: =+K27*$H13 -> 0 | L85: =+L27*$H13 -> 2400 | ... P85: =+P27*$H13 -> 2400 | Q85: =SUM(E85:P85) -> 9600
B87: TOTAL | D87: =SUM(D78:D85) -> 0 | E87: =SUM(E78:E85) -> 0 | F87: =SUM(F78:F85) -> 0 | G87: =SUM(G78:G85) -> 5833.3333 | H87: =SUM(H78:H85) -> 0 | I87: =SUM(I78:I85) -> 0 | J87: =SUM(J78:J85) -> 4400 | K87: =SUM(K78:K85) -> 5833.3333 | ... Q87: =SUM(Q78:Q85) -> 35100

Sheet 07_PL_TiposPDV
B3: P&L Base por Tipo de PDV y Zona
B5: Formato | C5: Zona | D5: Tiendas Finales | E5: Ventas Mensual | F5: Margen % | G5: Margen Bruto | H5: Merma | I5: Markteting | J5: Gastos Personal | K5: Alquileres | L5: G&A/Otros | M5: Logistica | N5: EBITDA | O5: EBITDA % | Q5: Gastos Personal | R5: Alquileres | S5: G&A/Otros | T5: Logistica
B6: ='06_Red_CAPEX'!B6 -> Flagship | C6: ='06_Red_CAPEX'!C6 -> CABA | D6: ='06_Red_CAPEX'!G6 -> 11 | E6: ='06_Red_CAPEX'!D6*'06_Red_CAPEX'!I6 -> 5320 | F6: 0.39 | G6: =E6*F6 -> 2074.8 | H6: =-E6*'08_Core_Financiero'!$AC$8 -> 55.86 | I6: =-E6*'08_Core_Financiero'!$AC$12 -> 76.841155 | J6: =+$E6*Q6 -> 691.6 | K6: =+$E6*R6 -> 186.2 | L6: =+$E6*S6 -> 345.8 | M6: =+$E6*T6 -> 145.22902 | N6: =G6-J6-K6-L6-M6-H6-I6 -> 573.26982 | O6: =N6/E6 -> 0.10775749 | Q6: 0.13 | R6: 0.035 | S6: 0.065 | T6: =+'04_Digital_Logistica'!$P$13 -> 0.027298688
B7: ='06_Red_CAPEX'!B7 -> Flagship | C7: ='06_Red_CAPEX'!C7 -> GBA | D7: ='06_Red_CAPEX'!G7 -> 6 | E7: ='06_Red_CAPEX'!D7*'06_Red_CAPEX'!I7 -> 6555 | F7: 0.355 | G7: =E7*F7 -> 2327.025 | H7: =-E7*'08_Core_Financiero'!$AC$8 -> 68.8275 | I7: =-E7*'08_Core_Financiero'!$AC$12 -> 94.67928 | J7: =+$E7*Q7 -> 786.6 | K7: =+$E7*R7 -> 163.875 | L7: =+$E7*S7 -> 360.525 | M7: =+$E7*T7 -> 178.9429 | N7: =G7-J7-K7-L7-M7-H7-I7 -> 673.57532 | O7: =N7/E7 -> 0.10275749 | Q7: 0.12 | R7: 0.025 | S7: 0.055 | T7: =+'04_Digital_Logistica'!$P$13 -> 0.027298688
B8: ='06_Red_CAPEX'!B8 -> Standard | C8: ='06_Red_CAPEX'!C8 -> CABA | D8: ='06_Red_CAPEX'!G8 -> 20 | E8: ='06_Red_CAPEX'!D8*'06_Red_CAPEX'!I8 -> 2850 | F8: 0.355 | G8: =E8*F8 -> 1011.75 | H8: =-E8*'08_Core_Financiero'!$AC$8 -> 29.925 | I8: =-E8*'08_Core_Financiero'!$AC$12 -> 41.164904 | J8: =+$E8*Q8 -> 413.25 | K8: =+$E8*R8 -> 128.25 | L8: =+$E8*S8 -> 213.75 | M8: =+$E8*T8 -> 77.801262 | N8: =G8-J8-K8-L8-M8-H8-I8 -> 107.60883 | O8: =N8/E8 -> 0.037757486 | Q8: =+Q6+0.015 -> 0.145 | R8: =+R6+0.01 -> 0.045 | S8: =+S6+0.01 -> 0.075 | T8: =+'04_Digital_Logistica'!$P$13 -> 0.027298688
B9: ='06_Red_CAPEX'!B9 -> Standard | C9: ='06_Red_CAPEX'!C9 -> GBA | D9: ='06_Red_CAPEX'!G9 -> 32 | E9: ='06_Red_CAPEX'!D9*'06_Red_CAPEX'!I9 -> 7600 | F9: 0.32 | G9: =E9*F9 -> 2432 | H9: =-E9*'08_Core_Financiero'!$AC$8 -> 79.8 | I9: =-E9*'08_Core_Financiero'!$AC$12 -> 109.77308 | J9: =+$E9*Q9 -> 1026 | K9: =+$E9*R9 -> 266 | L9: =+$E9*S9 -> 494 | M9: =+$E9*T9 -> 207.47003 | N9: =G9-J9-K9-L9-M9-H9-I9 -> 248.95689 | O9: =N9/E9 -> 0.032757486 | Q9: =+Q7+0.015 -> 0.135 | R9: =+R7+0.01 -> 0.035 | S9: =+S7+0.01 -> 0.065 | T9: =+'04_Digital_Logistica'!$P$13 -> 0.027298688
B10: ='06_Red_CAPEX'!B10 -> Proximidad | C10: ='06_Red_CAPEX'!C10 -> CABA | D10: ='06_Red_CAPEX'!G10 -> 18 | E10: ='06_Red_CAPEX'!D10*'06_Red_CAPEX'!I10 -> 1282.5 | F10: 0.34 | G10: =E10*F10 -> 436.05 | H10: =-E10*'08_Core_Financiero'!$AC$8 -> 13.46625 | I10: =-E10*'08_Core_Financiero'!$AC$12 -> 18.524207 | J10: =+$E10*Q10 -> 205.2 | K10: =+$E10*R10 -> 70.5375 | L10: =+$E10*S10 -> 109.0125 | M10: =+$E10*T10 -> 35.010568 | N10: =G10-J10-K10-L10-M10-H10-I10 -> -15.701025 | O10: =N10/E10 -> -0.012242514 | Q10: =+Q8+0.015 -> 0.16 | R10: =+R8+0.01 -> 0.055 | S10: =+S8+0.01 -> 0.085 | T10: =+'04_Digital_Logistica'!$P$13 -> 0.027298688
B11: ='06_Red_CAPEX'!B11 -> Proximidad | C11: ='06_Red_CAPEX'!C11 -> GBA | D11: ='06_Red_CAPEX'!G11 -> 21 | E11: ='06_Red_CAPEX'!D11*'06_Red_CAPEX'!I11 -> 3800 | F11: 0.295 | G11: =E11*F11 -> 1121 | H11: =-E11*'08_Core_Financiero'!$AC$8 -> 39.9 | I11: =-E11*'08_Core_Financiero'!$AC$12 -> 54.886539 | J11: =+$E11*Q11 -> 570 | K11: =+$E11*R11 -> 171 | L11: =+$E11*S11 -> 285 | M11: =+$E11*T11 -> 103.73502 | N11: =G11-J11-K11-L11-M11-H11-I11 -> -103.52155 | O11: =N11/E11 -> -0.027242514 | Q11: =+Q9+0.015 -> 0.15 | R11: =+R9+0.01 -> 0.045 | S11: =+S9+0.01 -> 0.075 | T11: =+'04_Digital_Logistica'!$P$13 -> 0.027298688
B12: ='06_Red_CAPEX'!B12 -> Hub/Dark Store | C12: ='06_Red_CAPEX'!C12 -> CABA | D12: ='06_Red_CAPEX'!G12 -> 5 | E12: ='06_Red_CAPEX'!D12*'06_Red_CAPEX'!I12 -> 237.5 | F12: 0.32 | G12: =E12*F12 -> 76 | H12: =-E12*'08_Core_Financiero'!$AC$8 -> 2.49375 | I12: =-E12*'08_Core_Financiero'!$AC$12 -> 3.4304087 | J12: =+$E12*Q12 -> 23.75 | K12: =+$E12*R12 -> 4.75 | L12: =+$E12*S12 -> 9.5 | M12: =+$E12*T12 -> 20.1875 | N12: =G12-J12-K12-L12-M12-H12-I12 -> 11.888341 | O12: =N12/E12 -> 0.050056174 | Q12: 0.1 | R12: 0.02 | S12: 0.04 | T12: =+'04_Digital_Logistica'!$P$10 -> 0.085
B13: ='06_Red_CAPEX'!B13 -> Hub/Dark Store | C13: ='06_Red_CAPEX'!C13 -> GBA | D13: ='06_Red_CAPEX'!G13 -> 7 | E13: ='06_Red_CAPEX'!D13*'06_Red_CAPEX'!I13 -> 855 | F13: 0.31 | G13: =E13*F13 -> 265.05 | H13: =-E13*'08_Core_Financiero'!$AC$8 -> 8.9775 | I13: =-E13*'08_Core_Financiero'!$AC$12 -> 12.349471 | J13: =+$E13*Q13 -> 85.5 | K13: =+$E13*R13 -> 17.1 | L13: =+$E13*S13 -> 25.65 | M13: =+$E13*T13 -> 72.675 | N13: =G13-J13-K13-L13-M13-H13-I13 -> 42.798029 | O13: =N13/E13 -> 0.050056174 | Q13: 0.1 | R13: 0.02 | S13: 0.03 | T13: =+'04_Digital_Logistica'!$P$10 -> 0.085
B14: TOTAL | D14: =SUM(D6:D13) -> 120 | E14: =SUM(E6:E13) -> 28500 | F14: =SUMPRODUCT(F6:F13,E6:E13)/SUM(E6:E13) -> 0.34188333 | G14: =SUM(G6:G13) -> 9743.675 | H14: =SUM(H6:H13) -> 299.25 | I14: =SUM(I6:I13) -> 411.64904 | J14: =SUM(J6:J13) -> 3801.9 | K14: =SUM(K6:K13) -> 1007.7125 | L14: =SUM(L6:L13) -> 1843.2375 | M14: =SUM(M6:M13) -> 841.0513 | N14: =SUM(N6:N13) -> 1538.8747 | O14: =N14/E14 -> 0.053995602 | Q14: =SUMPRODUCT(Q6:Q13,$E$6:$E$13)/$E$14 -> 0.1334 | R14: =SUMPRODUCT(R6:R13,$E$6:$E$13)/$E$14 -> 0.035358333 | S14: =SUMPRODUCT(S6:S13,$E$6:$E$13)/$E$14 -> 0.064675 | T14: =SUMPRODUCT(T6:T13,$E$6:$E$13)/$E$14 -> 0.029510572
F15: =+'02_Pricing'!Q18 -> 0 | G15: =+G14/$E$14 -> 0.34188333 | H15: =+H14/$E$14 -> 0.0105 | I15: =+I14/$E$14 -> 0.014443826 | J15: =+J14/$E$14 -> 0.1334 | K15: =+K14/$E$14 -> 0.035358333 | L15: =+L14/$E$14 -> 0.064675 | M15: =+M14/$E$14 -> 0.029510572 | N15: =+N14/$E$14 -> 0.053995602
B18: Revenue Teórico | D18: Mes 0 | E18: Mes 1 | F18: Mes 2 | G18: Mes 3 | H18: Mes 4 | I18: Mes 5 | J18: Mes 6 | K18: Mes 7 | L18: Mes 8 | M18: Mes 9 | N18: Mes 10 | O18: Mes 11 | P18: Mes 12 | Q18: Total
B19: ='06_Red_CAPEX'!B20 -> Flagship | D19: =+E6 -> 5320 | E19: =+$D19+'06_Red_CAPEX'!E34+'06_Red_CAPEX'!E62 -> 5320 | F19: =+$D19+'06_Red_CAPEX'!F34+'06_Red_CAPEX'!F62 -> 5320 | G19: =+$D19+'06_Red_CAPEX'!G34+'06_Red_CAPEX'!G62 -> 5985 | H19: =+$D19+'06_Red_CAPEX'!H34+'06_Red_CAPEX'!H62 -> 5985 | I19: =+$D19+'06_Red_CAPEX'!I34+'06_Red_CAPEX'!I62 -> 5985 | J19: =+$D19+'06_Red_CAPEX'!J34+'06_Red_CAPEX'!J62 -> 5985 | K19: =+$D19+'06_Red_CAPEX'!K34+'06_Red_CAPEX'!K62 -> 6650 | L19: =+$D19+'06_Red_CAPEX'!L34+'06_Red_CAPEX'!L62 -> 6650 | ... P19: =+$D19+'06_Red_CAPEX'!P34+'06_Red_CAPEX'!P62 -> 7315 | Q19: =SUM(E19:P19) -> 76475
B20: ='06_Red_CAPEX'!B21 -> Flagship | D20: =+E7 -> 6555 | E20: =+$D20+'06_Red_CAPEX'!E35+'06_Red_CAPEX'!E63 -> 6555 | F20: =+$D20+'06_Red_CAPEX'!F35+'06_Red_CAPEX'!F63 -> 6555 | G20: =+$D20+'06_Red_CAPEX'!G35+'06_Red_CAPEX'!G63 -> 6555 | H20: =+$D20+'06_Red_CAPEX'!H35+'06_Red_CAPEX'!H63 -> 6555 | I20: =+$D20+'06_Red_CAPEX'!I35+'06_Red_CAPEX'!I63 -> 6555 | J20: =+$D20+'06_Red_CAPEX'!J35+'06_Red_CAPEX'!J63 -> 6555 | K20: =+$D20+'06_Red_CAPEX'!K35+'06_Red_CAPEX'!K63 -> 6555 | L20: =+$D20+'06_Red_CAPEX'!L35+'06_Red_CAPEX'!L63 -> 6555 | ... P20: =+$D20+'06_Red_CAPEX'!P35+'06_Red_CAPEX'!P63 -> 6555 | Q20: =SUM(E20:P20) -> 78660
B21: ='06_Red_CAPEX'!B22 -> Standard | D21: =+E8 -> 2850 | E21: =+$D21+'06_Red_CAPEX'!E36+'06_Red_CAPEX'!E64 -> 2850 | F21: =+$D21+'06_Red_CAPEX'!F36+'06_Red_CAPEX'!F64 -> 2850 | G21: =+$D21+'06_Red_CAPEX'!G36+'06_Red_CAPEX'!G64 -> 2850 | H21: =+$D21+'06_Red_CAPEX'!H36+'06_Red_CAPEX'!H64 -> 2850 | I21: =+$D21+'06_Red_CAPEX'!I36+'06_Red_CAPEX'!I64 -> 2850 | J21: =+$D21+'06_Red_CAPEX'!J36+'06_Red_CAPEX'!J64 -> 2850 | K21: =+$D21+'06_Red_CAPEX'!K36+'06_Red_CAPEX'!K64 -> 2850 | L21: =+$D21+'06_Red_CAPEX'!L36+'06_Red_CAPEX'!L64 -> 2850 | ... P21: =+$D21+'06_Red_CAPEX'!P36+'06_Red_CAPEX'!P64 -> 2850 | Q21: =SUM(E21:P21) -> 34200
B22: ='06_Red_CAPEX'!B23 -> Standard | D22: =+E9 -> 7600 | E22: =+$D22+'06_Red_CAPEX'!E37+'06_Red_CAPEX'!E65 -> 7600 | F22: =+$D22+'06_Red_CAPEX'!F37+'06_Red_CAPEX'!F65 -> 7600 | G22: =+$D22+'06_Red_CAPEX'!G37+'06_Red_CAPEX'!G65 -> 7600 | H22: =+$D22+'06_Red_CAPEX'!H37+'06_Red_CAPEX'!H65 -> 7600 | I22: =+$D22+'06_Red_CAPEX'!I37+'06_Red_CAPEX'!I65 -> 7600 | J22: =+$D22+'06_Red_CAPEX'!J37+'06_Red_CAPEX'!J65 -> 7600 | K22: =+$D22+'06_Red_CAPEX'!K37+'06_Red_CAPEX'!K65 -> 7600 | L22: =+$D22+'06_Red_CAPEX'!L37+'06_Red_CAPEX'!L65 -> 7600 | ... P22: =+$D22+'06_Red_CAPEX'!P37+'06_Red_CAPEX'!P65 -> 7600 | Q22: =SUM(E22:P22) -> 91200
B23: ='06_Red_CAPEX'!B24 -> Proximidad | D23: =+E10 -> 1282.5 | E23: =+$D23+'06_Red_CAPEX'!E38+'06_Red_CAPEX'!E66 -> 1282.5 | F23: =+$D23+'06_Red_CAPEX'!F38+'06_Red_CAPEX'!F66 -> 1282.5 | G23: =+$D23+'06_Red_CAPEX'!G38+'06_Red_CAPEX'!G66 -> 1282.5 | H23: =+$D23+'06_Red_CAPEX'!H38+'06_Red_CAPEX'!H66 -> 1282.5 | I23: =+$D23+'06_Red_CAPEX'!I38+'06_Red_CAPEX'!I66 -> 1282.5 | J23: =+$D23+'06_Red_CAPEX'!J38+'06_Red_CAPEX'!J66 -> 1282.5 | K23: =+$D23+'06_Red_CAPEX'!K38+'06_Red_CAPEX'!K66 -> 1282.5 | L23: =+$D23+'06_Red_CAPEX'!L38+'06_Red_CAPEX'!L66 -> 1282.5 | ... P23: =+$D23+'06_Red_CAPEX'!P38+'06_Red_CAPEX'!P66 -> 1282.5 | Q23: =SUM(E23:P23) -> 15390
B24: ='06_Red_CAPEX'!B25 -> Proximidad | D24: =+E11 -> 3800 | E24: =+$D24+'06_Red_CAPEX'!E39+'06_Red_CAPEX'!E67 -> 3800 | F24: =+$D24+'06_Red_CAPEX'!F39+'06_Red_CAPEX'!F67 -> 3800 | G24: =+$D24+'06_Red_CAPEX'!G39+'06_Red_CAPEX'!G67 -> 3681.25 | H24: =+$D24+'06_Red_CAPEX'!H39+'06_Red_CAPEX'!H67 -> 3443.75 | I24: =+$D24+'06_Red_CAPEX'!I39+'06_Red_CAPEX'!I67 -> 3206.25 | J24: =+$D24+'06_Red_CAPEX'!J39+'06_Red_CAPEX'!J67 -> 2968.75 | K24: =+$D24+'06_Red_CAPEX'!K39+'06_Red_CAPEX'!K67 -> 2731.25 | L24: =+$D24+'06_Red_CAPEX'!L39+'06_Red_CAPEX'!L67 -> 2493.75 | ... P24: =+$D24+'06_Red_CAPEX'!P39+'06_Red_CAPEX'!P67 -> 2493.75 | Q24: =SUM(E24:P24) -> 36100
B25: ='06_Red_CAPEX'!B26 -> Hub/Dark Store | D25: =+E12 -> 237.5 | E25: =+$D25+'06_Red_CAPEX'!E40+'06_Red_CAPEX'!E68 -> 237.5 | F25: =+$D25+'06_Red_CAPEX'!F40+'06_Red_CAPEX'!F68 -> 237.5 | G25: =+$D25+'06_Red_CAPEX'!G40+'06_Red_CAPEX'!G68 -> 237.5 | H25: =+$D25+'06_Red_CAPEX'!H40+'06_Red_CAPEX'!H68 -> 237.5 | I25: =+$D25+'06_Red_CAPEX'!I40+'06_Red_CAPEX'!I68 -> 237.5 | J25: =+$D25+'06_Red_CAPEX'!J40+'06_Red_CAPEX'!J68 -> 475 | K25: =+$D25+'06_Red_CAPEX'!K40+'06_Red_CAPEX'!K68 -> 475 | L25: =+$D25+'06_Red_CAPEX'!L40+'06_Red_CAPEX'!L68 -> 712.5 | ... P25: =+$D25+'06_Red_CAPEX'!P40+'06_Red_CAPEX'!P68 -> 1187.5 | Q25: =SUM(E25:P25) -> 6650
B26: ='06_Red_CAPEX'!B27 -> Hub/Dark Store | D26: =+E13 -> 855 | E26: =+$D26+'06_Red_CAPEX'!E41+'06_Red_CAPEX'!E69 -> 855 | F26: =+$D26+'06_Red_CAPEX'!F41+'06_Red_CAPEX'!F69 -> 855 | G26: =+$D26+'06_Red_CAPEX'!G41+'06_Red_CAPEX'!G69 -> 855 | H26: =+$D26+'06_Red_CAPEX'!H41+'06_Red_CAPEX'!H69 -> 855 | I26: =+$D26+'06_Red_CAPEX'!I41+'06_Red_CAPEX'!I69 -> 855 | J26: =+$D26+'06_Red_CAPEX'!J41+'06_Red_CAPEX'!J69 -> 1140 | K26: =+$D26+'06_Red_CAPEX'!K41+'06_Red_CAPEX'!K69 -> 1140 | L26: =+$D26+'06_Red_CAPEX'!L41+'06_Red_CAPEX'!L69 -> 1425 | ... P26: =+$D26+'06_Red_CAPEX'!P41+'06_Red_CAPEX'!P69 -> 1995 | Q26: =SUM(E26:P26) -> 14820
B27: Total | D27: =SUM(D18:D26) -> 28500 | E27: =SUM(E18:E26) -> 28500 | F27: =SUM(F18:F26) -> 28500 | G27: =SUM(G18:G26) -> 29046.25 | H27: =SUM(H18:H26) -> 28808.75 | I27: =SUM(I18:I26) -> 28571.25 | J27: =SUM(J18:J26) -> 28856.25 | K27: =SUM(K18:K26) -> 29283.75 | ... P27: =SUM(P18:P26) -> 31278.75 | Q27: =SUM(Q18:Q25) -> 338675
D30: Mes 0 | E30: Mes 1 | F30: Mes 2 | G30: Mes 3 | H30: Mes 4 | I30: Mes 5 | J30: Mes 6 | K30: Mes 7 | L30: Mes 8 | M30: Mes 9 | N30: Mes 10 | O30: Mes 11 | P30: Mes 12 | Q30: Total
B31: Gastos Personal | D31: =SUMPRODUCT(D19:D26,$Q$6:$Q$13)/D27 -> 0.1334 | E31: =SUMPRODUCT(E19:E26,$Q$6:$Q$13)/E27 -> 0.1334 | F31: =SUMPRODUCT(F19:F26,$Q$6:$Q$13)/F27 -> 0.1334 | G31: =SUMPRODUCT(G19:G26,$Q$6:$Q$13)/G27 -> 0.13325429 | H31: =SUMPRODUCT(H19:H26,$Q$6:$Q$13)/H27 -> 0.13311624 | I31: =SUMPRODUCT(I19:I26,$Q$6:$Q$13)/I27 -> 0.13297589 | J31: =SUMPRODUCT(J19:J26,$Q$6:$Q$13)/J27 -> 0.13223868 | K31: =SUMPRODUCT(K19:K26,$Q$6:$Q$13)/K27 -> 0.1320438 | ... P31: =SUMPRODUCT(P19:P26,$Q$6:$Q$13)/P27 -> 0.13025816
B32: Alquileres | D32: =SUMPRODUCT($R$6:$R$13,D19:D26)/D27 -> 0.035358333 | E32: =SUMPRODUCT($R$6:$R$13,E19:E26)/E27 -> 0.035358333 | F32: =SUMPRODUCT($R$6:$R$13,F19:F26)/F27 -> 0.035358333 | G32: =SUMPRODUCT($R$6:$R$13,G19:G26)/G27 -> 0.035310711 | H32: =SUMPRODUCT($R$6:$R$13,H19:H26)/H27 -> 0.035230833 | I32: =SUMPRODUCT($R$6:$R$13,I19:I26)/I27 -> 0.035149626 | J32: =SUMPRODUCT($R$6:$R$13,J19:J26)/J27 -> 0.034794239 | K32: =SUMPRODUCT($R$6:$R$13,K19:K26)/K27 -> 0.034716139 | ... P32: =SUMPRODUCT($R$6:$R$13,P19:P26)/P27 -> 0.033906606
B33: G&A/Otros | D33: =SUMPRODUCT($S$6:$S$13,D19:D26)/D27 -> 0.064675 | E33: =SUMPRODUCT($S$6:$S$13,E19:E26)/E27 -> 0.064675 | F33: =SUMPRODUCT($S$6:$S$13,F19:F26)/F27 -> 0.064675 | G33: =SUMPRODUCT($S$6:$S$13,G19:G26)/G27 -> 0.064640229 | H33: =SUMPRODUCT($S$6:$S$13,H19:H26)/H27 -> 0.064554823 | I33: =SUMPRODUCT($S$6:$S$13,I19:I26)/I27 -> 0.064467997 | J33: =SUMPRODUCT($S$6:$S$13,J19:J26)/J27 -> 0.063839506 | K33: =SUMPRODUCT($S$6:$S$13,K19:K26)/K27 -> 0.063775345 | ... P33: =SUMPRODUCT($S$6:$S$13,P19:P26)/P27 -> 0.062251329

Sheet 08_Core_Financiero
B2: Core Economico-Financiero - P&L mensual, Cashflow y Constraints
B4: Linea P&L / Caja | C4: Mes 1 | D4: Mes 2 | E4: Mes 3 | F4: Mes 4 | G4: Mes 5 | H4: Mes 6 | I4: Mes 7 | J4: Mes 8 | K4: Mes 9 | L4: Mes 10 | M4: Mes 11 | N4: Mes 12 | O4: Total | Q4: Mes 1 | R4: Mes 2 | S4: Mes 3 | T4: Mes 4 | U4: Mes 5 | V4: Mes 6 | W4: Mes 7 | X4: Mes 8 | Y4: Mes 9 | Z4: Mes 10 | AA4: Mes 11 | AB4: Mes 12 | AC4: Total
B5: Ventas netas | C5: ='01_Master_Variables'!D6 -> 29368.464 | D5: ='01_Master_Variables'!E6 -> 28959.999 | E5: ='01_Master_Variables'!F6 -> 29137.949 | F5: ='01_Master_Variables'!G6 -> 28569.856 | G5: ='01_Master_Variables'!H6 -> 28037.177 | H5: ='01_Master_Variables'!I6 -> 28060.276 | I5: ='01_Master_Variables'!J6 -> 28257.162 | J5: ='01_Master_Variables'!K6 -> 28340.977 | ... N5: ='01_Master_Variables'!O6 -> 29507.551 | O5: =SUM(C5:N5) -> 344699.21 | Q5: =+C5/C$5 -> 1 | R5: =+D5/D$5 -> 1 | S5: =+E5/E$5 -> 1 | T5: =+F5/F$5 -> 1 | U5: =+G5/G$5 -> 1 | V5: =+H5/H$5 -> 1 | W5: =+I5/I$5 -> 1 | X5: =+J5/J$5 -> 1 | ... AC5: =+O5/O$5 -> 1
B6: Costo de ventas | C6: =-C5*(1-'01_Master_Variables'!D7) -> -19332.935 | D6: =-D5*(1-'01_Master_Variables'!E7) -> -19064.047 | E6: =-E5*(1-'01_Master_Variables'!F7) -> -19181.19 | F6: =-F5*(1-'01_Master_Variables'!G7) -> -18807.22 | G6: =-G5*(1-'01_Master_Variables'!H7) -> -18456.564 | H6: =-H5*(1-'01_Master_Variables'!I7) -> -18471.77 | I6: =-I5*(1-'01_Master_Variables'!J7) -> -18601.377 | J6: =-J5*(1-'01_Master_Variables'!K7) -> -18656.552 | ... N6: =-N5*(1-'01_Master_Variables'!O7) -> -19424.495 | O6: =SUM(C6:N6) -> -226911.68 | Q6: =+C6/C$5 -> -0.65828894 | R6: =+D6/D$5 -> -0.65828894 | S6: =+E6/E$5 -> -0.65828894 | T6: =+F6/F$5 -> -0.65828894 | U6: =+G6/G$5 -> -0.65828894 | V6: =+H6/H$5 -> -0.65828894 | W6: =+I6/I$5 -> -0.65828894 | X6: =+J6/J$5 -> -0.65828894 | ... AC6: =+O6/O$5 -> -0.65828894
B7: Margen bruto | C7: =C5+C6 -> 10035.529 | D7: =D5+D6 -> 9895.9517 | E7: =E5+E6 -> 9956.7595 | F7: =F5+F6 -> 9762.6358 | G7: =G5+G6 -> 9580.6135 | H7: =H5+H6 -> 9588.5067 | I7: =I5+I6 -> 9655.7847 | J7: =J5+J6 -> 9684.4252 | ... N7: =N5+N6 -> 10083.057 | O7: =SUM(C7:N7) -> 117787.53 | Q7: =+C7/C$5 -> 0.34171106 | R7: =+D7/D$5 -> 0.34171106 | S7: =+E7/E$5 -> 0.34171106 | T7: =+F7/F$5 -> 0.34171106 | U7: =+G7/G$5 -> 0.34171106 | V7: =+H7/H$5 -> 0.34171106 | W7: =+I7/I$5 -> 0.34171106 | X7: =+J7/J$5 -> 0.34171106 | ... AC7: =+O7/O$5 -> 0.34171106
B8: Mermas y vencidos | C8: =-C5*'03_CatMan_DDI'!F18 -> -308.36887 | D8: =-D5*'03_CatMan_DDI'!F18 -> -304.07999 | E8: =-E5*'03_CatMan_DDI'!F18 -> -305.94847 | F8: =-F5*'03_CatMan_DDI'!F18 -> -299.98349 | G8: =-G5*'03_CatMan_DDI'!F18 -> -294.39036 | H8: =-H5*'03_CatMan_DDI'!F18 -> -294.6329 | I8: =-I5*'03_CatMan_DDI'!F18 -> -296.7002 | J8: =-J5*'03_CatMan_DDI'!F18 -> -297.58026 | K8: =-K5*'03_CatMan_DDI'!F18 -> -295.75862 | L8: =-L5*'03_CatMan_DDI'!F18 -> -306.67956 | M8: =-M5*'03_CatMan_DDI'!F18 -> -305.38972 | N8: =-N5*'03_CatMan_DDI'!F18 -> -309.82929 | O8: =SUM(C8:N8) -> -3619.3417 | Q8: =+C8/C$5 -> -0.0105 | R8: =+D8/D$5 -> -0.0105 | S8: =+E8/E$5 -> -0.0105 | T8: =+F8/F$5 -> -0.0105 | U8: =+G8/G$5 -> -0.0105 | V8: =+H8/H$5 -> -0.0105 | W8: =+I8/I$5 -> -0.0105 | X8: =+J8/J$5 -> -0.0105 | ... AC8: =+O8/O$5 -> -0.0105
B9: Margen final | C9: =C7+C8 -> 9727.16 | D9: =D7+D8 -> 9591.8718 | E9: =E7+E8 -> 9650.811 | F9: =F7+F8 -> 9462.6523 | G9: =G7+G8 -> 9286.2231 | H9: =H7+H8 -> 9293.8738 | I9: =I7+I8 -> 9359.0845 | J9: =J7+J8 -> 9386.8449 | ... N9: =N7+N8 -> 9773.2272 | O9: =SUM(C9:N9) -> 114168.19
B10: MG% | C10: =+C9/C5 -> 0.33121106 | D10: =+D9/D5 -> 0.33121106 | E10: =+E9/E5 -> 0.33121106 | F10: =+F9/F5 -> 0.33121106 | G10: =+G9/G5 -> 0.33121106 | H10: =+H9/H5 -> 0.33121106 | I10: =+I9/I5 -> 0.33121106 | J10: =+J9/J5 -> 0.33121106 | ... O10: =+O9/O5 -> 0.33121106 | Q10: =+C9/C$5 -> 0.33121106 | R10: =+D9/D$5 -> 0.33121106 | S10: =+E9/E$5 -> 0.33121106 | T10: =+F9/F$5 -> 0.33121106 | U10: =+G9/G$5 -> 0.33121106 | V10: =+H9/H$5 -> 0.33121106 | W10: =+I9/I$5 -> 0.33121106 | X10: =+J9/J$5 -> 0.33121106 | ... AC10: =+O9/O$5 -> 0.33121106
B12: Marketing | C12: =-'01_Master_Variables'!D13 -> -265.41118 | D12: =-'01_Master_Variables'!E13 -> -302.15039 | E12: =-'01_Master_Variables'!F13 -> -335.49743 | F12: =-'01_Master_Variables'!G13 -> -365.71247 | G12: =-'01_Master_Variables'!H13 -> -393.03734 | H12: =-'01_Master_Variables'!I13 -> -417.69673 | I12: =-'01_Master_Variables'!J13 -> -439.89941 | J12: =-'01_Master_Variables'!K13 -> -459.83924 | ... N12: =-'01_Master_Variables'!O13 -> -520.38041 | O12: =SUM(C12:N12) -> -4978.7755 | Q12: =+C12/C$5 -> -0.0090372852 | R12: =+D12/D$5 -> -0.01043337 | S12: =+E12/E$5 -> -0.011514106 | T12: =+F12/F$5 -> -0.012800641 | U12: =+G12/G$5 -> -0.014018435 | V12: =+H12/H$5 -> -0.014885696 | W12: =+I12/I$5 -> -0.015567714 | X12: =+J12/J$5 -> -0.016225243 | ... AC12: =+O12/O$5 -> -0.014443826
B13: Gastos logisticos | C13: =-'01_Master_Variables'!D10 -> -1020.6711 | D13: =-'01_Master_Variables'!E10 -> -1007.539 | E13: =-'01_Master_Variables'!F10 -> -1013.2601 | F13: =-'01_Master_Variables'!G10 -> -994.99588 | G13: =-'01_Master_Variables'!H10 -> -977.87025 | H13: =-'01_Master_Variables'!I10 -> -1015.1879 | I13: =-'01_Master_Variables'!J10 -> -1021.5178 | J13: =-'01_Master_Variables'!K10 -> -1060.7874 | ... N13: =-'01_Master_Variables'!O10 -> -1171.4428 | O13: =SUM(C13:N13) -> -12584.98 | Q13: =+C13/C$5 -> -0.034753984 | R13: =+D13/D$5 -> -0.034790711 | S13: =+E13/E$5 -> -0.034774584 | T13: =+F13/F$5 -> -0.034826772 | U13: =+G13/G$5 -> -0.034877628 | V13: =+H13/H$5 -> -0.036178827 | W13: =+I13/I$5 -> -0.036150756 | X13: =+J13/J$5 -> -0.037429458 | ... AC13: =+O13/O$5 -> -0.036510033
B14: Personal operaciones | C14: =-C5*'07_PL_TiposPDV'!E31 -> -3917.7531 | D14: =-D5*'07_PL_TiposPDV'!F31 -> -3863.2638 | E14: =-E5*'07_PL_TiposPDV'!G31 -> -3882.7568 | F14: =-F5*'07_PL_TiposPDV'!H31 -> -3803.1119 | G14: =-G5*'07_PL_TiposPDV'!I31 -> -3728.2687 | H14: =-H5*'07_PL_TiposPDV'!J31 -> -3710.654 | I14: =-I5*'07_PL_TiposPDV'!K31 -> -3731.1829 | J14: =-J5*'07_PL_TiposPDV'!L31 -> -3722.115 | ... N14: =-N5*'07_PL_TiposPDV'!P31 -> -3843.5994 | O14: =SUM(C14:N14) -> -45525.05 | Q14: =+C14/C$5 -> -0.1334 | R14: =+D14/D$5 -> -0.1334 | S14: =+E14/E$5 -> -0.13325429 | T14: =+F14/F$5 -> -0.13311624 | U14: =+G14/G$5 -> -0.13297589 | V14: =+H14/H$5 -> -0.13223868 | W14: =+I14/I$5 -> -0.1320438 | X14: =+J14/J$5 -> -0.13133333 | ... AC14: =+O14/O$5 -> -0.13207181
B15: Alquileres + expensas | C15: =-C5*'07_PL_TiposPDV'!E32 -> -1038.4199 | D15: =-D5*'07_PL_TiposPDV'!F32 -> -1023.9773 | E15: =-E5*'07_PL_TiposPDV'!G32 -> -1028.8817 | F15: =-F5*'07_PL_TiposPDV'!H32 -> -1006.5398 | G15: =-G5*'07_PL_TiposPDV'!I32 -> -985.49629 | H15: =-H5*'07_PL_TiposPDV'!J32 -> -976.33595 | I15: =-I5*'07_PL_TiposPDV'!K32 -> -980.97958 | J15: =-J5*'07_PL_TiposPDV'!L32 -> -974.1784 | ... N15: =-N5*'07_PL_TiposPDV'!P32 -> -1000.5009 | O15: =SUM(C15:N15) -> -11973.791 | Q15: =+C15/C$5 -> -0.035358333 | R15: =+D15/D$5 -> -0.035358333 | S15: =+E15/E$5 -> -0.035310711 | T15: =+F15/F$5 -> -0.035230833 | U15: =+G15/G$5 -> -0.035149626 | V15: =+H15/H$5 -> -0.034794239 | W15: =+I15/I$5 -> -0.034716139 | X15: =+J15/J$5 -> -0.034373494 | ... AC15: =+O15/O$5 -> -0.034736926
B16: G&A / Central | C16: =-C5*'07_PL_TiposPDV'!E33 -> -1899.4054 | D16: =-D5*'07_PL_TiposPDV'!F33 -> -1872.9879 | E16: =-E5*'07_PL_TiposPDV'!G33 -> -1883.4837 | F16: =-F5*'07_PL_TiposPDV'!H33 -> -1844.322 | G16: =-G5*'07_PL_TiposPDV'!I33 -> -1807.5006 | H16: =-H5*'07_PL_TiposPDV'!J33 -> -1791.3542 | I16: =-I5*'07_PL_TiposPDV'!K33 -> -1802.1103 | J16: =-J5*'07_PL_TiposPDV'!L33 -> -1790.262 | ... N16: =-N5*'07_PL_TiposPDV'!P33 -> -1836.8843 | O16: =SUM(C16:N16) -> -21963.824 | Q16: =+C16/C$5 -> -0.064675 | R16: =+D16/D$5 -> -0.064675 | S16: =+E16/E$5 -> -0.064640229 | T16: =+F16/F$5 -> -0.064554823 | U16: =+G16/G$5 -> -0.064467997 | V16: =+H16/H$5 -> -0.063839506 | W16: =+I16/I$5 -> -0.063775345 | X16: =+J16/J$5 -> -0.063168675 | ... AC16: =+O16/O$5 -> -0.063718811
B17: EBITDA operativo | C17: =SUM(C9:C16) -> 1585.8305 | D17: =SUM(D9:D16) -> 1522.2846 | E17: =SUM(E9:E16) -> 1507.2624 | F17: =SUM(F9:F16) -> 1448.3014 | G17: =SUM(G9:G16) -> 1394.3811 | H17: =SUM(H9:H16) -> 1382.9762 | I17: =SUM(I9:I16) -> 1383.7258 | J17: =SUM(J9:J16) -> 1379.9942 | ... N17: =SUM(N9:N16) -> 1400.7507 | O17: =SUM(C17:N17) -> 17145.745 | Q17: =+C17/C$5 -> 0.053997732 | R17: =+D17/D$5 -> 0.052565078 | S17: =+E17/E$5 -> 0.051728501 | T17: =+F17/F$5 -> 0.05069334 | U17: =+G17/G$5 -> 0.049733291 | V17: =+H17/H$5 -> 0.04928591 | W17: =+I17/I$5 -> 0.048969029 | X17: =+J17/J$5 -> 0.04869254 | ... AC17: =+O17/O$5 -> 0.049741178
B18: EBITDA ajustado Cost-to-Serve | C18: =C17 -> 1585.8305 | D18: =D17 -> 1522.2846 | E18: =E17 -> 1507.2624 | F18: =F17 -> 1448.3014 | G18: =G17 -> 1394.3811 | H18: =H17 -> 1382.9762 | I18: =I17 -> 1383.7258 | J18: =J17 -> 1379.9942 | ... N18: =N17 -> 1400.7507 | O18: =SUM(C18:N18) -> 17145.745
B19: EBITDA % | C19: =+C18/C5 -> 0.053997732 | D19: =+D18/D5 -> 0.052565078 | E19: =+E18/E5 -> 0.051728501 | F19: =+F18/F5 -> 0.05069334 | G19: =+G18/G5 -> 0.049733291 | H19: =+H18/H5 -> 0.04928591 | I19: =+I18/I5 -> 0.048969029 | J19: =+J18/J5 -> 0.04869254 | ... N19: =+N18/N5 -> 0.047470922
B21: Liberacion / absorcion WC | C21: ='01_Master_Variables'!D12 -> 5482.9781 | D21: ='01_Master_Variables'!E12 -> 0 | E21: ='01_Master_Variables'!F12 -> 0 | F21: ='01_Master_Variables'!G12 -> 0 | G21: ='01_Master_Variables'!H12 -> 0 | H21: ='01_Master_Variables'!I12 -> 0 | I21: ='01_Master_Variables'!J12 -> 0 | J21: ='01_Master_Variables'!K12 -> 0 | ... N21: ='01_Master_Variables'!O12 -> 0 | O21: =SUM(C21:N21) -> 5482.9781
B22: CAPEX | C22: =-'01_Master_Variables'!D14 -> 0 | D22: =-'01_Master_Variables'!E14 -> 0 | E22: =-'01_Master_Variables'!F14 -> -5833.3333 | F22: =-'01_Master_Variables'!G14 -> 0 | G22: =-'01_Master_Variables'!H14 -> 0 | H22: =-'01_Master_Variables'!I14 -> -4400 | I22: =-'01_Master_Variables'!J14 -> -5833.3333 | J22: =-'01_Master_Variables'!K14 -> -4400 | ... N22: =-'01_Master_Variables'!O14 -> -4400 | O22: =SUM(C22:N22) -> -35100
B23: Flujo de caja libre | C23: =C18+C21+C22 -> 7068.8085 | D23: =D18+D21+D22 -> 1522.2846 | E23: =E18+E21+E22 -> -4326.0709 | F23: =F18+F21+F22 -> 1448.3014 | G23: =G18+G21+G22 -> 1394.3811 | H23: =H18+H21+H22 -> -3017.0238 | I23: =I18+I21+I22 -> -4449.6075 | J23: =J18+J21+J22 -> -3020.0058 | ... N23: =N18+N21+N22 -> -2999.2493 | O23: =SUM(C23:N23) -> -12471.277
B24: Caja final | C24: ='00_General'!C12+C23 -> -17931.191 | D24: =C24+D23 -> -16408.907 | E24: =D24+E23 -> -20734.978 | F24: =E24+F23 -> -19286.676 | G24: =F24+G23 -> -17892.295 | H24: =G24+H23 -> -20909.319 | I24: =H24+I23 -> -25358.927 | J24: =I24+J23 -> -28378.932 | K24: =J24+K23 -> -27028.972 | ... N24: =M24+N23 -> -37471.277 | O24: =N24 -> -37471.277
B25: Alerta FCF negativo | C25: =IF(C23<0,"FCF negativo","OK") -> OK | D25: =IF(D23<0,"FCF negativo","OK") -> OK | E25: =IF(E23<0,"FCF negativo","OK") -> FCF negativo | F25: =IF(F23<0,"FCF negativo","OK") -> OK | G25: =IF(G23<0,"FCF negativo","OK") -> OK | H25: =IF(H23<0,"FCF negativo","OK") -> FCF negativo | I25: =IF(I23<0,"FCF negativo","OK") -> FCF negativo | J25: =IF(J23<0,"FCF negativo","OK") -> FCF negativo | ... N25: =IF(N23<0,"FCF negativo","OK") -> FCF negativo

Sheet 09_Dashboard
B3: Dashboard Ejecutivo - PharmaLink 360
B5: KPI | C5: Resultado | E5: Alertas
B6: EBITDA anual | C6: ='08_Core_Financiero'!O17 -> 17145.745 | E6: CAPEX > limite | G6: =IF(C9>'00_General'!C15,"ROJO","OK") -> OK
B7: FCF anual | C7: ='08_Core_Financiero'!O23 -> -12471.277 | E7: Caja final negativa | G7: =IF(C8<0,"ROJO","OK") -> ROJO
B8: Caja final | C8: ='08_Core_Financiero'!N24 -> -37471.277 | E8: Meses FCF negativo | G8: =COUNTIF('08_Core_Financiero'!C25:N25,"FCF negativo") -> 6
B9: CAPEX utilizado | C9: =-SUM('08_Core_Financiero'!C22:N22) -> 35100 | E9: Validacion cierres red | G9: =IF('06_Red_CAPEX'!F15/'06_Red_CAPEX'!D15>20%,"ROJO","OK") -> OK
B12: Mes | C12: Mes 1 | D12: Mes 2 | E12: Mes 3 | F12: Mes 4 | G12: Mes 5 | H12: Mes 6 | I12: Mes 7 | J12: Mes 8 | K12: Mes 9 | L12: Mes 10 | M12: Mes 11 | N12: Mes 12 | O12: TOTAL
B13: Ventas | C13: ='08_Core_Financiero'!C5 -> 29368.464 | D13: ='08_Core_Financiero'!D5 -> 28959.999 | E13: ='08_Core_Financiero'!E5 -> 29137.949 | F13: ='08_Core_Financiero'!F5 -> 28569.856 | G13: ='08_Core_Financiero'!G5 -> 28037.177 | H13: ='08_Core_Financiero'!H5 -> 28060.276 | I13: ='08_Core_Financiero'!I5 -> 28257.162 | J13: ='08_Core_Financiero'!J5 -> 28340.977 | ... N13: ='08_Core_Financiero'!N5 -> 29507.551 | O13: =SUM(C13:N13) -> 344699.21
B14: EBITDA | C14: ='08_Core_Financiero'!C17 -> 1585.8305 | D14: ='08_Core_Financiero'!D17 -> 1522.2846 | E14: ='08_Core_Financiero'!E17 -> 1507.2624 | F14: ='08_Core_Financiero'!F17 -> 1448.3014 | G14: ='08_Core_Financiero'!G17 -> 1394.3811 | H14: ='08_Core_Financiero'!H17 -> 1382.9762 | I14: ='08_Core_Financiero'!I17 -> 1383.7258 | J14: ='08_Core_Financiero'!J17 -> 1379.9942 | ... N14: ='08_Core_Financiero'!N17 -> 1400.7507 | O14: =SUM(C14:N14) -> 17145.745
B15: FCF | C15: ='08_Core_Financiero'!C23 -> 7068.8085 | D15: ='08_Core_Financiero'!D23 -> 1522.2846 | E15: ='08_Core_Financiero'!E23 -> -4326.0709 | F15: ='08_Core_Financiero'!F23 -> 1448.3014 | G15: ='08_Core_Financiero'!G23 -> 1394.3811 | H15: ='08_Core_Financiero'!H23 -> -3017.0238 | I15: ='08_Core_Financiero'!I23 -> -4449.6075 | J15: ='08_Core_Financiero'!J23 -> -3020.0058 | ... N15: ='08_Core_Financiero'!N23 -> -2999.2493 | O15: =SUM(C15:N15) -> -12471.277
B16: Caja Final | C16: ='08_Core_Financiero'!C24 -> -17931.191 | D16: ='08_Core_Financiero'!D24 -> -16408.907 | E16: ='08_Core_Financiero'!E24 -> -20734.978 | F16: ='08_Core_Financiero'!F24 -> -19286.676 | G16: ='08_Core_Financiero'!G24 -> -17892.295 | H16: ='08_Core_Financiero'!H24 -> -20909.319 | I16: ='08_Core_Financiero'!I24 -> -25358.927 | J16: ='08_Core_Financiero'!J24 -> -28378.932 | ... N16: ='08_Core_Financiero'!N24 -> -37471.277 | O16: =SUM(C16:N16) -> -301729.19
